Workbook

Sheet ReadMe_File

Sheet # Databases
A1: Database Screening | B1: # Studies Identified | C1: # 1st Filter | D1: # 2nd Filter duplicattion | E1: # Studies Pass Eligibility Assessment | F1: # Studies Included
A2: IEEE Xplore | B2: =COUNTIF('1 Identification'!$A$2:$A$428,$A2) -> 78 | C2: =COUNTIF('2 Screening'!$A$2:$A$173,$A2) -> 27 | D2: =COUNTIF('3 Eligibility'!$A$2:$A$142,$A2) -> 26 | E2: =COUNTIFS('3 Eligibility'!$T$2:$T$142,">=3.5", '3 Eligibility'!$A$2:$A$142,$A2) -> 13 | F2: =COUNTIF('4 Included'!$A$2:$A$52,$A2) -> 8
A3: Scopus | B3: =COUNTIF('1 Identification'!$A$2:$A$428,$A3) -> 150 | C3: =COUNTIF('2 Screening'!$A$2:$A$173,$A3) -> 44 | D3: =COUNTIF('3 Eligibility'!$A$2:$A$142,$A3) -> 25 | E3: =COUNTIFS('3 Eligibility'!$T$2:$T$142,">=3.5", '3 Eligibility'!$A$2:$A$142,$A3) -> 12 | F3: =COUNTIF('4 Included'!$A$2:$A$52,$A3) -> 20
A4: ScienceDirect | B4: =COUNTIF('1 Identification'!$A$2:$A$428,$A4) -> 36 | C4: =COUNTIF('2 Screening'!$A$2:$A$173,$A4) -> 21 | D4: =COUNTIF('3 Eligibility'!$A$2:$A$142,$A4) -> 21 | E4: =COUNTIFS('3 Eligibility'!$T$2:$T$142,">=3.5", '3 Eligibility'!$A$2:$A$142,$A4) -> 8 | F4: =COUNTIF('4 Included'!$A$2:$A$52,$A4) -> 10
A5: Web of Science | B5: =COUNTIF('1 Identification'!$A$2:$A$428,$A5) -> 163 | C5: =COUNTIF('2 Screening'!$A$2:$A$173,$A5) -> 80 | D5: =COUNTIF('3 Eligibility'!$A$2:$A$142,$A5) -> 68 | E5: =COUNTIFS('3 Eligibility'!$T$2:$T$142,">=3.5", '3 Eligibility'!$A$2:$A$142,$A5) -> 18 | F5: =COUNTIF('4 Included'!$A$2:$A$52,$A5) -> 13
A6: Total | B6: =SUM(B2:B5) -> 427 | C6: =SUM(C2:C5) -> 172 | D6: =SUM(D2:D5) -> 140 | E6: =SUM(E2:E5) -> 51 | F6: =SUM(F2:F5) -> 51

Sheet #Publisher
A1: Publisher | B1: # of papers identified
A2: IEEE | B2: =COUNTIF('4 Included'!$D$2:$E$52,$A2) -> 22
A3: Elsevier | B3: =COUNTIF('4 Included'!$D$2:$E$52,$A3) -> 11
A4: Springer | B4: =COUNTIF('4 Included'!$D$2:$E$52,$A4) -> 6
A5: MDPI | B5: =COUNTIF('4 Included'!$D$2:$E$52,$A5) -> 5
A6: SPIE | B6: =COUNTIF('4 Included'!$D$2:$E$52,$A6) -> 2
A7: CRC Press | B7: =COUNTIF('4 Included'!$D$2:$E$52,$A7) -> 1
A8: Wiley | B8: =COUNTIF('4 Included'!$D$2:$E$52,$A8) -> 1
A9: Maruzen | B9: =COUNTIF('4 Included'!$D$2:$E$52,$A9) -> 1
A10: PeerJ | B10: =COUNTIF('4 Included'!$D$2:$E$52,$A10) -> 1
A11: IIETA | B11: =COUNTIF('4 Included'!$D$2:$E$52,$A11) -> 1
A12: Total | B12: =SUM(B2:B11) -> 51

Sheet # Reference Type
A1: Reference Type | B1: # of papers
A2: Journal Article | B2: =COUNTIF('4 Included'!$D$2:$D$52,$A2) -> 27
A3: Conference Proceedings | B3: =COUNTIF('4 Included'!$D$2:$D$52,$A3) -> 23
A4: Book Section | B4: =COUNTIF('4 Included'!$D$2:$D$52,$A4) -> 1
A5: Total | B5: =SUM(B2:B4) -> 51

Sheet # Years
A1: Year | B1: # of papers identified | C1: # of papers included
A2: 2020 | B2: =COUNTIF('1 Identification'!$D$2:$D$428,$A2) -> 15 | C2: =COUNTIF('4 Included'!$C$2:$C$52,$A2) -> 3
A3: 2021 | B3: =COUNTIF('1 Identification'!$D$2:$D$428,$A3) -> 66 | C3: =COUNTIF('4 Included'!$C$2:$C$52,$A3) -> 10
A4: 2022 | B4: =COUNTIF('1 Identification'!$D$2:$D$428,$A4) -> 148 | C4: =COUNTIF('4 Included'!$C$2:$C$52,$A4) -> 15
A5: 2023 | B5: =COUNTIF('1 Identification'!$D$2:$D$428,$A5) -> 175 | C5: =COUNTIF('4 Included'!$C$2:$C$52,$A5) -> 20
A6: 2024 | B6: =COUNTIF('1 Identification'!$D$2:$D$428,$A6) -> 23 | C6: =COUNTIF('4 Included'!$C$2:$C$52,$A6) -> 3
A7: Total | B7: =SUM(B2:B6) -> 427 | C7: =SUM(C2:C6) -> 51

Sheet # E&QA
A1: Score | B1: # of papers
A2: 0 | B2: =COUNTIF('3 Eligibility'!$T$2:$T$142,$A2) -> 0
A3: 0.5 | B3: =COUNTIF('3 Eligibility'!$T$2:$T$142,$A3) -> 3
A4: 1 | B4: =COUNTIF('3 Eligibility'!$T$2:$T$142,$A4) -> 5
A5: 1.5 | B5: =COUNTIF('3 Eligibility'!$T$2:$T$142,$A5) -> 38
A6: 2 | B6: =COUNTIF('3 Eligibility'!$T$2:$T$142,$A6) -> 28
A7: 2.5 | B7: =COUNTIF('3 Eligibility'!$T$2:$T$142,$A7) -> 10
A8: 3 | B8: =COUNTIF('3 Eligibility'!$T$2:$T$142,$A8) -> 5
A9: 3.5 | B9: =COUNTIF('3 Eligibility'!$T$2:$T$142,$A9) -> 15
A10: 4 | B10: =COUNTIF('3 Eligibility'!$T$2:$T$142,$A10) -> 37
A11: Total | B11: =SUM(B2:B10) -> 141

Sheet Techniques
A1: Parent | B1: Child | C1: #Parent | D1: #Child
A2: |AlexNet| | B2: |AlexNet| | C2: =D2 -> 2 | D2: {=SUMPRODUCT(--(ISNUMBER(SEARCH($B2,'4 Included'!$P$2:$P$52))))} -> 2
A3: |CHS-Net| | B3: |CHS-Net| | C3: =D3 -> 1 | D3: {=SUMPRODUCT(--(ISNUMBER(SEARCH($B3,'4 Included'!$P$2:$P$52))))} -> 1
A4: |CNN| | B4: |CNN| | C4: =D4 -> 23 | D4: {=SUMPRODUCT(--(ISNUMBER(SEARCH($B4,'4 Included'!$P$2:$P$52))))} -> 23
A5: |DCNN| | B5: |DCNN| | C5: =D5 -> 1 | D5: {=SUMPRODUCT(--(ISNUMBER(SEARCH($B5,'4 Included'!$P$2:$P$52))))} -> 1
A6: |DenseNet| | B6: |DenseNet| | C6: =SUM(D6:D9) -> 11 | D6: {=SUMPRODUCT(--(ISNUMBER(SEARCH($B6,'4 Included'!$P$2:$P$52))))} -> 1
B7: |DenseNet-121| | D7: {=SUMPRODUCT(--(ISNUMBER(SEARCH($B7,'4 Included'!$P$2:$P$52))))} -> 5
B8: |DenseNet-169| | D8: {=SUMPRODUCT(--(ISNUMBER(SEARCH($B8,'4 Included'!$P$2:$P$52))))} -> 3
B9: |DenseNet-201| | D9: {=SUMPRODUCT(--(ISNUMBER(SEARCH($B9,'4 Included'!$P$2:$P$52))))} -> 2
A10: |DINO| | B10: |DINO-v2| | C10: =D10 -> 1 | D10: {=SUMPRODUCT(--(ISNUMBER(SEARCH($B10,'4 Included'!$P$2:$P$52))))} -> 1
A11: |DLMs| | B11: |DLMs| | C11: =D11 -> 1 | D11: {=SUMPRODUCT(--(ISNUMBER(SEARCH($B11,'4 Included'!$P$2:$P$52))))} -> 1
A12: |DNN| | B12: |DNN| | C12: =D12 -> 1 | D12: {=SUMPRODUCT(--(ISNUMBER(SEARCH($B12,'4 Included'!$P$2:$P$52))))} -> 1
A13: |EfficientNet| | B13: |EfficientNet| | C13: =SUM(D13:D18) -> 10 | D13: {=SUMPRODUCT(--(ISNUMBER(SEARCH($B13,'4 Included'!$P$2:$P$52))))} -> 2
B14: |EfficientNet-B3| | D14: {=SUMPRODUCT(--(ISNUMBER(SEARCH($B14,'4 Included'!$P$2:$P$52))))} -> 2
B15: |EfficientNet-B4| | D15: {=SUMPRODUCT(--(ISNUMBER(SEARCH($B15,'4 Included'!$P$2:$P$52))))} -> 1
B16: |EfficientNet-B5| | D16: {=SUMPRODUCT(--(ISNUMBER(SEARCH($B16,'4 Included'!$P$2:$P$52))))} -> 1
B17: |EfficientNet-B7| | D17: {=SUMPRODUCT(--(ISNUMBER(SEARCH($B17,'4 Included'!$P$2:$P$52))))} -> 2
B18: |EfficientNet-v2| | D18: {=SUMPRODUCT(--(ISNUMBER(SEARCH($B18,'4 Included'!$P$2:$P$52))))} -> 2
A19: |EXP-Net| | B19: |EXP-Net| | C19: =D19 -> 1 | D19: {=SUMPRODUCT(--(ISNUMBER(SEARCH($B19,'4 Included'!$P$2:$P$52))))} -> 1
A20: |GINet| | B20: |GINet| | C20: =D20 -> 1 | D20: {=SUMPRODUCT(--(ISNUMBER(SEARCH($B20,'4 Included'!$P$2:$P$52))))} -> 1
A21: |GLDCNet| | B21: |GLDCNet| | C21: =D21 -> 1 | D21: {=SUMPRODUCT(--(ISNUMBER(SEARCH($B21,'4 Included'!$P$2:$P$52))))} -> 1
A22: |GoogLeNet| | B22: |GoogLeNet| | C22: =D22 -> 1 | D22: {=SUMPRODUCT(--(ISNUMBER(SEARCH($B22,'4 Included'!$P$2:$P$52))))} -> 1
A23: |HighRes3DNet| | B23: |HighRes3DNet| | C23: =D23 -> 1 | D23: {=SUMPRODUCT(--(ISNUMBER(SEARCH($B23,'4 Included'!$P$2:$P$52))))} -> 1
A24: |Inception| | B24: |Inception| | C24: =SUM(D24:D26) -> 7 | D24: {=SUMPRODUCT(--(ISNUMBER(SEARCH($B24,'4 Included'!$P$2:$P$52))))} -> 1
B25: |Inception-v2| | D25: {=SUMPRODUCT(--(ISNUMBER(SEARCH($B25,'4 Included'!$P$2:$P$52))))} -> 1
B26: |Inception-v3| | D26: {=SUMPRODUCT(--(ISNUMBER(SEARCH($B26,'4 Included'!$P$2:$P$52))))} -> 5
A27: |LightGBM| | B27: |LightGBM| | C27: =D27 -> 1 | D27: {=SUMPRODUCT(--(ISNUMBER(SEARCH($B27,'4 Included'!$P$2:$P$52))))} -> 1
A28: |Mask R CNN| | B28: |Mask R CNN| | C28: =D28 -> 2 | D28: {=SUMPRODUCT(--(ISNUMBER(SEARCH($B28,'4 Included'!$P$2:$P$52))))} -> 2
A29: |MobileNet| | B29: |MobileNet| | C29: =SUM(D29:D31) -> 6 | D29: {=SUMPRODUCT(--(ISNUMBER(SEARCH($B29,'4 Included'!$P$2:$P$52))))} -> 2
B30: |MobileNet-v2| | D30: {=SUMPRODUCT(--(ISNUMBER(SEARCH($B30,'4 Included'!$P$2:$P$52))))} -> 2
B31: |MobileNet-v3| | D31: {=SUMPRODUCT(--(ISNUMBER(SEARCH($B31,'4 Included'!$P$2:$P$52))))} -> 2
A32: |Mosquito Net| | B32: |Mosquito Net| | C32: =D32 -> 1 | D32: {=SUMPRODUCT(--(ISNUMBER(SEARCH($B32,'4 Included'!$P$2:$P$52))))} -> 1
A33: |PReLU-Net| | B33: |PReLU-Net| | C33: =D33 -> 1 | D33: {=SUMPRODUCT(--(ISNUMBER(SEARCH($B33,'4 Included'!$P$2:$P$52))))} -> 1
A34: |Res2Net| | B34: |Res2Net| | C34: =D34 -> 1 | D34: {=SUMPRODUCT(--(ISNUMBER(SEARCH($B34,'4 Included'!$P$2:$P$52))))} -> 1
A35: |ResNet| | B35: |ResNet| | C35: =SUM(D35:D41) -> 19 | D35: {=SUMPRODUCT(--(ISNUMBER(SEARCH($B35,'4 Included'!$P$2:$P$52))))} -> 2
B36: |ResNet-101| | D36: {=SUMPRODUCT(--(ISNUMBER(SEARCH($B36,'4 Included'!$P$2:$P$52))))} -> 3
B37: |ResNet-152v2| | D37: {=SUMPRODUCT(--(ISNUMBER(SEARCH($B37,'4 Included'!$P$2:$P$52))))} -> 1
B38: |ResNet-18| | D38: {=SUMPRODUCT(--(ISNUMBER(SEARCH($B38,'4 Included'!$P$2:$P$52))))} -> 1
B39: |ResNet-32| | D39: {=SUMPRODUCT(--(ISNUMBER(SEARCH($B39,'4 Included'!$P$2:$P$52))))} -> 1
B40: |ResNet-34| | D40: {=SUMPRODUCT(--(ISNUMBER(SEARCH($B40,'4 Included'!$P$2:$P$52))))} -> 1
B41: |ResNet-50| | D41: {=SUMPRODUCT(--(ISNUMBER(SEARCH($B41,'4 Included'!$P$2:$P$52))))} -> 10
A42: |SqueezeNET| | B42: |SqueezeNET| | C42: =D42 -> 2 | D42: {=SUMPRODUCT(--(ISNUMBER(SEARCH($B42,'4 Included'!$P$2:$P$52))))} -> 2
A43: |Swin Transformer| | B43: |Swin Transformer| | C43: =D43 -> 1 | D43: {=SUMPRODUCT(--(ISNUMBER(SEARCH($B43,'4 Included'!$P$2:$P$52))))} -> 1
A44: |VGG| | B44: |VGG| | C44: =SUM(D44:D46) -> 18 | D44: {=SUMPRODUCT(--(ISNUMBER(SEARCH($B44,'4 Included'!$P$2:$P$52))))} -> 2
B45: |VGG16| | D45: {=SUMPRODUCT(--(ISNUMBER(SEARCH($B45,'4 Included'!$P$2:$P$52))))} -> 12
B46: |VGG19| | D46: {=SUMPRODUCT(--(ISNUMBER(SEARCH($B46,'4 Included'!$P$2:$P$52))))} -> 4
A47: |Vision Transformer| | B47: |Vision Transformer| | C47: =D47 -> 1 | D47: {=SUMPRODUCT(--(ISNUMBER(SEARCH($B47,'4 Included'!$P$2:$P$52))))} -> 1
A48: |WCENet| | B48: |WCENet| | C48: =D48 -> 1 | D48: {=SUMPRODUCT(--(ISNUMBER(SEARCH($B48,'4 Included'!$P$2:$P$52))))} -> 1
A49: |Xception| | B49: |Xception| | C49: =D49 -> 2 | D49: {=SUMPRODUCT(--(ISNUMBER(SEARCH($B49,'4 Included'!$P$2:$P$52))))} -> 2
A50: |YOLO| | B50: |YOLO| | C50: =D50 -> 1 | D50: {=SUMPRODUCT(--(ISNUMBER(SEARCH($B50,'4 Included'!$P$2:$P$52))))} -> 1
B51: Total | C51: =SUBTOTAL(109,Techniques!$C$2:$C$50) -> 120 | D51: =SUBTOTAL(109,Techniques!$D$2:$D$50) -> 120

Sheet Variations
A1: Short name | B1: # of papers
A2: |Grad-CAM| | B2: {=SUMPRODUCT(--(ISNUMBER(SEARCH($A2,'4 Included'!$Q$2:$Q$52))))} -> 38
A3: |Grad-CAM++| | B3: {=SUMPRODUCT(--(ISNUMBER(SEARCH($A3,'4 Included'!$Q$2:$Q$52))))} -> 9
A4: |Guided Grad-CAM| | B4: {=SUMPRODUCT(--(ISNUMBER(SEARCH($A4,'4 Included'!$Q$2:$Q$52))))} -> 3
A5: |LIME| | B5: {=SUMPRODUCT(--(ISNUMBER(SEARCH($A5,'4 Included'!$Q$2:$Q$52))))} -> 3
A6: |Ablation-CAM| | B6: {=SUMPRODUCT(--(ISNUMBER(SEARCH($A6,'4 Included'!$Q$2:$Q$52))))} -> 1
A7: |CAM| | B7: {=SUMPRODUCT(--(ISNUMBER(SEARCH($A7,'4 Included'!$Q$2:$Q$52))))} -> 1
A8: |DGXAINet| | B8: {=SUMPRODUCT(--(ISNUMBER(SEARCH($A8,'4 Included'!$Q$2:$Q$52))))} -> 1
A9: |EigenGrad-CAM| | B9: {=SUMPRODUCT(--(ISNUMBER(SEARCH($A9,'4 Included'!$Q$2:$Q$52))))} -> 1
A10: |FEM| | B10: {=SUMPRODUCT(--(ISNUMBER(SEARCH($A10,'4 Included'!$Q$2:$Q$52))))} -> 1
A11: |Grad-CAM-based RFS (GRFS)| | B11: {=SUMPRODUCT(--(ISNUMBER(SEARCH($A11,'4 Included'!$Q$2:$Q$52))))} -> 1
A12: |HayCAM| | B12: {=SUMPRODUCT(--(ISNUMBER(SEARCH($A12,'4 Included'!$Q$2:$Q$52))))} -> 1
A13: |LayersCAM| | B13: {=SUMPRODUCT(--(ISNUMBER(SEARCH($A13,'4 Included'!$Q$2:$Q$52))))} -> 1
... A21: |TS-CNN| | B21: {=SUMPRODUCT(--(ISNUMBER(SEARCH($A21,'4 Included'!$Q$2:$Q$52))))} -> 1

Sheet Metrics
A1: Short name | B1: # of papers
A2: Accuracy | B2: {=SUMPRODUCT(--(ISNUMBER(SEARCH($A2,'4 Included'!$R$2:$R$52))))} -> 42
A3: F1-Score | B3: {=SUMPRODUCT(--(ISNUMBER(SEARCH($A3,'4 Included'!$R$2:$R$52))))} -> 18
A4: Precision | B4: {=SUMPRODUCT(--(ISNUMBER(SEARCH($A4,'4 Included'!$R$2:$R$52))))} -> 17
A5: Recall | B5: {=SUMPRODUCT(--(ISNUMBER(SEARCH($A5,'4 Included'!$R$2:$R$52))))} -> 14
A6: AUC | B6: {=SUMPRODUCT(--(ISNUMBER(SEARCH($A6,'4 Included'!$R$2:$R$52))))} -> 11
A7: Specificity | B7: {=SUMPRODUCT(--(ISNUMBER(SEARCH($A7,'4 Included'!$R$2:$R$52))))} -> 9
A8: Sensitivity | B8: {=SUMPRODUCT(--(ISNUMBER(SEARCH($A8,'4 Included'!$R$2:$R$52))))} -> 8
A9: Loss | B9: {=SUMPRODUCT(--(ISNUMBER(SEARCH($A9,'4 Included'!$R$2:$R$52))))} -> 5
A10: Training Loss | B10: {=SUMPRODUCT(--(ISNUMBER(SEARCH($A10,'4 Included'!$R$2:$R$52))))} -> 4
A11: Cohen's Kappa | B11: {=SUMPRODUCT(--(ISNUMBER(SEARCH($A11,'4 Included'!$R$2:$R$52))))} -> 3
A12: MCC | B12: {=SUMPRODUCT(--(ISNUMBER(SEARCH($A12,'4 Included'!$R$2:$R$52))))} -> 2
A13: BA | B13: {=SUMPRODUCT(--(ISNUMBER(SEARCH($A13,'4 Included'!$R$2:$R$52))))} -> 1
... A23: Training time | B23: {=SUMPRODUCT(--(ISNUMBER(SEARCH($A23,'4 Included'!$R$2:$R$52))))} -> 1

Sheet 4 Included
A1: Database | B1: Author Name | C1: Year | D1: Type | E1: Publisher | F1: Published in | G1: Link | H1: Publication date | I1: Title | J1: DOI | K1: Paper ID | L1: Column1 | M1: Title | N1: Dataset | O1: Dataset Link | P1: Techniques | Q1: variations | R1: Metrics
A2: Scopus | B2: G. Mettivier; R. Ricciardi; A. Sarno; F. S. Maddaloni; M. Porzio; M. Staffa; S. Minelli; A. Santoro; E. Antignani; M. Masi; V. Landoni; P. Ordonez; F. Ferranti; L. Greco; S. Clemente; P. Russo | C2: 2022 | D2: Conference Proceedings | E2: SPIE | F2: 16th International Workshop on Breast Imaging (IWBI2022 | G2: https://www.scopus.com/inward/record.uri?eid=2-s2.0-85136130200&doi=10.1117%2f12.2625369&partnerID=40&md5=530e4632c3249279cb1b8bb57b46b5c2 | I2: DeepLook: A deep learning computed diagnosis support for breast tomosynthesis | J2: 10.1117/12.2625369 | M2: DeepLook: A deep learning computed diagnosis support for breast tomosynthesis | N2: Tomosynthesis datasets | O2: Private Dataset | P2: |DCNN| | Q2: |Grad-CAM| | R2: AUC, Accuracy, Precision, Sensitivity, Specificity, F1-Score, false positive rate | S2: .
A3: Web of Science | B3: R. R. Selvaraju; M. Cogswell; A. Das; R. Vedantam; D. Parikh; D. Batra | C3: 2020 | D3: Conference Proceedings | E3: IEEE | F3: 2017 IEEE International Conference on Computer Vision (ICCV) | G3: https://openaccess.thecvf.com/content_iccv_2017/html/Selvaraju_Grad-CAM_Visual_Explanations_ICCV_2017_paper.html | H3: 2020 FEB | I3: Grad-CAM: Visual Explanations from Deep Networks via Gradient-Based Localization | J3: 10.1007/s11263-019-01228-7 | K3: WOS:000511807100003 | M3: Grad-CAM: Visual Explanations from Deep Networks via Gradient-Based Localization | N3: Dataset bias | O3: https://github.com/ramprs/grad-cam/ | P3: |CNN|, |AlexNet|, |VGG|, |ResNet| | Q3: |Grad-CAM| | R3: Accuracy
A4: Scopus | B4: A. Schottl | C4: 2020 | D4: Conference Proceedings | E4: IEEE | F4: 2020 10th International Conference on Advanced Computer Information Technologies (ACIT) | G4: https://www.scopus.com/inward/record.uri?eid=2-s2.0-85094097648&doi=10.1109%2fACIT49673.2020.9208950&partnerID=40&md5=be4fbb5d5fc2235731ce20492f77e6cb | I4: A Light-weight Method to Foster the (Grad)CAM Interpretability and Explainability of Classification Networks | J4: 10.1109/ACIT49673.2020.9208950 | M4: A Light-weight Method to Foster the (Grad)CAM Interpretability and Explainability of Classification Networks | N4: PASCAL VOC 2012 datase | O4: https://paperswithcode.com/dataset/pascal-voc | P4: |ResNet-50| | Q4: |Grad-CAM| | R4: Accuracy
A5: Scopus | B5: E. Ennadifi; S. Laraba; D. Vincke; B. Mercatoris; B. Gosselin | C5: 2020 | D5: Conference Proceedings | E5: IEEE | F5: 2020 International Conference on Intelligent Systems and Computer Vision, ISCV 2020 | G5: https://www.scopus.com/inward/record.uri?eid=2-s2.0-85093829351&doi=10.1109%2fISCV49265.2020.9204258&partnerID=40&md5=69751b3ad91ceba11c9f2f6fe9420273 | I5: Wheat Diseases Classification and Localization Using Convolutional Neural Networks and Grad-CAM Visualization | J5: 10.1109/ISCV49265.2020.9204258 | M5: Wheat Diseases Classification and Localization Using Convolutional Neural Networks and Grad-CAM Visualization | N5: Proposed dataset | O5: Private Dataset | P5: |CNN|, |Mask R CNN|, |DenseNet-121| | Q5: |Grad-CAM| | R5: Accuracy, Training time | S5: .
A6: Scopus | B6: S. Kusunose; Y. Shinomiya; T. Ushiwaka; N. Maeda; Y. Hoshino | C6: 2021 | D6: Conference Proceedings | E6: IEEE | F6: 2021 5th IEEE International Conference on Cybernetics, CYBCONF 2021 | G6: https://www.scopus.com/inward/record.uri?eid=2-s2.0-85113749231&doi=10.1109%2fCYBCONF51991.2021.9464134&partnerID=40&md5=7489d6d47de8e9b798c8ca31d548912b | I6: Improving Individually Selectness for Immune Cells using Grad-CAM | J6: 10.1109/CYBCONF51991.2021.9464134 | M6: Improving Individually Selectness for Immune Cells using Grad-CAM | N6: N/A | O6: No detail provided | P6: |CNN|, |ResNet-32| | Q6: |Grad-CAM-based RFS (GRFS)| | R6: Accuracy, Precision, Recall
A7: IEEE Xplore | B7: V. K. Prasad; K. M. N. Raj; S. Muthya; R. S. Nair | C7: 2021 | D7: Conference Proceedings | E7: IEEE | F7: 2021 IEEE 9th International Conference on Healthcare Informatics (ICHI) | G7: https://ieeexplore.ieee.org/abstract/document/9565704 | H7: 9-12 Aug. 2021 | I7: Development and validation of ECG rhythm classification on a multitude of data sources using Deep Learning | J7: 10.1109/ICHI52183.2021.00026 | M7: Development and validation of ECG rhythm classification on a multitude of data sources using Deep Learning | N7: MIT-BIH ARRHYTHMIA DATASET | O7: Signal dataset | P7: |CNN|, |EfficientNet-B3| | Q7: |Grad-CAM| | R7: Specificity, Sensitivity, F1-Score, AUC
A8: Scopus | B8: M. I. Patel; S. Singla; R. A. Ali Mattathodi; S. Sharma; D. Gautam; S. R. Kundeti | C8: 2021 | D8: Conference Proceedings | E8: IEEE | F8: 2021 IEEE International Conference on Cloud Computing in Emerging Markets (CCEM) | G8: https://www.scopus.com/inward/record.uri?eid=2-s2.0-85128330243&doi=10.1109%2fCCEM53267.2021.00011&partnerID=40&md5=20beb7cb25babda5e8c0dc6a4857db72 | I8: Simulating Realistic MRI variations to Improve Deep Learning model and visual explanations using Grad-CAM | J8: 10.1109/CCEM53267.2021.00011 | M8: Simulating Realistic MRI variations to Improve Deep Learning model and visual explanations using Grad-CAM | N8: OASIS-3 dataset | O8: https://www.oasis-brains.org/ | P8: |HighRes3DNet| | Q8: |Grad-CAM| | R8: MSE Loss
A9: Scopus | B9: X. Cai; Z. Qiao; Y. Gan; J. Wu; M. Wu; H. Dong | C9: 2022 | D9: Conference Proceedings | E9: IEEE | F9: 2022 2nd International Conference on Computer Graphics, Image and Virtualization (ICCGIV) | G9: https://www.scopus.com/inward/record.uri?eid=2-s2.0-85150681687&doi=10.1109%2fICCGIV57403.2022.00024&partnerID=40&md5=7b20826697f96b5bdd0d1e8fb75ed456 | I9: Sound Event Detection on Grad­CAM method with Complex Pretrained Model | J9: 10.1109/ICCGIV57403.2022.00024 | M9: Sound Event Detection on Grad­CAM method with Complex Pretrained Model | N9: DCASE2022task4 dataset | O9: https://dcase.community/challenge2022/index | P9: |CNN| | Q9: |Grad-CAM| | R9: PSDS2
A10: IEEE Xplore | B10: J. Maximino; M. Coimbra; J. Pedrosa | C10: 2022 | D10: Conference Proceedings | E10: IEEE | F10: 2022 44th Annual International Conference of the IEEE Engineering in Medicine & Biology Society (EMBC) | G10: https://ieeexplore.ieee.org/abstract/document/9871235 | H10: 11-15 July 2022 | I10: Detection of COVID-19 in Point of Care Lung Ultrasound | J10: 10.1109/EMBC48229.2022.9871235 | M10: Detection of COVID-19 in Point of Care Lung Ultrasound | N10: POCOVID | O10: https://github.com/jannisborn/covid19_ultrasound | P10: |VGG16|, |ResNet-50|, |DenseNet-169|, |MobileNet-v2| | Q10: |Grad-CAM| | R10: Accuracy | S10: .
A11: IEEE Xplore | B11: H. Nasiri; G. Kheyroddin; M. Dorrigiv; M. Esmaeili; A. R. Nafchi; M. H. Ghorbani; P. Zarkesh-Ha | C11: 2022 | D11: Conference Proceedings | E11: IEEE | F11: 2022 IEEE World AI IoT Congress (AIIoT) | G11: https://ieeexplore.ieee.org/abstract/document/9817375 | H11: 6-9 June 2022 | I11: Classification of COVID-19 in Chest X-ray Images Using Fusion of Deep Features and LightGBM | J11: 10.1109/AIIoT54504.2022.9817375 | M11: Classification of COVID-19 in Chest X-ray Images Using Fusion of Deep Features and LightGBM | N11: ChestX-ray8 dataset | O11: https://openaccess.thecvf.com/content_cvpr_2017/html/Wang_ChestX-ray8_Hospital-Scale_Chest_CVPR_2017_paper.html | P11: |LightGBM|, |DenseNet-169|, |MobileNet| | Q11: |Grad-CAM| | R11: Sensitivity, Specificity, Precision, F1-Score, Accuracy
A12: Scopus | B12: H. E. Mohamadi; M. E. Hassouni | C12: 2023 | D12: Conference Proceedings | E12: IEEE | F12: 2023 10th International Conference on Wireless Networks and Mobile Communications (WINCOM) | G12: https://www.scopus.com/inward/record.uri?eid=2-s2.0-85179508570&doi=10.1109%2fWINCOM59760.2023.10322952&partnerID=40&md5=4c797ab7f52568c378255bb9a4450a6a | I12: Enhanced Deep Learning Explainability for COVID-19 Diagnosis from Chest X-ray Images by Fusing Texture and Shape Features | J12: 10.1109/WINCOM59760.2023.10322952 | M12: Enhanced Deep Learning Explainability for COVID-19 Diagnosis from Chest X-ray Images by Fusing Texture and Shape Features | N12: CXR images | O12: Private Dataset | P12: |CNN|, |VGG16|, |ResNet-50| | Q12: |FEM|, |Grad-CAM| | R12: Precision, Recall, F-Score, Accuracy, Training Loss
A13: IEEE Xplore | B13: R. H. Rifat; A. C. Shruti; M. Kamal; M. G. R. Alam | C13: 2023 | D13: Conference Proceedings | E13: IEEE | F13: 2023 26th International Conference on Computer and Information Technology (ICCIT) | G13: https://ieeexplore.ieee.org/abstract/document/10441001 | H13: 13-15 Dec. 2023 | I13: Privacy-Preserving Knee Osteoarthritis Classification: A Federated Learning Approach with Grad-CAM Visualization | J13: 10.1109/ICCIT60459.2023.10441001 | M13: Privacy-Preserving Knee Osteoarthritis Classification: A Federated Learning Approach with Grad-CAM Visualization | N13: Knee osteoarthritis severity grading dataset | O13: https://www.ncbi.nlm.nih.gov/pmc/articles/PMC9410095/ | P13: |DenseNet-169|, |Inception-v2|, |MobileNet-v2| | Q13: |Grad-CAM| | R13: Accuracy, Precision, Recall, F1-Score | S13: .
A14: Scopus | B14: R. Golash; U. Gupta; V. Vats; K. Sharma; K. Golash | C14: 2023 | D14: Conference Proceedings | E14: IEEE | F14: 2023 2nd International Conference on Smart Technologies for Smart Nation, SmartTechCon 2023 | G14: https://www.scopus.com/inward/record.uri?eid=2-s2.0-85184810534&doi=10.1109%2fSmartTechCon57526.2023.10391741&partnerID=40&md5=606cb96e6cc031b37632ae99b103c05f | I14: Unveiling the Opacity: Exploring Rationality and Explainability in Tomato Disease Classification | J14: 10.1109/SmartTechCon57526.2023.10391741 | M14: Unveiling the Opacity: Exploring Rationality and Explainability in Tomato Disease Classification | N14: PlantVillage dataset | O14: https://plantvillage.psu.edu/ | P14: |ResNet-101|, |EfficientNet-B7|, |Vision Transformer| | Q14: |Guided Grad-CAM| | R14: Accuracy, Training Loss
A15: IEEE Xplore | B15: W. Tan; J. Renkhoff; A. Velasquez; Z. Wang; L. Li; J. Wang; S. Niu; F. Yang; Y. Liu; H. Song | C15: 2023 | D15: Conference Proceedings | E15: IEEE | F15: 2023 IEEE International Conference on Fuzzy Systems (FUZZ) | G15: https://ieeexplore.ieee.org/abstract/document/10309766 | H15: 45239 | I15: NoiseCAM: Explainable AI for the Boundary Between Noise and Adversarial Attacks | M15: NoiseCAM: Explainable AI for the Boundary Between Noise and Adversarial Attacks | N15: ImageNet2012 dataset | O15: https://www.tensorflow.org/datasets/catalog/imagenet2012 | P15: |VGG16| | Q15: |Grad-CAM|, |NoiseCAM| | R15: Accuracy | S15: .
A16: IEEE Xplore | B16: P. V. R; U. Shanmugam | C16: 2023 | D16: Conference Proceedings | E16: IEEE | F16: 2023 Innovations in Power and Advanced Computing Technologies (i-PACT) | G16: https://ieeexplore.ieee.org/abstract/document/10434658 | H16: 8-10 Dec. 2023 | I16: Explainable AI for Medical Imaging: Advancing Transparency and Trust in Diagnostic Decision-Making | J16: 10.1109/i-PACT58649.2023.10434658 | M16: Explainable AI for Medical Imaging: Advancing Transparency and Trust in Diagnostic Decision-Making | N16: X-ray, MRI, and CT scans | O16: Private Dataset | P16: |CNN| | Q16: |Grad-CAM++| | R16: Accuracy, Precision, Recall, F1-Score | S16: .
A17: Scopus | B17: K. Jitha; P. Mohammed Waleed; K. Navas; C. M. Nihad Ahmed; C. P. Najiya Nasrin | C17: 2023 | D17: Conference Proceedings | E17: IEEE | F17: 2023 International Conference on Innovations in Engineering and Technology (ICIET) | G17: https://www.scopus.com/inward/record.uri?eid=2-s2.0-85171524411&doi=10.1109%2fICIET57285.2023.10220839&partnerID=40&md5=646ec919f0f808164e3f078f5967a741 | I17: Deep Learning and Grad-CAM for the Diagnosis of Pneumonia Based on X-Rays | J17: 10.1109/ICIET57285.2023.10220839 | M17: Deep Learning and Grad-CAM for the Diagnosis of Pneumonia Based on X-Rays | N17: Pneumonia dataset | O17: Private Dataset | P17: |CNN| | Q17: |Grad-CAM| | R17: Accuracy, Training Loss
A18: IEEE Xplore | B18: U. Rashmi; B. M. Beena; S. Ambesange | C18: 2023 | D18: Conference Proceedings | E18: IEEE | F18: 2023 International Conference on the Confluence of Advancements in Robotics, Vision and Interdisciplinary Technology Management (IC-RVITM) | G18: https://ieeexplore.ieee.org/abstract/document/10435182 | H18: 28-29 Nov. 2023 | I18: BrainCrossFed CNN Model for Alzheimer Classification using MRI data and Comparison and Benchmarking proposed model with DINOv2 and ExplainableAI using Grad-CAM | J18: 10.1109/IC-RVITM60032.2023.10435182 | M18: BrainCrossFed CNN Model for Alzheimer Classification using MRI data and Comparison and Benchmarking proposed model with DINOv2 and ExplainableAI using Grad-CAM | N18: ALZHEIMER'S DATASET | O18: No detail provided | P18: |DINO-v2|, |ResNet-101|, |DenseNet-121|, |VGG16| | Q18: |Grad-CAM| | R18: Accuracy, F1-Score, Precision, Recall
A19: Scopus | B19: A. Bhat; A. Raychowdhury | C19: 2023 | D19: Conference Proceedings | E19: IEEE | F19: AICAS 2023 - IEEE International Conference on Artificial Intelligence Circuits and Systems, Proceeding | G19: https://www.scopus.com/inward/record.uri?eid=2-s2.0-85166375420&doi=10.1109%2fAICAS57966.2023.10168594&partnerID=40&md5=b4ea125381ed9d581f927296b947793d | I19: Reducing Overhead of Feature Importance Visualization via Static Grad-CAM Computation | J19: 10.1109/AICAS57966.2023.10168594 | M19: Reducing Overhead of Feature Importance Visualization via Static Grad-CAM Computation | N19: CIFAR-10 dataset | O19: https://www.cs.toronto.edu/~kriz/cifar.html | P19: |CNN|, |ResNet-18| | Q19: |Grad-CAM| | R19: Accuracy, Latency (ms) | S19: .
A20: Scopus | B20: D. F. Collazos-Huertas; A. M. Álvarez-Meza; G. Castellanos-Dominguez | C20: 2022 | D20: Journal Article | E20: MDPI | F20: Applied Sciences (Switzerland) | G20: https://www.scopus.com/inward/record.uri?eid=2-s2.0-85124356263&doi=10.3390%2fapp12031695&partnerID=40&md5=868c6dc268f93ae37f3b4ec2ec7c25a7 | I20: Image-Based Learning Using Gradient Class Activation Maps for Enhanced Physiological Interpretability of Motor Imagery Skills | J20: 10.3390/app12031695 | L20: Journal MDPI | M20: Image-Based Learning Using Gradient Class Activation Maps for Enhanced Physiological Interpretability of Motor Imagery Skills | N20: Giga-Science | O20: https://gigadb.org/dataset/100295 | P20: |CNN| | Q20: |Grad-CAM++| | R20: Accuracy
A21: ScienceDirect | B21: M. Raju; V. P. Gopi; V. S. Anitha; A. Sherawat | C21: 2023 | D21: Journal Article | E21: Elsevier | F21: BenchCouncil Transactions on Benchmarks, Standards and Evaluations | G21: https://www.sciencedirect.com/science/article/pii/S2772485923000364 | H21: 2023 June | I21: CoviDetector: A transfer learning-based semi supervised approach to detect Covid-19 using CXR images | J21: https://doi.org/10.1016/j.tbench.2023.100119 | M21: Early diagnosis of Alzhiemer's disease using wavelet-pooling based deep convolutional neural network | N21: COVID CXR Image Dataset (Research), DLAI3 Hackathon Phase3 COVID-19 CXR Challenge, COVID-19 Radiography Database, Covid19 Detection | O21: https://www.kaggle.com/datasets/sid321axn/covid-cxr-image-dataset-research, https://www.kaggle.com/datasets/jonathanchan/dlai3-hackathon-phase3-covid19-cxr-challenge, https://www.kaggle.com/datasets/tawsifurrahman/covid19-radiography-database,https://www.kaggle.com/datasets/donjon00/covid19-detection | P21: |EfficientNet|, |DenseNet-121|, |VGG16|, |VGG19|, |Inception-v3| | Q21: |Grad-CAM| | R21: Accuracy, Precision, Recall, F1-Score | S21: .
A22: ScienceDirect | B22: D. Bajhaiya; S. Narayanan Unni | C22: 2024 | D22: Journal Article | E22: Elsevier | F22: Biomedical Signal Processing and Control | G22: https://www.sciencedirect.com/science/article/pii/S1746809424001836 | H22: 2024/07/01/ | I22: Deep learning-enabled detection and localization of gastrointestinal diseases using wireless-capsule endoscopic images | J22: https://doi.org/10.1016/j.bspc.2024.106125 | M22: Deep learning-enabled detection and localization of gastrointestinal diseases using wireless-capsule endoscopic images | N22: kvasir-capsule dataset | O22: https://osf.io/dv2ag/ | P22: |CNN|, |GINet| | Q22: |Grad-CAM|, |Guided Grad-CAM| | R22: Sensitivity, Specificity | S22: .
A23: Scopus | B23: M. S. Jamil; S. P. Banik; G. M. A. Rahaman; S. Saha | C23: 2023 | D23: Book Section | E23: CRC Press | F23: Computer Vision and Image Analysis for Industry 4.0 | G23: https://www.scopus.com/inward/record.uri?eid=2-s2.0-85161149678&partnerID=40&md5=9765291af356700831c028689b522a46 | I23: Advanced Grad-CAM++: Improved visual explanations of CNN decisions in diabetic retinopathy | M23: Advanced Grad-CAM++: Improved visual explanations of CNN decisions in diabetic retinopathy | N23: EyePacs dataset | O23: https://paperswithcode.com/dataset/kaggle-eyepacs | P23: |CNN|, |VGG16| | Q23: |Grad-CAM++| | R23: IoU
A24: ScienceDirect | B24: Y. Liu; J. Su; Z. Zheng; D. Liu; Y. Song; Y. Fang; P. Yang; B. Su | C24: 2024 | D24: Journal Article | E24: Elsevier | F24: Computers and Electronics in Agriculture | G24: https://www.sciencedirect.com/science/article/pii/S0168169924000590 | H24: 45312 | I24: GLDCNet: A novel convolutional neural network for grapevine leafroll disease recognition using UAV-based imagery | M24: GLDCNet: A novel convolutional neural network for grapevine leafroll disease recognition using UAV-based imagery | N24: QGIS | O24: https://qgis.org/en/site/ | P24: |GLDCNet| | Q24: |Grad-CAM| | R24: Recall, F1-Score, Accuracy, Precision
A25: ScienceDirect | B25: N. A. Hroub; A. N. Alsannaa; M. Alowaifeer; M. Alfarraj; E. Okafor | C25: 2024 | D25: Journal Article | E25: Elsevier | F25: COMPUTERS IN BIOLOGY AND MEDICINE | G25: https://www.sciencedirect.com/science/article/pii/S0010482524000969 | H25: 2024 MAR | I25: Explainable deep learning diagnostic system for prediction of lung disease from medical images | J25: 10.1016/j.compbiomed.2024.108012 | K25: WOS:001171926500001 | M25: Explainable deep learning diagnostic system for prediction of lung disease from medical images | N25: chest X-ray datasets | O25: https://www.kaggle.com/datasets/prashant268/chest-xray-covid19-pneumonia | P25: |ResNet-50|, |Inception-v3|, |DenseNet-201|, |EfficientNet-B7|, |MobileNet-v3| | Q25: |Grad-CAM|, |Grad-CAM++|, |EigenGrad-CAM|, |Ablation-CAM|, |Random-CAM|
A26: ScienceDirect | B26: S. Jain; A. Seal; A. Ojha; A. Yazidi; J. Bures; I. Tacheci; O. Krejcar | C26: 2021 | D26: Journal Article | E26: Elsevier | F26: Computers in Biology and Medicine | G26: https://www.sciencedirect.com/science/article/pii/S0010482521005837 | H26: 2021/10/01/ | I26: A deep CNN model for anomaly detection and localization in wireless capsule endoscopy images | J26: https://doi.org/10.1016/j.compbiomed.2021.104789 | M26: A deep CNN model for anomaly detection and localization in wireless capsule endoscopy images | N26: KID dataset | O26: https://hcup-us.ahrq.gov/db/nation/kid/kiddbdocumentation.jsp | P26: |CNN|, |WCENet| | Q26: |Grad-CAM++| | R26: Accuracy, Precision, Recall, F1-Score, AUC | S26: .
A27: Scopus | B27: J. Schneider; M. Vlachos | C27: 2023 | D27: Journal Article | E27: Springer | F27: Data Mining and Knowledge Discovery | G27: https://www.scopus.com/inward/record.uri?eid=2-s2.0-85148039931&doi=10.1007%2fs10618-023-00920-0&partnerID=40&md5=569b8404b41ca22ce4649a8f98ff3426 | I27: Reflective-net: learning from explanations | J27: 10.1007/s10618-023-00920-0 | M27: Reflective-net: learning from explanations | N27: Fashion-mnist | O27: https://github.com/zalandoresearch/fashion-mnist | P27: |CNN|, ResNet, |VGG| | Q27: |Grad-CAM| | R27: Accuracy | S27: .
A28: Web of Science | B28: B. Tasci | C28: 2023 | D28: Journal Article | E28: MDPI | F28: DIAGNOSTICS | G28: https://www.mdpi.com/2075-4418/13/5/859 | H28: 2023 MAR | I28: Attention Deep Feature Extraction from Brain MRIs in Explainable Mode: DGXAINet | J28: 10.3390/diagnostics13050859 | K28: WOS:000947696800001 | M28: Attention Deep Feature Extraction from Brain MRIs in Explainable Mode: DGXAINet | N28: Brain tumor dataset | O28: https://www.kaggle.com/datasets/sartajbhuvaji/brain-tumor-classification-mri | P28: |DenseNet-201| | Q28: |DGXAINet|, |Grad-CAM| | R28: Accuracy
A29: Web of Science | B29: M. Karki; K. Kantipudi; F. Yang; H. Yu; Y. X. J. Wang; Z. Yaniv; S. Jaeger | C29: 2022 | D29: Journal Article | E29: MDPI | F29: DIAGNOSTICS | G29: https://www.mdpi.com/2075-4418/12/1/188 | H29: 2022 JAN | I29: Generalization Challenges in Drug-Resistant Tuberculosis Detection from Chest X-rays | J29: 10.3390/diagnostics12010188 | K29: WOS:000746962500001 | M29: Generalization Challenges in Drug-Resistant Tuberculosis Detection from Chest X-rays | N29: CXR dataset | O29: https://github.com/v7labs/covid-19-xray-dataset | P29: |CNN| | Q29: |Grad-CAM| | R29: AUC, Accuracy | S29: .
A30: Web of Science | B30: S. Tummala; S. Kadry; A. Nadeem; H. T. Rauf; N. Gul | C30: 2023 | D30: Journal Article | E30: MDPI | F30: DIAGNOSTICS | G30: https://www.mdpi.com/2075-4418/13/9/1594 | H30: 2023 APR 29 | I30: An Explainable Classification Method Based on Complex Scaling in Histopathology Images for Lung and Colon Cancer | J30: 10.3390/diagnostics13091594 | K30: WOS:000986652400001 | M30: An Explainable Classification Method Based on Complex Scaling in Histopathology Images for Lung and Colon Cancer | N30: LC25000 histopathology dataset | O30: https://www.kaggle.com/datasets/andrewmvd/lung-and-colon-cancer-histopathological-images | P30: |EfficientNet-v2| | Q30: |Grad-CAM|, |saliency map| | R30: Accuracy, AUC, F1-Score, BA, MCC
A31: Scopus | B31: A. Kumar; S. B. Singh; S. C. Satapathy; M. Rout | C31: 2022 | D31: Journal Article | E31: Wiley | F31: Expert Systems | G31: https://www.scopus.com/inward/record.uri?eid=2-s2.0-85102651015&doi=10.1111%2fexsy.12695&partnerID=40&md5=489719e06db29aef5c68331216224d0b | I31: MOSQUITO-NET: A deep learning based CADx system for malaria diagnosis along with model interpretation using Grad-CAM and class activation maps | J31: 10.1111/exsy.12695 | M31: MOSQUITO-NET: A deep learning based CADx system for malaria diagnosis along with model interpretation using Grad-CAM and class activation maps | N31: Malaria dataset | O31: No detail provided | P31: |CNN|, |Mosquito Net| | Q31: |Grad-CAM| | R31: Accuracy, AUC, Sensitivity, Specificity, F1-Score, MCC | S31: .
A32: Web of Science | B32: V. Jain; O. Nankar; D. J. Jerrish; S. Gite; S. Patil; K. Kotecha | C32: 2021 | D32: Journal Article | E32: IEEE | F32: IEEE ACCESS | G32: https://ieeexplore.ieee.org/abstract/document/9611247 | H32: 2021 | I32: A Novel AI-Based System for Detection and Severity Prediction of Dementia Using MRI | J32: 10.1109/ACCESS.2021.3127394 | K32: WOS:000721988800001 | M32: A Novel AI-Based System for Detection and Severity Prediction of Dementia Using MRI | N32: Dementia dataset | O32: https://www.kaggle.com/datasets/shashwatwork/dementia-prediction-dataset | P32: |CNN|, |VGG16|, |VGG19| | Q32: |Grad-CAM| | R32: Precision, Recall, F1-Score, Accuracy | S32: .
A33: Web of Science | B33: D. Varam; R. Mitra; M. Mkadmi; R. A. Riyas; D. A. Abuhani; S. Dhou; A. Alzaatreh | C33: 2023 | D33: Journal Article | E33: IEEE | F33: IEEE ACCESS | G33: https://ieeexplore.ieee.org/abstract/document/10262261 | H33: 2023 | I33: Wireless Capsule Endoscopy Image Classification: An Explainable AI Approach | J33: 10.1109/ACCESS.2023.3319068 | K33: WOS:001081607200001 | M33: Wireless Capsule Endoscopy Image Classification: An Explainable AI Approach | N33: Kvasir-Capsule Dataset | O33: https://osf.io/dv2ag/ | P33: |Inception-v3|, |EfficientNet-v2|, |VGG16|, |VGG19|,|MobileNet-v3|, |ResNet-152v2|, | Q33: |Grad-CAM|, |Grad-CAM++|, |LayersCAM|, |LIME|, |SHAP| | S33: .
A34: Web of Science | B34: V. A. Ashwath; O. K. Sikha; R. Benitez | C34: 2023 | D34: Journal Article | E34: IEEE | F34: IEEE ACCESS | G34: https://ieeexplore.ieee.org/stamp/stamp.jsp?arnumber=10197361 | H34: 2023 | I34: TS-CNN: A Three-Tier Self-Interpretable CNN for Multi-Region Medical Image Classification | J34: 10.1109/ACCESS.2023.3299850 | K34: WOS:001041887000001 | M34: TS-CNN: A Three-Tier Self-Interpretable CNN for Multi-Region Medical Image Classification | N34: PAD-UFES-20 dataset | O34: https://github.com/sikha2552/TS-CNN-A-Three-Tier-Self-Interpretable-CNN-for-Medical-Image-Classification-Empowered-with-Post-hoc | P34: |DenseNet-121|, |Inception|, |Xception|, |ResNet-50| | Q34: |TS-CNN| | R34: Accuracy, Precision, Recall, F1-Score, AUC | S34: .
A35: Web of Science | B35: Z. Lai; L. C. Oliveira; R. Guo; W. Xu; Z. Hu; K. Mifflin; C. Decarli; S.-C. Cheung; C.-N. Chuah; B. N. Dugger | C35: 2022 | D35: Journal Article | E35: IEEE | F35: IEEE ACCESS | G35: https://ieeexplore.ieee.org/abstract/document/9766171 | H35: 2022 | I35: BrainSec: Automated Brain Tissue Segmentation Pipeline for Scalable Neuropathological Analysis | J35: 10.1109/ACCESS.2022.3171927 | K35: WOS:000797423700001 | M35: BrainSec: Automated Brain Tissue Segmentation Pipeline for Scalable Neuropathological Analysis | N35: Whole Slide Images (WSIs) dataset | O35: No detail provided | P35: |CNN| | Q35: |Grad-CAM| | R35: Accuracy | S35: .
A36: Web of Science | B36: P. X. Nguyen; H. Q. Cao; K. V. T. Nguyen; H. Nguyen; T. Yairi | C36: 2022 | D36: Journal Article | E36: Maruzen | F36: IEICE TRANSACTIONS ON INFORMATION AND SYSTEMS | G36: https://search.ieice.org/bin/summary.php?id=e105-d_8_1401 | H36: 2022 AUG | I36: SeCAM: Tightly Accelerate the Image Explanation via Region-Based Segmentation | J36: 10.1587/transinf.2021EDP7205 | K36: WOS:000836845200005 | M36: SeCAM: Tightly Accelerate the Image Explanation via Region-Based Segmentation | N36: ILSVRC-2012 | O36: No detail provided | P36: |ResNet-50|, |Inception-v3|, |VGG16| | Q36: |SeCAM| | R36: Accuracy
A37: IEEE Xplore | B37: D. E. Turan; E. Aptoula; A. Ertürk; G. Taskin | C37: 2023 | D37: Conference Proceedings | E37: IEEE | F37: IGARSS 2023 - 2023 IEEE International Geoscience and Remote Sensing Symposium | G37: https://ieeexplore.ieee.org/abstract/document/10282341 | H37: 45219 | I37: Interpreting Hyperspectral Remote Sensing Image Classification Methods Via Explainable Artificial Intelligence | J37: 10.1109/IGARSS52108.2023.10282341 | M37: Interpreting Hyperspectral Remote Sensing Image Classification Methods Via Explainable Artificial Intelligence | N37: Pavia University dataset | O37: Private Dataset | P37: |CNN| | Q37: |Grad-CAM|, |Grad-CAM++|, |Guided Backpropagation| | R37: Visual representation
A38: ScienceDirect | B38: S. Singh; P. K. Jain; N. Sharma; M. Pohit; S. Roy | C38: 2023 | D38: Journal Article | E38: Elsevier | F38: Intelligent Medicine | G38: https://www.sciencedirect.com/science/article/pii/S2667102623000414 | H38: 2023/07/01/ | I38: Atherosclerotic plaque classification in carotid ultrasound images using machine learning and explainable deep learning | J38: https://doi.org/10.1016/j.imed.2023.05.003 | M38: Atherosclerotic plaque classification in carotid ultrasound images using machine learning and explainable deep learning | N38: ultrasound images | O38: http://splab.cz/en/download/databaze/ultrasound | P38: |VGG16|, |ResNet-50|, |GoogLeNet|, |Xception|, |SqueezeNET| | Q38: |Grad-CAM| | R38: Accuracy, Sensitivity, Specificity, F1-Score, Cohen's kappa, AUC
A39: ScienceDirect | B39: G. Rani; A. Misra; V. S. Dhaka; D. Buddhi; R. K. Sharma; E. Zumpano; E. Vocaturo | C39: 2022 | D39: Journal Article | E39: Elsevier | F39: Intelligent Systems with Applications | G39: https://www.sciencedirect.com/science/article/pii/S2667305322000850 | H39: 2022/11/01/ | I39: A multi-modal bone suppression, lung segmentation, and classification approach for accurate COVID-19 detection using chest radiographs | J39: https://doi.org/10.1016/j.iswa.2022.200148 | M39: A multi-modal bone suppression, lung segmentation, and classification approach for accurate COVID-19 detection using chest radiographs | N39: COVID-Pneumonia CXR | O39: https://github.com/ieee8023/covid-chestxray-dataset | P39: |EXP-Net| | Q39: |Grad-CAM++| | R39: AUC, Cohen's kappa, F1-Score, Training Loss, Accuracy, Precision, Recall
A40: Scopus | B40: S. Park; C. Wallraven | C40: 2022 | D40: Conference Proceedings | E40: Springer | F40: Lecture Notes in Computer Science (including subseries Lecture Notes in Artificial Intelligence and Lecture Notes in Bioinformatics) | G40: https://www.scopus.com/inward/record.uri?eid=2-s2.0-85130341946&doi=10.1007%2f978-3-031-02375-0_30&partnerID=40&md5=831c755d4dbb4c7cc508c6f867ed7cc8 | I40: Comparing Facial Expression Recognition in Humans and Machines: Using CAM, Grad-CAM, and Extremal Perturbation | J40: 10.1007/978-3-031-02375-0_30 | M40: Comparing Facial Expression Recognition in Humans and Machines: Using CAM, Grad-CAM, and Extremal Perturbation | N40: AffectNet dataset | O40: https://paperswithcode.com/dataset/affectnet | P40: |DNN| | Q40: |CAM|, |Grad-CAM| | R40: Accuracy | S40: .
A41: Scopus | B41: M. El Habib Daho; A. Khouani; M. E. A. Lazouni; S. A. Mahmoudi | C41: 2021 | D41: Conference Proceedings | E41: Springer | F41: Lecture Notes in Networks and Systems | G41: https://www.scopus.com/inward/record.uri?eid=2-s2.0-85111331898&doi=10.1007%2f978-3-030-73882-2_89&partnerID=40&md5=42cd157847d8fdcef292d60fccfb986f | I41: Explainable Deep Learning Model for COVID-19 Screening in Chest CT Images | J41: 10.1007/978-3-030-73882-2_89 | M41: Explainable Deep Learning Model for COVID-19 Screening in Chest CT Images | N41: SARS-CoV-2 CT-scan | O41: https://www.medrxiv.org/content/10.1101/2020.04.24.20078584v3 | P41: |ResNet-50|, |DenseNet-121| | Q41: |Grad-CAM| | R41: Accuracy, Sensitivity, Specificity, F1-Score
A42: Web of Science | B42: N. S. Punn; S. Agarwal | C42: 2022 | D42: Journal Article | E42: Springer | F42: NEURAL PROCESSING LETTERS | G42: https://link.springer.com/article/10.1007/s11063-022-10785-x | H42: 2022 OCT | I42: CHS-Net: A Deep Learning Approach for Hierarchical Segmentation of COVID-19 via CT Images | J42: 10.1007/s11063-022-10785-x | K42: WOS:000769826600001 | M42: CHS-Net: A Deep Learning Approach for Hierarchical Segmentation of COVID-19 via CT Images | N42: COVID-19 CT | O42: https://github.com/nspunn1993/CHS-Net-COVID-19-hierarchical-segmentation-network | P42: |CHS-Net| | Q42: |Grad-CAM++| | R42: Accuracy, Precision, Specificity, Recall, Dice coefficient, Jaccard
A43: ScienceDirect | B43: J. Chang; J. Lee; A. Ha; Y. S. Han; E. Bak; S. Choi; J. M. Yun; U. Kang; I. H. Shin; J. Y. Shin; T. Ko; Y. Seul; K. L. Oh; K. H. Park; S. M. Park | C43: 2021 | D43: Journal Article | E43: Elsevier | F43: OPHTHALMOLOGY | G43: https://www.researchgate.net/publication/342489976_Explaining_the_Rationale_of_Deep_Learning_Glaucoma_Decisions_with_Adversarial_Examples | H43: 2021 JAN | I43: Explaining the Rationale of Deep Learning Glaucoma Decisions with Adversarial Examples | J43: 10.1016/j.opatha.2020.06.036 | K43: WOS:000600748500024 | M43: Explaining the Rationale of Deep Learning Glaucoma Decisions with Adversarial Examples | N43: Glaucoma | O43: Private Dataset | P43: |DLMs| | Q43: |Grad-CAM| | R43: AUC, Sensitivity, Specificity
A44: Web of Science | B44: A. R. Bhatt; A. Ganatra; K. Kotecha | C44: 2021 | D44: Journal Article | E44: PeerJ | F44: PEERJ COMPUTER SCIENCE | G44: https://peerj.com/articles/cs-348/?trk=public_post_comment-text | H44: 2021 FEB 18 | I44: Cervical cancer detection in pap smear whole slide images using convNet with transfer learning and progressive resizing | J44: 10.7717/peerj-cs.348 | K44: WOS:000620829800001 | M44: Cervical cancer detection in pap smear whole slide images using convNet with transfer learning and progressive resizing | N44: SIPaKMeD | O44: https://paperswithcode.com/dataset/sipakmed< (https://www.cs.uoi.gr/~marina/sipakmed.html) | P44: |VGG19|, |ResNet-34|, |ResNet-101|, |EfficientNet-B3|, |EfficientNet-B4|, |EfficientNet-B5| | Q44: |Grad-CAM| | R44: Accuracy, Precision, Recall, F-Beta Score, Cohen's kappa
A45: Scopus | B45: A. Schöttl | C45: 2022 | D45: Conference Proceedings | E45: Elsevier | F45: Procedia Computer Science | G45: https://www.scopus.com/inward/record.uri?eid=2-s2.0-85127740915&doi=10.1016%2fj.procs.2022.01.260&partnerID=40&md5=88694e89dce47995239a24a92e580d64 | I45: Improving the Interpretability of Grad-CAMs in Deep Classification Networks | J45: 10.1016/j.procs.2022.01.260 | M45: Improving the Interpretability of Grad-CAMs in Deep Classification Networks | N45: Imagenet ILSVRC 2012 | O45: https://www.image-net.org/challenges/LSVRC/2012/ | P45: |ResNet-50| | Q45: |Grad-CAM| | R45: Accuracy
A46: ScienceDirect | B46: K. Niranjan; S. Shankar Kumar; S. Vedanth; D. S. Chitrakala | C46: 2023 | D46: Journal Article | E46: Elsevier | F46: Procedia Computer Science | G46: https://www.sciencedirect.com/science/article/pii/S1877050923001680 | H46: 2023/01/01/ | I46: An Explainable AI driven Decision Support System for COVID-19 Diagnosis using Fused Classification and Segmentation | J46: https://doi.org/10.1016/j.procs.2023.01.168 | M46: An Explainable AI driven Decision Support System for COVID-19 Diagnosis using Fused Classification and Segmentation | N46: CT scan dataset | O46: https://github.com/UCSD-AI4H/COVID-CT | P46: |CNN|, |Res2Net| | Q46: |Guided Grad-CAM| | R46: Accuracy, Precision, Recll, F1−Score
A47: Scopus | B47: X. A. Inbaraj; J. H. Jeng | C47: 2021 | D47: Conference Proceedings | E47: SPIE | F47: Proceedings of the 6th International Conference on Inventive Computation Technologies, ICICT 2021 | G47: https://www.scopus.com/inward/record.uri?eid=2-s2.0-85102560062&doi=10.1109%2fICICT50816.2021.9358569&partnerID=40&md5=c300a8eb38b8a93b1a433a3c5078b25a | I47: Mask-Grad-CAM: Object Identification and Localization of Visual Presentation for Deep Convolutional Network | J47: 10.1109/ICICT50816.2021.9358569 | M47: Mask-Grad-CAM: Object Identification and Localization of Visual Presentation for Deep Convolutional Network | N47: N/A | O47: No detail provided | P47: |Mask R CNN| | Q47: |Mask Grad-CAM| | R47: Accuracy
A48: Web of Science | B48: I. Palatnik de Sousa; M. M. B. R. Vellasco; E. Costa da Silva | C48: 2021 | D48: Journal Article | E48: MDPI | F48: SENSORS | G48: https://www.mdpi.com/1424-8220/21/16/5657 | H48: 2021 AUG | I48: Explainable Artificial Intelligence for Bias Detection in COVID CT-Scan Classifiers | J48: 10.3390/s21165657 | K48: WOS:000689893900001 | M48: Explainable Artificial Intelligence for Bias Detection in COVID CT-Scan Classifiers | N48: COVID-CT dataset | O48: https://github.com/UCSD-AI4H/COVID-CT | P48: |VGG16|, |DenseNet|, |EfficientNet| | Q48: |Grad-CAM|, |LIME|, |RISE|, |Squaregrid| | R48: Accuracy, F1-Score, AUC | S48: .
A49: Scopus | B49: M. De Silva; P. Kumarasinghe; K. De Zoysa; C. Keppitiyagama | C49: 2022 | D49: Journal Article | E49: Springer | F49: SN Computer Science | G49: https://www.scopus.com/inward/record.uri?eid=2-s2.0-85129707185&doi=10.1007%2fs42979-022-01057-5&partnerID=40&md5=3af24b60f97cec486b3e6dca5512927a | I49: Reidentifying Asian Elephants from Ear Images Using a Cascade of Convolutional Neural Networks and Explaining with Grad-CAM | J49: 10.1007/s42979-022-01057-5 | M49: Reidentifying Asian Elephants from Ear Images Using a Cascade of Convolutional Neural Networks and Explaining with Grad-CAM | N49: Asian elephants image dataset | O49: https://www.elephantlisteningproject.orga/ | P49: |YOLO|, |CNN|, |VGG16|, |ResNet-50|, |Inception-v3|, |AlexNet| | Q49: |Grad-CAM| | R49: Accuracy
A50: Scopus | B50: B. S. Sharmila; H. S. Santhosh; S. Parameshwara; M. S. Swamy; W. H. Baig; S. V. Nanditha | C50: 2023 | D50: Journal Article | E50: Springer | F50: SN Computer Science | G50: https://www.scopus.com/inward/record.uri?eid=2-s2.0-85174151165&doi=10.1007%2fs42979-023-02239-5&partnerID=40&md5=a4637bc54f9b7f42bf86b12bb6c559e5 | I50: Optimizing Deep Learning Networks for Edge Devices with an Instance of Skin Cancer and Corn Leaf Disease Dataset | J50: 10.1007/s42979-023-02239-5 | M50: Optimizing Deep Learning Networks for Edge Devices with an Instance of Skin Cancer and Corn Leaf Disease Dataset | N50: Corn Leaf Disease and Skin Cancer Disease datasets | O50: https://github.com/pratikkayal/PlantDoc-Dataset, https://github.com/pratikkayal/PlantDoc-Object-Detection-Dataset | P50: |CNN|, |ResNet|, |MobileNet| | Q50: |Grad-CAM| | R50: Accuracy, Memory size
A51: Web of Science | B51: A. H. Ornek; M. Ceylan | C51: 2022 | D51: Journal Article | E51: IIETA | F51: TRAITEMENT DU SIGNAL | G51: https://iieta.org/journals/ts/paper/10.18280/ts.390529 | H51: 2022 OCT | I51: HayCAM: A Novel Visual Explanation for Deep Convolutional Neural Networks | J51: 10.18280/ts.390529 | K51: WOS:000907630800022 | M51: HayCAM: A Novel Visual Explanation for Deep Convolutional Neural Networks | N51: Face Mask detection Dataset | O51: No detail provided | P51: |CNN| | Q51: |HayCAM| | R51: Accuracy
A52: ScienceDirect | B52: R. Rahman; M. G. R. Alam; M. T. Reza; A. Huq; G. Jeon; M. Z. Uddin; M. M. Hassan | C52: 2023 | D52: Journal Article | E52: Elsevier | F52: ULTRASONICS | G52: https://www.sciencedirect.com/science/article/pii/S0041624X23000938 | H52: 2023 JUL | I52: Demystifying evidential Dempster Shafer-based CNN architecture for fetal plane detection from 2D ultrasound images leveraging fuzzy-contrast enhancement and explainable AI | J52: 10.1016/j.ultras.2023.107017 | K52: WOS:001004389700001 | M52: Demystifying evidential Dempster Shafer-based CNN architecture for fetal plane detection from 2D ultrasound images leveraging fuzzy-contrast enhancement and explainable AI | N52: Ultrasound images | O52: No detail provided | P52: |PReLU-Net|, |SqueezeNET|, |Swin Transformer| | Q52: |LIME|, |Grad-CAM| | R52: Accuracy, F1-Scores, Precision, Recall
I60: On the use of XAI for CNN Model Interpretation: A Remote Sensing Case Study
I61: A Fusion of Three Custom-Tailored Deep Learning Architectures for Waste Classification
I62: NoiseCAM: Explainable AI for the Boundary Between Noise and Adversarial Attacks
I63: Interpreting Hyperspectral Remote Sensing Image Classification Methods Via Explainable Artificial Intelligence
I64: CoviDetector: A transfer learning-based semi supervised approach to detect Covid-19 using CXR images

Sheet 3 Eligibility
A1: Name of Database | B1: Reference Type | C1: Author | D1: Year | E1: Title | F1: Secondary Title | G1: Volume | H1: Number | I1: Pages | J1: Publisher | K1: Place Published | L1: URL | M1: DOI | N1: Keywords | O1: Abstract | P1: Relevence 0,1,0.5 | Q1: Methodology 0, 1, 0.5 | R1: Limitations 0,1,0.5 | S1: Findings 0,1,0.5 | T1: Total
A2: IEEE Xplore | B2: Conference Proceedings | C2: A. Bhat; A. Raychowdhury | D2: 2023 | E2: Reducing Overhead of Feature Importance Visualization via Static GradCAM Computation | F2: 2023 IEEE 5th International Conference on Artificial Intelligence Circuits and Systems (AICAS) | I2: 45413 | M2: 10.1109/AICAS57966.2023.10168594 | N2: Visualization_x000D_ Schedules_x000D_ Runtime_x000D_ Processor scheduling_x000D_ Computational modeling_x000D_ Software algorithms_x000D_ Inference algorithms_x000D_ Convolutional Neural Network (CNN)_x000D_ Explainable AI (XAI)_x000D_ Feature Attribution_x000D_ GradCAM_x000D_ FPGA_x000D_ High Level Synthesis (HLS)_x000D_ Domain Specific Hardware Accelerator | O2: Explainable AI (XAI) methods provide insights into the operation of black-box Deep Neural Network (DNN) models. GradCAM, an XAI algorithm, provides an explanation by highlighting regions in the input feature space that were relevant to the model’s output. It involves a gradient computation step that adds a significant overhead compared to inference and hinders providing explanations to end-users. In this work, we identify the root cause of the problem to be the dynamic run-time automatic differentiation. To overcome this issue, we propose to offload the gradient computation step to compile time via analytic evaluation. We validate the idea by designing an FPGA implementation of GradCAM that schedules the entire computation graph statically. For a TinyML ResNet18 model, we achieve a reduction in the explanation generation overhead from > 2× using software frameworks on CPU/GPU systems to < 0.01× on the FPGA using our designed hardware and static scheduling. | P2: 1 | Q2: 1 | R2: 0.5 | S2: 1 | T2: =SUM(Table145[[#This Row],[Relevence 0,1,0.5]:[Findings 0,1,0.5]]) -> 3.5
A3: IEEE Xplore | B3: Conference Proceedings | C3: S. Chakraborty; K. Kumar; B. P. Reddy; T. Meena; S. Roy | D3: 2023 | E3: An Explainable AI based Clinical Assistance Model for Identifying Patients with the Onset of Sepsis | F3: 2023 IEEE 24th International Conference on Information Reuse and Integration for Data Science (IRI) | I3: 297-302 | M3: 10.1109/IRI58017.2023.00059 | N3: Sensitivity_x000D_ Biological system modeling_x000D_ Predictive models_x000D_ Data science_x000D_ Sepsis_x000D_ Feature extraction_x000D_ Rough surfaces_x000D_ Healthcare_x000D_ XAI_x000D_ Sepsis Prediction_x000D_ Autoencoders | O3: The high mortality rate of sepsis, especially in Intensive Care Unit (ICU) makes it third-highest mortality disease globally. The treatment of sepsis is also time consuming and depends on multi-parametric tests, hence early identification of patients with sepsis becomes crucial. The recent rise in the development of Artificial Intelligence (AI) based models, especially in early prediction of sepsis, have improved the patient outcome. However, drawbacks like low sensitivity, use of excess features that leads to overfitting, and lack of interpretability limit their ability to be used in a clinical setting. So, in this research we have developed a smart, explainable and a highly accurate AI based model (called XAutoNet) that provides quick and early prediction of sepsis with a minimal number of features as input. An application based novel convolutional neural network (CNN) based autoencoder is also implemented that improves the performance of XAutoNet by dimensional reduction. Finally, to unbox the “Black Box” nature of these models, Gradient based Class Activation Map (GradCAM) and SHapley Additive exPlanations (SHAP) are implemented to provide interpretability of autoencoder and XAutoNet in the form of visualization graphs to assist clinicians in diagnosis and treatment. | P3: 0 | Q3: 0 | R3: 0.5 | S3: 1 | T3: =SUM(Table145[[#This Row],[Relevence 0,1,0.5]:[Findings 0,1,0.5]]) -> 1.5
A4: IEEE Xplore | B4: Conference Proceedings | C4: E. Ennadifi; S. Laraba; D. Vincke; B. Mercatoris; B. Gosselin | D4: 2020 | E4: Wheat Diseases Classification and Localization Using Convolutional Neural Networks and GradCAM Visualization | F4: 2020 International Conference on Intelligent Systems and Computer Vision (ISCV) | I4: 45413 | M4: 10.1109/ISCV49265.2020.9204258 | N4: Diseases_x000D_ Agriculture_x000D_ Task analysis_x000D_ Image segmentation_x000D_ Convolutional neural networks_x000D_ Machine learning_x000D_ Databases_x000D_ GradCAM_x000D_ Mask R-CNN_x000D_ image processing_x000D_ classification_x000D_ deep learning_x000D_ plant diseases detection | O4: The world has been witnessing a population boom that has several implications including food security. Wheat is one of the world's most important crops in terms of production and consumption, and demand for it is increasing. On the other hand, diseases can damage the abundance and the quality of the crop, so this needs to be revealed through advanced methods. In recent years, along with the various technological developments, using Convolutional Neural Networks (CNN) has proved to be showing great results in many image classification tasks. However, deep learning models are generally considered as black boxes and it is difficult to understand what the model has learned. The purpose of this article is to detect diseases from wheat images using CNNs and to use visualization methods to understand what these models have learned. For this reason, a wheat database has been collected by CRA-W (Walloon Agricultural Research Center), which contains 1163 images and is classified into two groups namely sick and healthy. Moreover, we propose to use the mask R-CNN for segmentation and extraction of wheat spikes from the background. Furthermore, a visualization and interpretation method, namely Gradient-weighted Class Activation Mapping (GradCAM), is used to locate the disease on the wheat spikes in a non-supervised way. GradCAM is actually used generally to highlight the most important regions from the CNN model's viewpoint that are used to perform the classification. | P4: 1 | Q4: 1 | R4: 1 | S4: 1 | T4: =SUM(Table145[[#This Row],[Relevence 0,1,0.5]:[Findings 0,1,0.5]]) -> 4
A5: IEEE Xplore | B5: Conference Proceedings | C5: R. Golash; U. Gupta; V. Vats; K. Sharma; K. Golash | D5: 2023 | E5: Unveiling the Opacity: Exploring Rationality and Explainability in Tomato Disease Classification | F5: 2023 Second International Conference On Smart Technologies For Smart Nation (SmartTechCon) | I5: 462-468 | M5: 10.1109/SmartTechCon57526.2023.10391741 | N5: Visualization_x000D_ Biological system modeling_x000D_ Crops_x000D_ Closed box_x000D_ Production_x000D_ Transformers_x000D_ Prediction algorithms_x000D_ Explainable AI_x000D_ Tomato Leaf Disease_x000D_ Classification_x000D_ Vision Transformers_x000D_ EfficientNet-B7_x000D_ ResNet101_x000D_ Integrated Gradient_x000D_ GradCAM | O5: Artificial Intelligence has advanced expeditiously over the past years and led to the production of highly complex and leading-edge models deployed to solve problems in a challenging environment. With high dependence on the machine made predictions, it has now become a necessity to be able to look transparently across the black-box and understand the features that influence it’s ability to make decisions. The paper contributes in understanding the rationality and explainability of the models in the classification of diseases in tomato fruit plants. We employed three models, Resnet101, EfficientNetB7, Vision Transformer (vit_base_patch16_224) to classify the disease present in tomato leaf. The opacity of these models are deciphered by implementing two Explainable Artificial Intelligence(XAI) methods, GuidedGradCAM and Integrated Gradients. The explainable algorithms help in unveiling and analyzing the factor that affects the prediction. According to the experimental results, EfficientNet-B7 demonstrates an exceptional level of accuracy, reaching a staggering 99.84% and classifies the disease based on the lesions. The Resnet101 also achieves a significant accuracy of 95.23%, whereas the vision transformer is able to achieve an accuracy of 77.76% only. The paper visualizes and draws a comparison between the two CNN-based models by evaluating their performance based on their validation loss and and accuracy. Interpreting the model’s intelligibility would help in strengthening the practitioner’s trust with the machine-driven decisions and ensure early detection and classification of the disease which would help in taking appropriate measures to prevent substantial crop and economical loss. | P5: 1 | Q5: 1 | R5: 0.5 | S5: 1 | T5: =SUM(Table145[[#This Row],[Relevence 0,1,0.5]:[Findings 0,1,0.5]]) -> 3.5
A6: IEEE Xplore | B6: Conference Proceedings | C6: Y. Hirose; S. Ono | D6: 2023 | E6: Black-box Adversarial Attack against Visual Interpreters for Deep Neural Networks | F6: 2023 18th International Conference on Machine Vision and Applications (MVA) | I6: 45444 | M6: 10.23919/MVA57639.2023.10215758 | N6: Adaptation models_x000D_ Visualization_x000D_ Perturbation methods_x000D_ Machine vision_x000D_ Closed box_x000D_ Artificial neural networks_x000D_ Predictive models | O6: With the rapid development of deep neural networks (DNNs), eXplainable AI, which provides a basis for prediction on inputs, has become increasingly important. In addition, DNNs have a vulnerability called an Adversarial Example (AE), which can cause incorrect output by applying special perturbations to inputs. Potential vulnerabilities can also exist in image interpreters such as GradCAM, necessitating their investigation, as these vulnerabilities could potentially result in misdiagnosis within medical imaging. Therefore, this study proposes a black-box adversarial attack method that misleads the image interpreter using Sep-CMA-ES. The proposed method deceptively shifts the focus area of the image interpreter to a different location from that of the original image while maintaining the same predictive labels. | P6: 0 | Q6: 1 | R6: 0.5 | S6: 0.5 | T6: =SUM(Table145[[#This Row],[Relevence 0,1,0.5]:[Findings 0,1,0.5]]) -> 2
A7: IEEE Xplore | B7: Conference Proceedings | C7: S. M. Javali; R. S. Upadhyayula; T. De | D7: 2022 | E7: Comparative study of xAI layer-wise algorithms with a Robust Recommendation framework of Inductive Clustering for Polyp Segmentation and Classification | F7: 2021 International Seminar on Machine Learning, Optimization, and Data Science (ISMODE) | I7: 325-330 | M7: 10.1109/ISMODE53584.2022.9743003 | N7: Deep learning_x000D_ Training_x000D_ Analytical models_x000D_ Visualization_x000D_ Computational modeling_x000D_ Predictive models_x000D_ Prediction algorithms_x000D_ eXplainable Artificial Intelligence (xAI)_x000D_ colorectal cancer_x000D_ polyp segmentation_x000D_ inductive clustering_x000D_ image matching_x000D_ Feature Pyramid Network (FPN) | O7: Explainable Artificial Intelligence (xAI) is aimed at unboxing the AI model choices by providing interpretable explanations mitigating the black-box nature of algorithms and improving the transparency. Availability of many xAI techniques for medical imaging studies, necessitates a need to understand and pick a suitable approach for different stakeholders (clinician/patient). Interpretation of model predictions could be benefitted by comparing different xAI approaches. We explored different xAI techniques on Kvasir-SEG polyp segmentation dataset. A comparative analysis of attributions from convolutional layers of Feature Pyramid Network (FPN) model (Dice coefficient = 0.942 and meanIOU = 0.916) is provided. We observed that Layered GradCAM provides a very robust visual trajectory of explanations flowing through encoder-decoder-segmentation blocks. We investigated an explanation-by-example approach wherein we compare and match the predicted mask with key-point features from the training corpus. In addition, we have developed a recommendation approach using Inductive Clustering for classifying predicted polyps based on their size and area into three classes – small, medium and large. The recommendation could assist in prioritizing the patient check-up and subsequent timely intervention by a clinician. | P7: 0 | Q7: 1 | R7: 0.5 | S7: 0.5 | T7: =SUM(Table145[[#This Row],[Relevence 0,1,0.5]:[Findings 0,1,0.5]]) -> 2
A8: IEEE Xplore | B8: Conference Proceedings | C8: S. Kusunose; Y. Shinomiya; T. Ushiwaka; N. Maeda; Y. Hoshino | D8: 2021 | E8: Improving Individually Selectness for Immune Cells using GradCAM | F8: 2021 5th IEEE International Conference on Cybernetics (CYBCONF) | I8: 034-038 | M8: 10.1109/CYBCONF51991.2021.9464134 | N8: Image recognition_x000D_ Shape_x000D_ Conferences_x000D_ Focusing_x000D_ Feature extraction_x000D_ Proposals_x000D_ Medical diagnostic imaging_x000D_ Deep Learning_x000D_ Immune Cell_x000D_ GradCAM_x000D_ Image Processing | O8: This paper focuses on the analysis of behavior of immune cells for supporting diagnosis. The previous work has proposed to detect immune cells from medical images by recognition frequency space. However, the work has a problem that selects a region including multiple cells as a single cell. This paper aims to relax the problem by focusing the locality of cell shapes. Our proposal uses gradient-weighted class activation mapping (GradCAM) to capture locality characteristics of immune cells. The results shows that the densely inhabited immune cells are correctly selected. Our proposal has some issues that a cell is occasionally detected as multiple ones. We consider that this issue is can be solved by image processing techniques such as non-maximum suppression. | P8: 1 | Q8: 1 | R8: 1 | S8: 1 | T8: =SUM(Table145[[#This Row],[Relevence 0,1,0.5]:[Findings 0,1,0.5]]) -> 4
A9: IEEE Xplore | B9: Conference Proceedings | C9: J. Maximino; M. Coimbra; J. Pedrosa | D9: 2022 | E9: Detection of COVID-19 in Point of Care Lung Ultrasound | F9: 2022 44th Annual International Conference of the IEEE Engineering in Medicine & Biology Society (EMBC) | I9: 1527-1530 | M9: 10.1109/EMBC48229.2022.9871235 | N9: COVID-19_x000D_ Training_x000D_ Ultrasonic imaging_x000D_ Point of care_x000D_ Lung_x000D_ Computer architecture_x000D_ Data models | O9: The coronavirus disease 2019 (COVID-19) evolved into a global pandemic, responsible for a significant number of infections and deaths. In this scenario, point-of-care ultrasound (POCUS) has emerged as a viable and safe imaging modality. Computer vision (CV) solutions have been proposed to aid clinicians in POCUS image interpretation, namely detection/segmentation of structures and image/patient classification but relevant challenges still remain. As such, the aim of this study is to develop CV algorithms, using Deep Learning techniques, to create tools that can aid doctors in the diagnosis of viral and bacterial pneumonia (VP and BP) through POCUS exams. To do so, convolutional neural networks were designed to perform in classification tasks. The architectures chosen to build these models were the VGG16, ResNet50, DenseNet169 e MobileNetV2. Patients images were divided in three classes: healthy (HE), BP and VP (which includes COVID-19). Through a comparative study, which was based on several performance metrics, the model based on the DenseNet169 architecture was designated as the best performing model, achieving 78% average accuracy value of the five iterations of 5- Fold Cross-Validation. Given that the currently available POCUS datasets for COVID-19 are still limited, the training of the models was negatively affected by such and the models were not tested in an independent dataset. Furthermore, it was also not possible to perform lesion detection tasks. Nonetheless, in order to provide explainability and understanding of the models, Gradient-weighted Class Activation Mapping (GradCAM) were used as a tool to highlight the most relevant classification regions. Clinical relevance – Reveals the potential of POCUS to support COVID-19 screening. The results are very promising although the dataset is limite | P9: 1 | Q9: 1 | R9: 1 | S9: 1 | T9: =SUM(Table145[[#This Row],[Relevence 0,1,0.5]:[Findings 0,1,0.5]]) -> 4
A10: IEEE Xplore | B10: Journal Article | C10: T. Meena; K. Sarawadekar | D10: 2024 | E10: An eXplainable Self-Attention-Based Spatial–Temporal Analysis for Human Activity Recognition | F10: IEEE Sensors Journal | G10: 24 | H10: 1 | I10: 635-644 | M10: 10.1109/JSEN.2023.3335449 | N10: Sensors_x000D_ Feature extraction_x000D_ Human activity recognition_x000D_ Convolutional neural networks_x000D_ Computer architecture_x000D_ Biomedical monitoring_x000D_ Computational modeling_x000D_ 1-D gradient-weighted class activation mapping (GradCAM)_x000D_ explainability_x000D_ human activity recognition (HAR)_x000D_ long short-term memory (LSTM)_x000D_ self-attention_x000D_ smartphones | O10: Human activity recognition (HAR) from inertial sensors has been a hot topic of research in recent years. Recognition of human activities from smartphone sensors poses a significant challenge because of the complexity of sensor data. In this work, a novel self-attention convolutional neural network-long short-term memory (CNN-LSTM) module is proposed by using the sensor data from inbuilt inertial sensors in smartphones. The experiment includes the results on the well-known HAR public datasets, namely, University of California HAR Dataset (UCI-HAR), University of California Human Activities and Postural Transitions (UCI-HAPT), and Sanitation datasets. The performance evaluation of the proposed model confirmed its effectiveness, as it achieved high accuracy rates across all tested datasets. Furthermore, ablation studies performed on the depth and number of hyperparameters used in the model demonstrate its effectiveness in achieving higher classification accuracy. The model was also evaluated using other metrics and was found to be cost effective in terms of the number of floating-point operations per second (FLOPs). In addition, a 1-D gradient-weighted class activation mapping (GradCAM) was implemented on the self-attention layer of the proposed model to determine and visualize the features responsible for the predicted activities. Our proposed model demonstrated superior performance on each individual dataset and achieved the best results on the UCI-HAR dataset. Specifically, for the UCI-HAR dataset, our model achieved an accuracy score of 0.9829, precision of 0.9833, recall of 0.9840, and ${F}1$ score of 0.9836 on the test data. Furthermore, the Matthews correlation coefficient (MCC) and Kappa score were calculated as 0.9795 and 0.9794, respectively. | P10: 0 | Q10: 0 | R10: 0.5 | S10: 1 | T10: =SUM(Table145[[#This Row],[Relevence 0,1,0.5]:[Findings 0,1,0.5]]) -> 1.5
A11: IEEE Xplore | B11: Conference Proceedings | C11: H. E. Mohamadi; M. E. Hassouni | D11: 2023 | E11: Enhanced Deep Learning Explainability for COVID-19 Diagnosis from Chest X-ray Images by Fusing Texture and Shape Features | F11: 2023 10th International Conference on Wireless Networks and Mobile Communications (WINCOM) | I11: 45444 | M11: 10.1109/WINCOM59760.2023.10322952 | N11: COVID-19_x000D_ Deep learning_x000D_ Shape_x000D_ Convolution_x000D_ Wireless networks_x000D_ Feature extraction_x000D_ Data mining_x000D_ COVID-19 detection_x000D_ CXR images_x000D_ XDL_x000D_ texture-shape_x000D_ guided filter fusion_x000D_ FEM_x000D_ GradCam | O11: In this paper, we propose a novel method of explainable deep learning for COVID-19 detection in Chest X-ray (CXR) images, employing a Texture-Shape approach. The method extracts texture information from the first convolution layer and shape features from the last convolution layer of Deep Neural Networks, namely CNN, VGG16, and ResNet50. To generate the final explainable map, the extracted texture and shape heatmaps are fused using a guided filter-based method. Our approach is versatile and can be adapted to work with classical explainability methods commonly used in the literature. We validate the efficacy of our method on a well-known COVID-19 database comprising CXR images. We conduct extensive experiments to assess its performance against classical explainability methods such as FEM (Feature Extraction Map) and GradCam (Gradientweighted Class Activation Mapping). For evaluation, we calculate metrics such as the average drop and increase in confidence scores. The obtained results demonstrate that fusing texture and shape information leads to significantly improved explainability compared to conventional methods. | P11: 1 | Q11: 1 | R11: 1 | S11: 1 | T11: =SUM(Table145[[#This Row],[Relevence 0,1,0.5]:[Findings 0,1,0.5]]) -> 4
A12: IEEE Xplore | B12: Conference Proceedings | C12: L. Moradi; B. Kalantar; E. H. Zaryabi; A. A. Halin; N. Ueda | D12: 2022 | E12: On the use of XAI for CNN Model Interpretation: A Remote Sensing Case Study | F12: 2022 IEEE Asia-Pacific Conference on Computer Science and Data Engineering (CSDE) | I12: 45413 | M12: 10.1109/CSDE56538.2022.10089337 | N12: Computer science_x000D_ Sensitivity_x000D_ Deconvolution_x000D_ Computational modeling_x000D_ Information retrieval_x000D_ Data engineering_x000D_ Data models_x000D_ XAI method_x000D_ primary attribution_x000D_ layer attribution_x000D_ GradCAM_x000D_ IntegratedGradients_x000D_ explainability | O12: In this paper, we investigate the use of Explainable Artificial Intelligence (XAI) methods for the interpretation of two Convolutional Neural Network (CNN) classifiers in the field of remote sensing (RS). Specifically, the SegNet and Unet architectures for RS building information extraction and segmentation are evaluated using a comprehensive array of primary- and layer-attributions XAI methods. The attribution methods are quantitatively evaluated using the sensitivity metric. Based on the visualization of the different XAI methods, Deconvolution and GradCAM results in many of the study areas show reliability. Moreover, these methods are able to accurately interpret both Unet's and SegNet's decisions and managed to analyze and reveal the internal mechanisms in both models (confirmed by the low sensitivity scores). Overall, no single method stood out as the best one. | P12: 0 | Q12: 1 | R12: 0.5 | S12: 0.5 | T12: =SUM(Table145[[#This Row],[Relevence 0,1,0.5]:[Findings 0,1,0.5]]) -> 2
A13: IEEE Xplore | B13: Conference Proceedings | C13: H. Nasiri; G. Kheyroddin; M. Dorrigiv; M. Esmaeili; A. R. Nafchi; M. H. Ghorbani; P. Zarkesh-Ha | D13: 2022 | E13: Classification of COVID-19 in Chest X-ray Images Using Fusion of Deep Features and LightGBM | F13: 2022 IEEE World AI IoT Congress (AIIoT) | I13: 201-206 | M13: 10.1109/AIIoT54504.2022.9817375 | N13: COVID-19_x000D_ Deep learning_x000D_ Heating systems_x000D_ Pandemics_x000D_ Pulmonary diseases_x000D_ Neural networks_x000D_ Feature extraction_x000D_ DenseNet169_x000D_ MobileNet_x000D_ Light-GBM_x000D_ Univariate Feature Selection_x000D_ GradCAM | O13: The COVID-19 disease was first discovered in Wuhan, China, and spread quickly worldwide. After the COVID-19 pandemic, many researchers have begun to identify a way to diagnose the COVID-19 using chest X-ray images. The early diagnosis of this disease can significantly impact the treatment process. In this article, we propose a new technique that is faster and more accurate than the other methods reported in the literature. The proposed method uses a combination of DenseNet169 and MobileNet Deep Neural Networks to extract the features of the patient's X-ray images. Using the univariate feature selection algorithm, we refined the features for the most important ones. Then we applied the selected features as input to the LightGBM (Light Gradient Boosting Machine) algorithm for classification. To assess the effectiveness of the proposed method, the ChestX-ray8 dataset, which includes 1125 X-ray images of the patient's chest, was used. The proposed method achieved 98.54% and 91.11% accuracies in the two-class (COVID-19, Healthy) and multi-class (COVID-19, Healthy, Pneumonia) classification problems, respectively. It is worth mentioning that we have used Gradient-weighted Class Activation Mapping (Grad-CAM) for future analysis. | P13: 1 | Q13: 1 | R13: 1 | S13: 1 | T13: =SUM(Table145[[#This Row],[Relevence 0,1,0.5]:[Findings 0,1,0.5]]) -> 4
A14: IEEE Xplore | B14: Conference Proceedings | C14: V. K. Prasad; K. M. N. Raj; S. Muthya; R. S. Nair | D14: 2021 | E14: Development and validation of ECG rhythm classification on a multitude of data sources using Deep Learning | F14: 2021 IEEE 9th International Conference on Healthcare Informatics (ICHI) | I14: 101-105 | M14: 10.1109/ICHI52183.2021.00026 | N14: Deep learning_x000D_ Strips_x000D_ Analytical models_x000D_ Sensitivity_x000D_ Electrocardiography_x000D_ Sensitivity and specificity_x000D_ Predictive models_x000D_ Electrocardiogram_x000D_ Arrhythmia_x000D_ Grad-CAM_x000D_ Computer Vision | O14: Electrocardiogram (ECG) serves a key role in understanding human health conditions and necessitates targeted treatments. Attempts to automate ECG interpretations using different algorithmic paradigms have existed for decades. However, a robust system or an approach that can automate the detection of a wide range of arrhythmia categories from ECGs captured or acquired from a multitude of sources remains a challenge, given the signal quality and extend of associated artifacts vary. The approach described in this paper takes the application of Deep Learning (DL) in arrhythmia detection to a new dimension, in which it uses class-discriminative visualization to improve interpretability and transparency as an additional step to validate the algorithm. A Convolutional Neural Network (CNN) of 20 rhythm categories was developed using 193,492 single-lead ten-second ECG strips. External validation was done against a test set of 5606 strips collected using Holter device (n=4447), patch (n=311), diagnostic ECG machine (n=806), and smartwatch (n=42), covering a wide variety of devices available in the current market. For IoU (Intersection over Union) score, GradCAM (Gradient-weighted Class Activation Mapping) analysis representing the region weighted by the model for inference was performed on 266 strips against Certified Cardiographic Technician annotations. The model with a weighted average F1 score of 0.94 across 20 rhythm categories had high sensitivity and specificity for critical arrhythmias like Atrial Fibrillation (0.997, 0.955) and Ventricular Tachycardia (0.999, 0.915). Besides, the mean IoU score calculated was 0.56, meaning the region of arrhythmia had a great impact on the predictions made by the model. | P14: 1 | Q14: 1 | R14: 0.5 | S14: 1 | T14: =SUM(Table145[[#This Row],[Relevence 0,1,0.5]:[Findings 0,1,0.5]]) -> 3.5
A15: IEEE Xplore | B15: Conference Proceedings | C15: P. V. R; U. Shanmugam | D15: 2023 | E15: Explainable AI for Medical Imaging: Advancing Transparency and Trust in Diagnostic Decision-Making | F15: 2023 Innovations in Power and Advanced Computing Technologies (i-PACT) | I15: 45444 | M15: 10.1109/i-PACT58649.2023.10434658 | N15: Deep learning_x000D_ Explainable AI_x000D_ Decision making_x000D_ Data models_x000D_ Osteoarthritis_x000D_ Heat maps_x000D_ Residual neural networks_x000D_ Explainable AI (XAI)_x000D_ Artificial Intelligence(AI)_x000D_ Learning Process_x000D_ Explainable model_x000D_ Diagnostic decision | O15: Osteoarthritis (OA) is an existing degenerative joint disease with a potential societal impact, requiring accurate and early diagnosis for effective treatment. In this work, we have deployed deep learning techniques, specifically ResNet50 and VGG16, to predict osteoarthritis from medical imaging data. Remarkably, our models produced an impressive accuracies of 91.0% and 89.5% respectively, showing the efficacy of CNN in OA classification. To further better the interpretability in the predictions of our model ,we used GradCam++ visualization, a technique that enabled us in generating heat maps that highlights the regions crucial for model decision-making. Optimizing GradCam++, we noticed an improvement in accuracy to 93.0%, reinforcing its value in refining model interpretability. The generated heat maps are used not only in understanding the model validation but also in providing clinicians with useful information regarding the areas of concern within the medical images. Our outcomes shows the ability of combining deep learning techniques with visualization tools like GradCam++ to enhance predictive accuracy and to offer trustable and interpretable results. The areas of concern in the heat maps throw light on the specific features influencing the model's decision. This combined method promises for advancing the field of medical image analysis, fostering more accurate and clinically applicable diagnostic tools for osteoarthritis and potentially other medical conditions. | P15: 1 | Q15: 1 | R15: 1 | S15: 1 | T15: =SUM(Table145[[#This Row],[Relevence 0,1,0.5]:[Findings 0,1,0.5]]) -> 4
A16: IEEE Xplore | B16: Conference Proceedings | C16: N. Rahman; S. K. Das | D16: 2022 | E16: A Fusion of Three Custom-Tailored Deep Learning Architectures for Waste Classification | F16: 2022 4th International Conference on Sustainable Technologies for Industry 4.0 (STI) | I16: 45444 | M16: 10.1109/STI56238.2022.10103297 | N16: Waste management_x000D_ Waste materials_x000D_ Biological system modeling_x000D_ Social factors_x000D_ Predictive models_x000D_ Real-time systems_x000D_ Recycling_x000D_ Climate change_x000D_ CNN_x000D_ X-AI_x000D_ EfficientNet_x000D_ Image Hashing_x000D_ Augmentation_x000D_ GradCAM_x000D_ Focal Loss_x000D_ Cross Entropy_x000D_ Albumentation | O16: Population growth is exploding exponentially in this current world. Due to this escalating population and urbanization, the overall amount of waste is experiencing a rapid growth worldwide. Consequently, plenty of waste contributes to climate change, affecting our ecosystems and species. Fortunately, trash management would help alleviate some of these effects since a large quantity of trash is highly biodegradable and recyclable. However, classifying waste manually based on its contents is highly expensive and time-consuming. This is why the classification of wastes based on their contents is a critical criterion for ensuring cost-effective performance throughout recycling procedures. This paper proposes a hybrid deep-learning framework to classify waste into four categories: paper, glass, plastic, and organic. To address the lack of sufficient data, we used the albumentation function to augment the data. Later, in order to remove any duplicates that might have existed in the updated dataset, we also applied an image hashing technique that tackles the problem of overfitting. After preprocessing, we integrate three different models (2 EfficientNet models with noisy-student and imagenet and a custom convolutional neural network model) and provide prediction, and a heatmap of the eXplainable Artificial Intelligence (X-AI) generated images based on the test dataset to improve the trustworthiness of the inference. In comparison to various earlier state-of-the-art studies in the area of waste management, our technique performed substantially better, scoring at around 97% accuracy. | P16: 0 | Q16: 1 | R16: 0.5 | S16: 0.5 | T16: =SUM(Table145[[#This Row],[Relevence 0,1,0.5]:[Findings 0,1,0.5]]) -> 2
A17: IEEE Xplore | B17: Conference Proceedings | C17: U. Rashmi; B. M. Beena; S. Ambesange | D17: 2023 | E17: BrainCrossFed CNN Model for Alzheimer Classification using MRI data and Comparison and Benchmarking proposed model with DINOv2 and ExplainableAI using GradCAM | F17: 2023 International Conference on the Confluence of Advancements in Robotics, Vision and Interdisciplinary Technology Management (IC-RVITM) | I17: 45474 | M17: 10.1109/IC-RVITM60032.2023.10435182 | N17: Computational modeling_x000D_ Magnetic resonance imaging_x000D_ Benchmark testing_x000D_ Brain modeling_x000D_ Data models_x000D_ Artificial intelligence_x000D_ Alzheimer's disease_x000D_ Federated Learning_x000D_ FedAvg_x000D_ Self Supervised Models_x000D_ DINOv2_x000D_ GradCAM_x000D_ BrainCrossFed_x000D_ Alzheimer_x000D_ MRI | O17: Alzheimer is one of the key mental illnesses suffered by 55 million people worldwide and 10 million new patients are added every year. If Alzheimer’s is detected in early stage, then the impact of disease will be reduced. Artificial intelligence (AI) models are helping in early diagnosis using MRI images. For better AI model development, the model needs to be trained over a huge dataset. But Health data privacy is another key concern of data collection, and hence federated learning framework helps models get trained over data without data transferring to cloud platform. Other Key concerns of AI model development is the availability of labeled data and benchmarking the model performance developed on dataset, which is trimmed or is a modified version. As availability of research work on specific data is rare. Currently, researchers have to develop other research models for specific data and such approaches take more time. Also, doctors expect explainability of the model, instead of black box model. Proposed BrainCrossFed model addresses data privacy concerns by avoiding the need for data transfer to cloud and leverage available labeled data at different federated nodes along with a dataset for Alzheimer to compute cross fed average of model weights. Due to the proposed Cross Fed Avg algorithm performance of the proposed deep learning model accuracy is increased from 99.11% to 99.77% close to 100%. Also such cross fed average enables the model to find global minima. Final performance achieved by the proposed model is 99.77%, with 100%. The performance of the model is benchmarked with current well known classification models, State-of-the-Art (SOTA), self supervised models like DINOv2 [1], for the same datasets. DINOv2 model has achieved 98%. Other generic well known models like ResNet101, DenseNet121, and Visual Geometry Group16 (VGG16) and customer models [2] have achieved max performance 97.60%. The GradCAM developed to explain the classification result. | P17: 1 | Q17: 1 | R17: 1 | S17: 1 | T17: =SUM(Table145[[#This Row],[Relevence 0,1,0.5]:[Findings 0,1,0.5]]) -> 4
A18: 1 | B18: Conference Proceedings | C18: R. H. Rifat; A. C. Shruti; M. Kamal; M. G. R. Alam | D18: 2023 | E18: Privacy-Preserving Knee Osteoarthritis Classification: A Federated Learning Approach with GradCAM Visualization | F18: 2023 26th International Conference on Computer and Information Technology (ICCIT) | I18: 45444 | M18: 10.1109/ICCIT60459.2023.10441001 | N18: Data privacy_x000D_ Federated learning_x000D_ Sociology_x000D_ Medical services_x000D_ Osteoarthritis_x000D_ Statistics_x000D_ X-ray imaging_x000D_ MobileNet_x000D_ Resnet_x000D_ DenseNet_x000D_ Knee Osteoarthritis_x000D_ Medical Images_x000D_ XAI_x000D_ Grad-CAM | O18: Knee Osteoarthritis (KOA) poses a significant global health challenge, impacting a substantial population. The conventional detection process involves multiple tests and meticulous examination by experienced physicians, which is time-consuming and susceptible to misclassification due to subtle variations in X-ray images. Additionally, privacy concerns hinder the sharing of sensitive data like X-rays. This study employs Federated Learning with pre-trained architectures (DenseNet-169, Inception-v2, and MobileNet-v2) to classify three KOA severity grades, utilizing two clients to ensure data privacy. The aim is to develop a generalized model for disease classification, improving efficiency while ensuring the confidentiality of patient information. DenseNet-169 excelled with an F1 score of 81% and an accuracy of 82%, while Inception-v2 and MobileNet-v2 performed well with slight F1 score variations. Moreover, the exploration of GradCAM visualization techniques is conducted to improve interpretability, highlighting the capability of this approach to effectively tackle the intricate challenges linked to Knee Osteoarthritis detection. | P18: 1 | Q18: 1 | R18: 1 | S18: 1 | T18: =SUM(Table145[[#This Row],[Relevence 0,1,0.5]:[Findings 0,1,0.5]]) -> 4
A19: IEEE Xplore | B19: Conference Proceedings | C19: S. Sengupta; J. Loomba; S. Sharma; D. E. Brown; L. Thorpe; M. A. Haendel; C. G. Chute; S. Hong | D19: 2022 | E19: Analyzing historical diagnosis code data from NIH N3C and RECOVER Programs using deep learning to determine risk factors for Long Covid | F19: 2022 IEEE International Conference on Bioinformatics and Biomedicine (BIBM) | I19: 2797-2802 | M19: 10.1109/BIBM55620.2022.9994851 | N19: COVID-19_x000D_ Deep learning_x000D_ Codes_x000D_ Medical conditions_x000D_ Market research_x000D_ National Institutes of Health_x000D_ Electronic medical records_x000D_ EHR_x000D_ GradCAM | O19: Post-acute sequelae of SARS-CoV-2 infection (PASC) or Long COVID is an emerging medical condition that has been observed in several patients with a positive diagnosis for COVID-19. Historical Electronic Health Records (EHR) like diagnosis codes, lab results and clinical notes have been analyzed using deep learning and have been used to predict future clinical events. In this paper, we propose an interpretable deep learning approach to analyze historical diagnosis code data from the National COVID Cohort Collective (N3C)1 to find the risk factors contributing to developing Long COVID. Using our deep learning approach, we are able to predict if a patient is suffering from Long COVID from a temporally ordered list of diagnosis codes up to 45 days post the first COVID positive test or diagnosis for each patient, with an accuracy of 70.48%. We are then able to examine the trained model using Gradient-weighted Class Activation Mapping (GradCAM) to give each input diagnoses a score. The highest scored diagnosis were deemed to be the most important for making the correct prediction for a patient. We also propose a way to summarize these top diagnoses for each patient in our cohort and look at their temporal trends to determine which codes contribute towards a positive Long COVID diagnosis. | P19: 0 | Q19: 1 | R19: 0.5 | S19: 0.5 | T19: =SUM(Table145[[#This Row],[Relevence 0,1,0.5]:[Findings 0,1,0.5]]) -> 2
A20: IEEE Xplore | B20: Conference Proceedings | C20: Y. Shu; A. V. d. Hengel; L. Liu | D20: 2023 | E20: Learning Common Rationale to Improve Self-Supervised Representation for Fine-Grained Visual Recognition Problems | F20: 2023 IEEE/CVF Conference on Computer Vision and Pattern Recognition (CVPR) | I20: 11392-11401 | M20: 10.1109/CVPR52729.2023.01096 | N20: Representation learning_x000D_ Visualization_x000D_ Computer vision_x000D_ Source coding_x000D_ Aggregates_x000D_ Fitting_x000D_ Detectors_x000D_ Self-supervised or unsupervised representation learning | O20: Self-supervised learning (SSL) strategies have demonstrated remarkable performance in various recognition tasks. However, both our preliminary investigation and recent studies suggest that they may be less effective in learning representations for fine-grained visual recognition (FGVR) since many features helpful for optimizing SSL objectives are not suitable for characterizing the subtle differences in FGVR. To overcome this issue, we propose learning an additional screening mechanism to identify discriminative clues commonly seen across instances and classes, dubbed as common rationales in this paper. Intuitively, common rationales tend to correspond to the discriminative patterns from the key parts of foreground objects. We show that a common rationale detector can be learned by simply exploiting the GradCAM induced from the SSL objective without using any pre-trained object parts or saliency detectors, making it seamlessly to be integrated with the existing SSL process. Specifically, we fit the GradCAM with a branch with limited fitting capacity, which allows the branch to capture the common rationales and discard the less common discriminative patterns. At the test stage, the branch generates a set of spatial weights to selectively aggregate features representing an instance. Extensive experimental results on four visual tasks demonstrate that the proposed method can lead to a significant improvement in different evaluation settings.11The source code will be publicly available at:https://github.com/GANPerf/LCR | P20: 0 | Q20: 1 | R20: 0.5 | S20: 0.5 | T20: =SUM(Table145[[#This Row],[Relevence 0,1,0.5]:[Findings 0,1,0.5]]) -> 2
A21: IEEE Xplore | B21: Conference Proceedings | C21: K. Siddiqui; T. E. Doyle | D21: 2022 | E21: Trust Metrics for Medical Deep Learning Using Explainable-AI Ensemble for Time Series Classification | F21: 2022 IEEE Canadian Conference on Electrical and Computer Engineering (CCECE) | I21: 370-377 | M21: 10.1109/CCECE49351.2022.9918458 | N21: Measurement_x000D_ Deep learning_x000D_ Medical devices_x000D_ Time series analysis_x000D_ Decision making_x000D_ Electrocardiography_x000D_ Stability analysis_x000D_ trust_x000D_ explainable AI_x000D_ XAI_x000D_ quantification_x000D_ time series_x000D_ ECG | O21: Trustworthiness is a roadblock in mass adoption of artificial intelligence (AI) in medicine. This research developed a framework to explore the trustworthiness as it applies to AI in medicine with respect to common stakeholders in medical device development. Within this framework the element of explainability of AI models was explored by evaluating an ensemble of explainable AI (XAI) methods. In current literature a litany of XAI methods are available that provide a variety of insights into the learning and function of AI models. XAI methods provide a human readable output for the AI’s learned processes. These XAI methods provide very subjective outputs with varying degrees of quality. Currently, there are no metrics or methods of objectively evaluating XAI generated explanations against outputs from other XAI methods or to test repeatable consistency of explanations from a single XAI method. This research presents two constituent elements, similarity and stability, to explore the concept of explainability for time series medical data (ECG). Thus providing a repeatable and testable framework to evaluate XAI methods and their generated explanations. This is accomplished using subject matter expert (SME) annotated ECG signals (time-series signals) represented as images to AI models and XAI methods. The XAI methods of Vanilla Saliency, SmoothGrad, GradCAM and GradCAM++ were used to generate XAI outputs for a VGG-16 based deep learning classification model. The framework provides insights about XAI method generated explanations for the AI and how closely that learning corresponds to SME decision making. It also objectively evaluates how closely explanations generated by any XAI method resemble outputs from other XAI methods. Lastly, the framework provides insights about possible enhancements to XAI to go beyond what was identified by the SMEs in their decision making. | P21: 0 | Q21: 1 | R21: 0.5 | S21: 0.5 | T21: =SUM(Table145[[#This Row],[Relevence 0,1,0.5]:[Findings 0,1,0.5]]) -> 2
A22: IEEE Xplore | B22: Journal Article | C22: P. Singh; A. Sharma | D22: 2022 | E22: Interpretation and Classification of Arrhythmia Using Deep Convolutional Network | F22: IEEE Transactions on Instrumentation and Measurement | G22: 71 | I22: 45627 | M22: 10.1109/TIM.2022.3204316 | N22: Electrocardiography_x000D_ Computational modeling_x000D_ Feature extraction_x000D_ Deep learning_x000D_ Neural networks_x000D_ Data models_x000D_ Predictive models_x000D_ Arrhythmia_x000D_ convolutional neural network (CNN)_x000D_ electrocardiogram (ECG)_x000D_ explainable artificial intelligence (XAI)_x000D_ local interpretable model-agnostic explanations (LIME)_x000D_ SHapley Additive exPlanations (SHAP) | O22: Electrocardiogram (ECG) signal analysis can be time-consuming, tedious, and error-prone. Therefore, automated analysis is need of time that will assist clinicians in detecting cardiac abnormalities accurately and efficiently. Recently, deep learning (DL) models have shown unprecedented progress and strong arrhythmia classification capabilities, but their deployment in the medical sector is constrained due to their “black-box” nature. This article proposes a robust explainability method to assist in explaining the underlying decision-making process in deep neural networks (DNNs) and help provide feedback on biases that would benefit in improving DNN models. To achieve these objectives, initially, a DL model is trained on the MIT-BIH Arrhythmia Database and their classification performance is evaluated. The classification findings are then interpreted using the post-hoc explanation methods such as the SHapley Additive exPlanations (SHAP), local interpretable model-agnostic explanations (LIME), and gradient-weighted class activation mapping (Grad-CAM) that interpret the decision rationale. As these methods are initially proposed for image applications therefore a new masking approach is proposed to cater these post-hoc explainability methods for ECG time-series data. After evaluating these methods for ECG arrhythmia classification, several drawbacks are drawn such as they fail to locate a feature’s importance if there are multiple occurrences of the same feature in a signal and also, SHAP and LIME perform random perturbations that sometimes produce unreliable explanations. Therefore, to overcome the drawbacks associated with these post-hoc explainability methods on time-series data, a novel K-GradCam method is proposed. The proposed K-GradCam method ensemble the benefits of these gradient-based and perturbation-based approaches and has demonstrated advantages over SHAP, Grad-CAM and LIME in terms of interpreting the models’ decisions. To compare the proposed technique with post-hoc explainability methods quantitatively, the confidence index of the proposed method is evaluated using dice loss. The proposed method shares 71% similarity with SHAP and 81% similarity with Grad-CAM methods; however, it shares the benefits of both methods and is computationally faster than SHAP and LIME. | P22: 0 | Q22: 1 | R22: 0.5 | S22: 0.5 | T22: =SUM(Table145[[#This Row],[Relevence 0,1,0.5]:[Findings 0,1,0.5]]) -> 2
A23: IEEE Xplore | B23: Conference Proceedings | C23: K. S. Srikanth; T. K. Ramesh; S. Palaniswamy; R. Srinivasan | D23: 2022 | E23: XAI based model evaluation by applying domain knowledge | F23: 2022 IEEE International Conference on Electronics, Computing and Communication Technologies (CONECCT) | I23: 45444 | M23: 10.1109/CONECCT55679.2022.9865816 | N23: Training_x000D_ Decision support systems_x000D_ Face recognition_x000D_ Computational modeling_x000D_ Communications technology_x000D_ Facial features_x000D_ XAI_x000D_ CNN_x000D_ Deep Learning_x000D_ Artificial intelligence | O23: Artificial intelligence(AI) is used in decision support systems which learn and perceive features as a function of the number of layers and the weights computed during training. Due to their inherent black box nature, it is insufficient to consider accuracy, precision and recall as metrices for evaluating a model's performance. Domain knowledge is also essential to identify features that are significant by the model to arrive at its decision. In this paper, we consider a use case of face mask recognition to explain the application and benefits of XAI. Eight models used to solve the face mask recognition problem were selected. GradCAM Explainable AI (XAI) is used to explain the state-of-art models. Models that were selecting incorrect features were eliminated even though, they had a high accuracy. Domain knowledge relevant to face mask recognition viz., facial feature importance is applied to identify the model that picked the most appropriate features to arrive at the decision. We demonstrate that models with high accuracies need not be necessarily select the right features. In applications requiring rapid deployment, this method can act as a deciding factor in shortlisting models with a guarantee that the models are looking at the right features for arriving at the classification. Furthermore, the outcomes of the model can be explained to the user enhancing their confidence on the AI model being deployed in the field. | P23: 0 | Q23: 0 | R23: 0.5 | S23: 1 | T23: =SUM(Table145[[#This Row],[Relevence 0,1,0.5]:[Findings 0,1,0.5]]) -> 1.5
A24: IEEE Xplore | B24: Conference Proceedings | C24: W. Tan; J. Renkhoff; A. Velasquez; Z. Wang; L. Li; J. Wang; S. Niu; F. Yang; Y. Liu; H. Song | D24: 2023 | E24: NoiseCAM: Explainable AI for the Boundary Between Noise and Adversarial Attacks | F24: 2023 IEEE International Conference on Fuzzy Systems (FUZZ) | I24: 45505 | M24: 10.1109/FUZZ52849.2023.10309766 | N24: Deep learning_x000D_ Perturbation methods_x000D_ Gaussian noise_x000D_ Artificial neural networks_x000D_ Behavioral sciences_x000D_ Artificial intelligence_x000D_ Fuzzy systems | O24: Deep Learning (DL) and Deep Neural Networks (DNNs) are widely used in various domains. However, adversarial attacks can easily mislead a neural network and lead to wrong decisions. Defense mechanisms are highly preferred in safety- critical applications. In this paper, firstly, we use the gradient class activation map (GradCAM) to analyze the behavior deviation of the VGG-16 network when its inputs are mixed with adversarial perturbation or Gaussian noise. In particular, our method can locate vulnerable layers that are sensitive to adversarial perturbation and Gaussian noise. We also show that the behavior deviation of vulnerable layers can be used to detect adversarial examples. Secondly, we propose a novel NoiseCAM algorithm that integrates information from globally and pixel- level weighted class activation maps. Our algorithm is highly sensitive to adversarial perturbations and will not respond to Gaussian random noise mixed in the inputs. Third, we compare detecting adversarial examples using both behavior deviation and NoiseCAM, and we show that NoiseCAM outperforms behavior deviation modeling in its overall performance. Our work could provide a useful tool to defend against certain types of adversarial attacks on deep neural networks. | P24: 1 | Q24: 1 | R24: 0.5 | S24: 1 | T24: =SUM(Table145[[#This Row],[Relevence 0,1,0.5]:[Findings 0,1,0.5]]) -> 3.5
A25: IEEE Xplore | B25: Conference Proceedings | C25: S. Tasneem; K. A. Islam | D25: 2023 | E25: Development of Trustable Deep Learning Model in Remote Sensing through Explainable-AI Method Selection | F25: 2023 IEEE 14th Annual Ubiquitous Computing, Electronics & Mobile Communication Conference (UEMCON) | I25: 0261-0267 | M25: 10.1109/UEMCON59035.2023.10316012 | N25: Deep learning_x000D_ Measurement_x000D_ Systematics_x000D_ Roads_x000D_ Atmospheric modeling_x000D_ Sensors_x000D_ US Department of Defense_x000D_ Explainable-AI_x000D_ Machine Learning_x000D_ Trustable Deep Learning_x000D_ Remote Sensing | O25: Remote sensing-based sensors are considered a pivotal medium to monitor remote objects by security-critical government organizations, e.g., DOD, DHS, and EPA. Historically, human operators used manual mapping in monitoring or detecting an object using remote sensing sensors, e.g., multi-spectral images. Deep learning algorithms can automatically identify and learn multi-spectral, multi-temporal, and multi-modality features of remote sensing datasets while detecting objects. They are also known as black box models because they lack clarity in decision-making. In this paper, we compared two explainable AI models, Grad-CAM and Score-CAM, to interpret the decisions in two multispectral datasets: UC-Merced and EuroSat. These datasets contain classes of land use, such as airplanes and buildings, and objects related to land cover, like forests and rivers. In the empirical analysis, we identified that ScoreCAM performed better than GradCAM based on three evaluation metrics: ROAD, SIC, and infidelity in UC-Merced and EuroSat datasets. | P25: 0 | Q25: 1 | R25: 0 | S25: 0.5 | T25: =SUM(Table145[[#This Row],[Relevence 0,1,0.5]:[Findings 0,1,0.5]]) -> 1.5
A26: IEEE Xplore | B26: Conference Proceedings | C26: Y. X. Teoh; A. Othmani; S. L. Goh; J. Usman; K. W. Lai | D26: 2023 | E26: Predicting Knee Osteoarthritis Pain Severity through A Deep Hybrid Learning Model: Data from the Osteoarthritis Initiative | F26: 2023 IEEE International Conference on Bioinformatics and Biomedicine (BIBM) | I26: 4148-4153 | M26: 10.1109/BIBM58861.2023.10385415 | N26: Radiography_x000D_ Deep learning_x000D_ Pain_x000D_ Biological system modeling_x000D_ Decision making_x000D_ Receivers_x000D_ Predictive models_x000D_ deep neural networks_x000D_ diagnosis_x000D_ knee osteoarthritis_x000D_ machine learning_x000D_ pain prediction | O26: Knee pain is the most common disabling symptom in osteoarthritis (OA). High correlation between knee pain and multiple OA features is reported in literature, but it has not been validated using deep learning models. In this study, we aim to develop a deep hybrid learning model for pain prediction directly from radiography images. We obtain an optimal hybrid model with VGG16, GAP, and KNN combination that gave a maximum of 89.75% accuracy and 0.91 Cohen’s kappa scores. The pain prediction of our proposed approach has achieved 0.99 of receiver operating characteristic area under curve (ROC-AUC). Binary pain classification has demonstrated better precision-recall curve pattern as compared to 11-class, 4-class, and 3-class pain prediction tasks. Based on Gradient-weighted Class Activation Mapping (GradCAM) analysis, joint center was identified as a key area that significantly contributes to the network’s decision-making process. The results of this study demonstrate the capability of hybrid deep learning model in predicting baseline pain severity from plain radiographs, therefore improving future OA pain assessment efforts. | P26: 0 | Q26: 1 | R26: 0.5 | S26: 0.5 | T26: =SUM(Table145[[#This Row],[Relevence 0,1,0.5]:[Findings 0,1,0.5]]) -> 2
A27: IEEE Xplore | B27: Conference Proceedings | C27: D. E. Turan; E. Aptoula; A. Ertürk; G. Taskin | D27: 2023 | E27: Interpreting Hyperspectral Remote Sensing Image Classification Methods Via Explainable Artificial Intelligence | F27: IGARSS 2023 - 2023 IEEE International Geoscience and Remote Sensing Symposium | I27: 5950-5953 | M27: 10.1109/IGARSS52108.2023.10282341 | N27: Backpropagation_x000D_ Decision making_x000D_ Behavioral sciences_x000D_ Convolutional neural networks_x000D_ Artificial intelligence_x000D_ Image classification_x000D_ Hyperspectral imaging_x000D_ Explainable artificial intelligence_x000D_ interpretability_x000D_ hyperspectral images_x000D_ GradCam_x000D_ guided backpropagation | O27: This study addresses the explainability challenges of deep-learning models in the context of hyperspectral remote sensing image classification. Three prominent explainable artificial intelligence methods, namely GradCAM, GradCAM++, and Guided Backpropagation, have been employed in order to comprehend the decision-making process of a typical convolutional neural network model during spatial-spectral hyperspectral image classification. The experiments that have been conducted investigate the impact of pixel patch sizes on spatial attention, as well as spectral band importance. The findings provide insights into the behavior of both convolutional neural networks, as well as the comparative performance of explainability techniques. | P27: 1 | Q27: 1 | R27: 1 | S27: 0.5 | T27: =SUM(Table145[[#This Row],[Relevence 0,1,0.5]:[Findings 0,1,0.5]]) -> 3.5
A28: IEEE Xplore | B28: Journal Article | C28: D. Varam; R. Mitra; M. Mkadmi; R. A. Riyas; D. A. Abuhani; S. Dhou; A. Alzaatreh | D28: 2023 | E28: Wireless Capsule Endoscopy Image Classification: An Explainable AI Approach | F28: IEEE Access | G28: 11 | I28: 105262-105280 | M28: 10.1109/ACCESS.2023.3319068 | N28: Solid modeling_x000D_ Analytical models_x000D_ Endoscopes_x000D_ Classification algorithms_x000D_ Feature extraction_x000D_ Wireless communication_x000D_ Gastrointestinal tract_x000D_ Deep learning_x000D_ Artificial intelligence_x000D_ Machine learning_x000D_ explainable AI_x000D_ gastrointestinal diseases_x000D_ vision transformer_x000D_ wireless capsule endoscopy | O28: Deep Learning has contributed significantly to the advances made in the fields of Medical Imaging and Computer Aided Diagnosis (CAD). Although a variety of Deep Learning (DL) models exist for the purposes of image classification in the medical domain, more analysis needs to be conducted on their decision-making processes. For this reason, several novel Explainable AI (XAI) techniques have been proposed in recent years to better understand DL models. Currently, medical professionals rely on visual inspections to diagnose potential diseases in endoscopic imaging in the preliminary stages. However, we believe that the use of automated systems can enhance both the efficiency for such diagnoses. The aim of this study is to increase the reliability of model predictions within the field of endoscopic imaging by implementing several transfer learning models on a balanced subset of Kvasir-capsule, a Wireless Capsule Endoscopy imaging dataset. This subset includes the top 9 classes of the dataset for training and testing. The results obtained were an F1-score of 97% ±1% for the Vision Transformer model, although other models such as MobileNetv3Large and ResNet152v2 were also able to achieve F1-scores of over 90%. These are currently the highest-reported metrics on this data, improving upon prior studies done on the same dataset. The heatmaps of several XAI techniques, including GradCAM, GradCAM++, LayersCAM, LIME, and SHAP have been presented in image form and evaluated according to their highlighted regions of importance. This is in an effort to better understand the decisions of the top-performing DL models and look beyond their black-box nature. | P28: 1 | Q28: 1 | R28: 0.5 | S28: 1 | T28: =SUM(Table145[[#This Row],[Relevence 0,1,0.5]:[Findings 0,1,0.5]]) -> 3.5
A29: ScienceDirect | B29: Journal Article | C29: J. P. Amorim; P. H. Abreu; J. Santos; M. Cortes; V. Vila | D29: 2023 | E29: Evaluating the faithfulness of saliency maps in explaining deep learning models using realistic perturbations | F29: Information Processing & Management | G29: 60 | H29: 2 | I29: 103225 | L29: https://www.sciencedirect.com/science/article/pii/S0306457322003260 | M29: https://doi.org/10.1016/j.ipm.2022.103225 | N29: Deep learning_x000D_ Interpretability_x000D_ Saliency map_x000D_ Convolutional neural network | O29: Deep Learning has reached human-level performance in several medical tasks including classification of histopathological images. Continuous effort has been made at finding effective strategies to interpret these types of models, among them saliency maps, which depict the weights of the pixels on the classification as an heatmap of intensity values, have been by far the most used for image classification. However, there is a lack of tools for the systematic evaluation of saliency maps, and existing works introduce non-natural noise such as random or uniform values. To address this issue, we propose an approach to evaluate the faithfulness of the saliency maps by introducing natural perturbations in the image, based on oppose-class substitution, and studying their impact on evaluation metrics adapted from saliency models. We validate the proposed approach on a breast cancer metastases detection dataset PatchCamelyon with 327,680 patches of histopathological images of sentinel lymph node sections. Results show that GradCAM, Guided-GradCAM and gradient-based saliency map methods are sensitive to natural perturbations and correlate to the presence of tumor evidence in the image. Overall, this approach proves to be a solution for the validation of saliency map methods without introducing confounding variables and shows potential for application on other medical imaging tasks. | P29: 0 | Q29: 1 | R29: 0 | S29: 0.5 | T29: =SUM(Table145[[#This Row],[Relevence 0,1,0.5]:[Findings 0,1,0.5]]) -> 1.5
A30: ScienceDirect | B30: Journal Article | C30: D. Bajhaiya; S. Narayanan Unni | D30: 2024 | E30: Deep learning-enabled detection and localization of gastrointestinal diseases using wireless-capsule endoscopic images | F30: Biomedical Signal Processing and Control | G30: 93 | I30: 106125 | L30: https://www.sciencedirect.com/science/article/pii/S1746809424001836 | M30: https://doi.org/10.1016/j.bspc.2024.106125 | N30: Gastrointestinal disease_x000D_ Wireless capsule endoscopy_x000D_ Convolutional neural network_x000D_ Deep learning_x000D_ GradCAM_x000D_ Guided-GradCAM | O30: Purpose Detection of gastrointestinal (GI) diseases involves several expensive, challenging, and time-consuming procedures. Deep learning techniques-based computer-aided diagnosis can significantly reduce the costs associated with examinations while enhancing the accuracy and speed of diagnosis. Methods This study developed a 13-layered convolutional neural network (CNN) model named as GINet for diagnosing GI diseases such as angiectasia, lymphangiectasia, GI bleeding, and ulcer. The model was trained, validated, and tested on 3658 wireless capsule endoscopy images. Results The GINet achieved an overall classification accuracy of 99% (standard error (SE): 0.7%) on the test dataset. The model achieved an overall sensitivity of 99.6 % (SE:0.5%) and specificity of 99.86%(SE:0.3%) on the test. We additionally employ GradCAM and Guided-GradCAM technique to enhance the interpretability and localization of detected lesions. Furthermore, the study effectively addressed biases that could arise from combining video frames of the same patients through domain adaptation techniques, ensuring accurate and unbiased analysis. Conclusions The results revealed that the GINet can classify GI diseases with higher sensitivity and specificity. Furthermore, the proposed approach has the potential for first-hand mass screening efforts, where advanced disease stages can be identified. This approach additionally helps gastroenterologists make quick and accurate treatment decisions at reduced time and cost. | P30: 1 | Q30: 1 | R30: 1 | S30: 1 | T30: =SUM(Table145[[#This Row],[Relevence 0,1,0.5]:[Findings 0,1,0.5]]) -> 4
A31: ScienceDirect | B31: Journal Article | C31: P. Besson; T. Parrish; A. K. Katsaggelos; S. K. Bandt | D31: 2021 | E31: Geometric deep learning on brain shape predicts sex and age | F31: Computerized Medical Imaging and Graphics | G31: 91 | I31: 101939 | L31: https://www.sciencedirect.com/science/article/pii/S0895611121000884 | M31: https://doi.org/10.1016/j.compmedimag.2021.101939 | N31: Geometric deep learning_x000D_ Brain shape_x000D_ Brain mapping_x000D_ Precision medicine_x000D_ Population health_x000D_ Big data | O31: The complex relationship between the shape and function of the human brain remains elusive despite extensive studies of cortical folding over many decades. The analysis of cortical gyrification presents an opportunity to advance our knowledge about this relationship, and better understand the etiology of a variety of pathologies involving diverse degrees of cortical folding abnormalities. Hypothesis-driven surface-based approaches have been shown to be particularly efficient in their ability to accurately describe unique features of the folded sheet topology of the cortical ribbon. However, the utility of these approaches has been blunted by their reliance on manually defined features aiming to capture the relevant geometric properties of cortical folding. In this paper, we propose an entirely novel, data-driven deep-learning based method to analyze the brain’s shape that eliminates this reliance on manual feature definition. This method builds on the emerging field of geometric deep-learning and uses traditional convolutional neural network architecture uniquely adapted to the surface representation of the cortical ribbon. This method is a complete departure from prior brain MRI CNN investigations, all of which have relied on three dimensional MRI data and interpreted features of the MRI signal for prediction. MRI data from 6410 healthy subjects obtained from 11 publicly available data repositories were used for analysis. Ages ranged from 6 to 89 years. Both inner and outer cortical surfaces were extracted using Freesurfer and then registered into MNI space. For purposes of method development, both a classification and regression challenge were introduced for network learning including sex and age prediction, respectively. Two independent graph convolutional neural networks (gCNNs) were trained, the first of which to predict subject’s self-identified sex, the second of which to predict subject’s age. Class Activation Maps (CAM) and Regression Activation Maps (RAM) were constructed respectively to map the topographic distribution of the most influential brain regions involved in the decision process for each gCNN. Using this approach, the gCNN was able to predict a subject’s sex with an average accuracy of 87.99 % and achieved a Person’s coefficient of correlation of 0.93 with an average absolute error 4.58 years when predicting a subject’s age. We believe this shape-based convolutional classifier offers a novel, data-driven approach to define biomedically relevant features from the brain at both the population and single subject levels and therefore lays a critical foundation for future precision medicine applications. | P31: 0 | Q31: 1 | R31: 0 | S31: 0.5 | T31: =SUM(Table145[[#This Row],[Relevence 0,1,0.5]:[Findings 0,1,0.5]]) -> 1.5
A32: ScienceDirect | B32: Journal Article | C32: L. Bloch; C. M. Friedrich | D32: 2024 | E32: Systematic comparison of 3D Deep learning and classical machine learning explanations for Alzheimer’s Disease detection | F32: Computers in Biology and Medicine | G32: 170 | I32: 108029 | L32: https://www.sciencedirect.com/science/article/pii/S0010482524001136 | M32: https://doi.org/10.1016/j.compbiomed.2024.108029 | N32: Alzheimer’s Disease_x000D_ Interpretable Machine Learning_x000D_ SHAP_x000D_ LIME_x000D_ GradCAM_x000D_ 3D CNN | O32: Black-box deep learning (DL) models trained for the early detection of Alzheimer’s Disease (AD) often lack systematic model interpretation. This work computes the activated brain regions during DL and compares those with classical Machine Learning (ML) explanations. The architectures used for DL were 3D DenseNets, EfficientNets, and Squeeze-and-Excitation (SE) networks. The classical models include Random Forests (RFs), Support Vector Machines (SVMs), eXtreme Gradient Boosting (XGBoost), Light Gradient Boosting (LightGBM), Decision Trees (DTs), and Logistic Regression (LR). For explanations, SHapley Additive exPlanations (SHAP) values, Local Interpretable Model-agnostic Explanations (LIME), Gradient-weighted Class Activation Mapping (GradCAM), GradCAM++ and permutation-based feature importance were implemented. During interpretation, correlated features were consolidated into aspects. All models were trained on the Alzheimer’s Disease Neuroimaging Initiative (ADNI) dataset. The validation includes internal and external validation on the Australian Imaging and Lifestyle flagship study of Ageing (AIBL) and the Open Access Series of Imaging Studies (OASIS). DL and ML models reached similar classification performances. Regarding the brain regions, both types focus on different regions. The ML models focus on the inferior and middle temporal gyri, and the hippocampus, and amygdala regions previously associated with AD. The DL models focus on a wider range of regions including the optical chiasm, the entorhinal cortices, the left and right vessels, and the 4th ventricle which were partially associated with AD. One explanation for the differences is the input features (textures vs. volumes). Both types show reasonable similarity to a ground truth Voxel-Based Morphometry (VBM) analysis. Slightly higher similarities were measured for ML models. | P32: 0 | Q32: 1 | R32: 0 | S32: 0.5 | T32: =SUM(Table145[[#This Row],[Relevence 0,1,0.5]:[Findings 0,1,0.5]]) -> 1.5
A33: ScienceDirect | B33: Journal Article | C33: D. Chowdhury; A. Das; A. Dey; S. Banerjee; M. Golec; D. Kollias; M. Kumar; G. Kaur; R. Kaur; R. C. Arya; G. Wander; P. Wander; G. S. Wander; A. K. Parlikad; S. S. Gill; S. Uhlig | D33: 2023 | E33: CoviDetector: A transfer learning-based semi supervised approach to detect Covid-19 using CXR images | F33: BenchCouncil Transactions on Benchmarks, Standards and Evaluations | G33: 3 | H33: 2 | I33: 100119 | L33: https://www.sciencedirect.com/science/article/pii/S2772485923000364 | M33: https://doi.org/10.1016/j.tbench.2023.100119 | N33: Machine learning_x000D_ Deep neural network_x000D_ Transfer learning_x000D_ Android app_x000D_ Chest X-ray (CXR)_x000D_ COVID-19_x000D_ Healthcare | O33: COVID-19 was one of the deadliest and most infectious illnesses of this century. Research has been done to decrease pandemic deaths and slow down its spread. COVID-19 detection investigations have utilised Chest X-ray (CXR) images with deep learning techniques with its sensitivity in identifying pneumonic alterations. However, CXR images are not publicly available due to users’ privacy concerns, resulting in a challenge to train a highly accurate deep learning model from scratch. Therefore, we proposed CoviDetector, a new semi-supervised approach based on transfer learning and clustering, which displays improved performance and requires less training data. CXR images are given as input to this model, and individuals are categorised into three classes: (1) COVID-19 positive; (2) Viral pneumonia; and (3) Normal. The performance of CoviDetector has been evaluated on four different datasets, achieving over 99% accuracy on them. Additionally, we generate heatmaps utilising Grad-CAM and overlay them on the CXR images to present the highlighted areas that were deciding factors in detecting COVID-19. Finally, we developed an Android app to offer a user-friendly interface. We release the code, datasets and results’ scripts of CoviDetector for reproducibility purposes; they are available at: https://github.com/dasanik2001/CoviDetector | P33: 0 | Q33: 0.5 | R33: 0.5 | S33: 1 | T33: =SUM(Table145[[#This Row],[Relevence 0,1,0.5]:[Findings 0,1,0.5]]) -> 2
A34: ScienceDirect | B34: Journal Article | C34: T. Faruk; L. C. Shum; A. Iaboni; S. S. Khan | D34: 2023 | E34: Walking path images from real-time location data predict degree of cognitive impairment | F34: Artificial Intelligence in Medicine | G34: 144 | I34: 102657 | L34: https://www.sciencedirect.com/science/article/pii/S0933365723001719 | M34: https://doi.org/10.1016/j.artmed.2023.102657 | N34: Dementia classification_x000D_ Walking patterns_x000D_ Artificial Intelligence_x000D_ Deep learning_x000D_ Real-time location systems_x000D_ Classification Activation Maps_x000D_ Health monitoring technology | O34: Background We propose a novel approach that uses spatial walking patterns produced by real-time location systems to classify the severity of cognitive impairment (CI) among residents of a memory care unit. Methods Each participant was classified as “No-CI”, “Mild-Moderate CI” or “Severe CI” based on their Mini-Mental State Examination scores. The location data was distributed into windows of various durations (5, 10, 15 and 30 min) and transformed into images used to train a custom convolutional neural network (CNN) at each window size. Class Activation Mapping was applied to the top-performing models to determine the features of images associated with each class. Results The best performing model achieved an accuracy of 87.38 % (30-min window length) with an overall pattern that larger window sizes perform better. The class activation maps were effectively consolidated into a Cognitive Impairment Classification Value (CICV) score that distinguishes between No-CI, Mild-Moderate CI, and Severe CI. Conclusion The class activation maps show that the CNN made relevant and intuitive distinctions for paths corresponding to each class. Future work should validate the proposed techniques with participants who are well-characterized clinically, over larger and diversified settings, and towards classification of neuropsychiatric symptoms such as motor agitation, mood, or apathy. | P34: 0 | Q34: 0 | R34: 0.5 | S34: 1 | T34: =SUM(Table145[[#This Row],[Relevence 0,1,0.5]:[Findings 0,1,0.5]]) -> 1.5
A35: ScienceDirect | B35: Journal Article | C35: S. Feng; D. Zhao; Q. Guan; J. Li; Z. Liu; Z. Jin; G. Li; T. Xu | D35: 2022 | E35: A deep convolutional neural network-based wavelength selection method for spectral characteristics of rice blast disease | F35: Computers and Electronics in Agriculture | G35: 199 | I35: 107199 | L35: https://www.sciencedirect.com/science/article/pii/S0168169922005154 | M35: https://doi.org/10.1016/j.compag.2022.107199 | N35: Rice blast_x000D_ Hyperspectral_x000D_ Characteristic wavelength_x000D_ Deep convolutional neural network_x000D_ Visualization | O35: Characteristic wavelength selection is a research hotspot in hyperspectral data processing and a key to improving the accuracy of identifying the degree of rice blast infection. This study combines deep learning and visualization techniques to create a wavelength selection method for spectral features of rice blast. A deep convolutional neural (DCNN) structure was designed by combining the convolutional block attention module (CBAM) with residual network (ResNet) to learn different classes of disease features. And the guided grade-weighted heatmap (Guided-GradHM) of the last layer of convolution was obtained using the guided gradient-weighted class activation mapping (Guided-GradCAM) method. Then the spectral characteristic wavelengths were selected based on the average Guided-GradHM of different disease levels. Finally, statistical analysis (JM distance, within-class scatter) and comparative modeling analysis were used to verify the method's validity in this study. The results show that the characteristic wavelengths selected by the Guided-GradCAM method based on the ResNet-CBAM network structure have good inter-class separability and intra-class aggregation, with JM distance greater than 1.9 and within-class scatter less than 0.4. Meanwhile, the random forest (RF) and support vector machine (SVM) models constructed from the spectral characteristic wavelengths selected by the Guided-GradCAM method achieved the best disease level classification accuracy, with overall accuracy (OA) and Kappa of 97.21% and 96.55%, 96.51%, and 95.69%, respectively. Overall, this research method can more accurately select the spectral characteristic wavelengths of different disease levels of rice blast and can provide a more effective method for accurate identification and timely control of the disease. | P35: 0 | Q35: 0.5 | R35: 0.5 | S35: 1 | T35: =SUM(Table145[[#This Row],[Relevence 0,1,0.5]:[Findings 0,1,0.5]]) -> 2
A36: ScienceDirect | B36: Journal Article | C36: N. A. Hroub; A. N. Alsannaa; M. Alowaifeer; M. Alfarraj; E. Okafor | D36: 2024 | E36: Explainable deep learning diagnostic system for prediction of lung disease from medical images | F36: Computers in Biology and Medicine | G36: 170 | I36: 108012 | L36: https://www.sciencedirect.com/science/article/pii/S0010482524000969 | M36: https://doi.org/10.1016/j.compbiomed.2024.108012 | N36: Deep learning_x000D_ Explainable artificial intelligence_x000D_ Medical imaging_x000D_ Software deployment | O36: Around the globe, respiratory lung diseases pose a severe threat to human survival. Based on a central goal to reduce contiguous transmission from infected to healthy persons, several technologies have evolved for diagnosing lung pathologies. One of the emerging technologies is the utility of Artificial Intelligence (AI) based on computer vision for processing wide varieties of medical imaging but AI methods without explainability are often treated as a black box. Based on a view to demystifying the rationale influencing AI decisions, this paper designed and developed a novel low-cost explainable deep-learning diagnostic tool for predicting lung disease from medical images. For this, we investigated explainable deep learning (DL) models (conventional DL and vision transformers (ViTs)) for performing prediction of the existence of pneumonia, COVID19, or no-disease from both original and data augmentation (DA)-based medical images (from two chest X-ray datasets). The results show that our experimental consideration of the DA that combines the impact of cropping, rotation, and horizontal flipping (CROP+ROT+HF) for transforming input images and then passed as input to an Inception-V3 architecture yielded a performance that surpasses all the ViTs and other conventional DL approaches in most of the evaluated performance metrics. Overall, the results suggest that the utility of data augmentation schemes aided the DL methods to yield higher classification accuracies. Furthermore, we compared five different class activation mapping (CAM) algorithms (GradCAM, GradCAM++, EigenGradCAM, AblationCAM, and RandomCAM). The result shows that most of the examined CAM algorithms were effective in identifying the attention region containing the existence of pneumonia or COVID-19 from the medical images (chest X-rays). Our developed low-cost AI diagnostic tool (pilot system) can assist medical experts and radiographers in proffering early diagnosis of lung disease. For this, we selected five to seven deep learning models and the explainable algorithms were deployed on a novel web interface implemented via a Gradio framework. | P36: 1 | Q36: 1 | R36: 1 | S36: 1 | T36: =SUM(Table145[[#This Row],[Relevence 0,1,0.5]:[Findings 0,1,0.5]]) -> 4
A37: ScienceDirect | B37: Journal Article | C37: H. D. Jahja; N. Yudistira; Sutrisno | D37: 2023 | E37: Mask usage recognition using vision transformer with transfer learning and data augmentation | F37: Intelligent Systems with Applications | G37: 17 | I37: 200186 | L37: https://www.sciencedirect.com/science/article/pii/S266730532300011X | M37: https://doi.org/10.1016/j.iswa.2023.200186 | N37: Mask classification_x000D_ Vision transformers_x000D_ Transfer learning_x000D_ Data augmentation | O37: The COVID-19 pandemic has disrupted various levels of society. The use of masks is essential in preventing the spread of COVID-19 by identifying an image of a person using a mask. Although only 23.1% of people use masks correctly, Artificial Neural Networks (ANN) can help classify the use of good masks to help slow the spread of the Covid-19 virus. However, it requires a large dataset to train an ANN that can classify the use of masks correctly. MaskedFace-Net is a suitable dataset consisting of 137016 digital images with 4 class labels, namely Mask, Mask Chin, Mask Mouth Chin, and Mask Nose Mouth. Mask classification training utilizes Vision Transformers (ViT) architecture with transfer learning method using pre-trained weights on ImageNet-21k, with random augmentation. In addition, the hyper-parameters of training of 20 epochs, an Stochastic Gradient Descent (SGD) optimizer with a learning rate of 0.03, a batch size of 64, a Gaussian Cumulative Distribution (GeLU) activation function, and a Cross-Entropy loss function are used to be applied on the training of three architectures of ViT, namely Base-16, Large-16, and Huge-14. Furthermore, comparisons of with and without augmentation and transfer learning are conducted. This study found that the best classification is transfer learning and augmentation using ViT Huge-14. Using this method on MaskedFace-Net dataset, the research reaches an accuracy of 0.9601 on training data, 0.9412 on validation data, and 0.9534 on test data. This research shows that training the ViT model with data augmentation and transfer learning improves classification of the mask usage, even better than convolutional-based Residual Network (ResNet). | P37: 0 | Q37: 1 | R37: 0 | S37: 0.5 | T37: =SUM(Table145[[#This Row],[Relevence 0,1,0.5]:[Findings 0,1,0.5]]) -> 1.5
A38: ScienceDirect | B38: Journal Article | C38: S. Jain; A. Seal; A. Ojha; A. Yazidi; J. Bures; I. Tacheci; O. Krejcar | D38: 2021 | E38: A deep CNN model for anomaly detection and localization in wireless capsule endoscopy images | F38: Computers in Biology and Medicine | G38: 137 | I38: 104789 | L38: https://www.sciencedirect.com/science/article/pii/S0010482521005837 | M38: https://doi.org/10.1016/j.compbiomed.2021.104789 | N38: Deep convolutional neural network_x000D_ Attention mechanism_x000D_ Wireless capsule endoscopy_x000D_ Anomaly detection_x000D_ Localization | O38: Wireless capsule endoscopy (WCE) is one of the most efficient methods for the examination of gastrointestinal tracts. Computer-aided intelligent diagnostic tools alleviate the challenges faced during manual inspection of long WCE videos. Several approaches have been proposed in the literature for the automatic detection and localization of anomalies in WCE images. Some of them focus on specific anomalies such as bleeding, polyp, lesion, etc. However, relatively fewer generic methods have been proposed to detect all those common anomalies simultaneously. In this paper, a deep convolutional neural network (CNN) based model ‘WCENet’ is proposed for anomaly detection and localization in WCE images. The model works in two phases. In the first phase, a simple and efficient attention-based CNN classifies an image into one of the four categories: polyp, vascular, inflammatory, or normal. If the image is classified in one of the abnormal categories, it is processed in the second phase for the anomaly localization. Fusion of Grad-CAM++ and a custom SegNet is used for anomalous region segmentation in the abnormal image. WCENet classifier attains accuracy and area under receiver operating characteristic of 98% and 99%. The WCENet segmentation model obtains a frequency weighted intersection over union of 81%, and an average dice score of 56% on the KID dataset. WCENet outperforms nine different state-of-the-art conventional machine learning and deep learning models on the KID dataset. The proposed model demonstrates potential for clinical applications. | P38: 1 | Q38: 1 | R38: 1 | S38: 1 | T38: =SUM(Table145[[#This Row],[Relevence 0,1,0.5]:[Findings 0,1,0.5]]) -> 4
A39: ScienceDirect | B39: Journal Article | C39: A. Khan; S. Han; N. Ilyas; Y.-M. Lee; B. Lee | D39: 2023 | E39: CervixFormer: A Multi-scale swin transformer-Based cervical pap-Smear WSI classification framework | F39: Computer Methods and Programs in Biomedicine | G39: 240 | I39: 107718 | L39: https://www.sciencedirect.com/science/article/pii/S016926072300384X | M39: https://doi.org/10.1016/j.cmpb.2023.107718 | N39: Cervical cancer_x000D_ WSI Analysis_x000D_ Medical data augmentation_x000D_ Swin transformer_x000D_ Image classification | O39: Background and Objectives Cervical cancer affects around 0.5 million women per year, resulting in over 0.3 million fatalities. Therefore, repetitive screening for cervical cancer is of utmost importance. Computer-assisted diagnosis is key for scaling up cervical cancer screening. Current recognition algorithms, however, perform poorly on the whole-slide image (WSI) analysis, fail to generalize for different staining methods and on uneven distribution for subtype imaging, and provide sub-optimal clinical-level interpretations. Herein, we developed CervixFormer—an end-to-end, multi-scale swin transformer-based adversarial ensemble learning framework to assess pre-cancerous and cancer-specific cervical malignant lesions on WSIs. Methods The proposed framework consists of (1) a self-attention generative adversarial network (SAGAN) for generating synthetic images during patch-level training to address the class imbalanced problems; (2) a multi-scale transformer-based ensemble learning method for cell identification at various stages, including atypical squamous cells (ASC) and atypical squamous cells of undetermined significance (ASCUS), which have not been demonstrated in previous studies; and (3) a fusion model for concatenating ensemble-based results and producing final outcomes. Results In the evaluation, the proposed method is first evaluated on a private dataset of 717 annotated samples from six classes, obtaining a high recall and precision of 0.940 and 0.934, respectively, in roughly 1.2 minutes. To further examine the generalizability of CervixFormer, we evaluated it on four independent, publicly available datasets, namely, the CRIC cervix, Mendeley LBC, SIPaKMeD Pap Smear, and Cervix93 Extended Depth of Field image datasets. CervixFormer obtained a fairly better performance on two-, three-, four-, and six-class classification of smear- and cell-level datasets. For clinical interpretation, we used GradCAM to visualize a coarse localization map, highlighting important regions in the WSI. Notably, CervixFormer extracts feature mostly from the cell nucleus and partially from the cytoplasm. Conclusions In comparison with the existing state-of-the-art benchmark methods, the CervixFormer outperforms them in terms of recall, accuracy, and computing time. | P39: 0 | Q39: 1 | R39: 0 | S39: 0.5 | T39: =SUM(Table145[[#This Row],[Relevence 0,1,0.5]:[Findings 0,1,0.5]]) -> 1.5
A40: ScienceDirect | B40: Journal Article | C40: I. Lahsaini; M. El Habib Daho; M. A. Chikh | D40: 2021 | E40: Deep transfer learning based classification model for covid-19 using chest CT-scans | F40: Pattern Recognition Letters | G40: 152 | I40: 122-128 | L40: https://www.sciencedirect.com/science/article/pii/S0167865521003366 | M40: https://doi.org/10.1016/j.patrec.2021.08.035 | N40: Xception_x000D_ Densenet-121_x000D_ Densenet-201_x000D_ COVID-19_x000D_ Imagenet | O40: COVID-19 is an infectious and contagious virus. As of this writing, more than 160 million people have been infected since its emergence, including more than 125,000 in Algeria. In this work, We first collected a dataset of 4986 COVID and non-COVID images confirmed by RT-PCR tests at Tlemcen hospital in Algeria. Then we performed a transfer learning on deep learning models that got the best results on the ImageNet dataset, such as DenseNet121, DenseNet201, VGG16, VGG19, Inception Resnet-V2, and Xception, in order to conduct a comparative study. Therefore, We have proposed an explainable model based on the DenseNet201 architecture and the GradCam explanation algorithm to detect COVID-19 in chest CT images and explain the output decision. Experiments have shown promising results and proven that the introduced model can be beneficial for diagnosing and following up patients with COVID-19. | P40: 0 | Q40: 1 | R40: 0 | S40: 0.5 | T40: =SUM(Table145[[#This Row],[Relevence 0,1,0.5]:[Findings 0,1,0.5]]) -> 1.5
A41: ScienceDirect | B41: Journal Article | C41: Y. Liu; J. Su; Z. Zheng; D. Liu; Y. Song; Y. Fang; P. Yang; B. Su | D41: 2024 | E41: GLDCNet: A novel convolutional neural network for grapevine leafroll disease recognition using UAV-based imagery | F41: Computers and Electronics in Agriculture | G41: 218 | I41: 108668 | L41: https://www.sciencedirect.com/science/article/pii/S0168169924000590 | M41: https://doi.org/10.1016/j.compag.2024.108668 | N41: Grapevine leafroll disease_x000D_ UAV_x000D_ Deep learning_x000D_ Multispectral_x000D_ Vegetation index_x000D_ Spatial resolution | O41: High-throughput phenotyping of grapevine leafroll disease (GLD) at the canopy scale helps develop fast and effective management in viticulture. However, detecting GLD efficiently in a vineyard is challenging owing to the limited adaptation of prior art. Therefore, we propose a novel convolutional neural network called GLDCNet to improve GLD recognition using unmanned aerial vehicle–based imagery. The effectiveness of the GLDCNet is attributed to the four new network designs used and is validated through ablation experiments. The GLDCNet achieves a classification accuracy of 99.57% using the RGB dataset and obtains more efficient and accurate results than nine other state-of-the-art methods. Furthermore, we systematically evaluated the impacts of image spatial resolution and vegetation indexes on the classification performance of the model. Experimental results suggest that improving image spatial resolution is more cost-effective than enhancing multispectral information for improving GLD recognition. Our proposed method offers a rapid, scalable, and accurate diagnostic protocol for detecting GLD in vineyards. | P41: 1 | Q41: 1 | R41: 0.5 | S41: 1 | T41: =SUM(Table145[[#This Row],[Relevence 0,1,0.5]:[Findings 0,1,0.5]]) -> 3.5
A42: ScienceDirect | B42: Journal Article | C42: H. W. Loh; C. P. Ooi; S. Seoni; P. D. Barua; F. Molinari; U. R. Acharya | D42: 2022 | E42: Application of explainable artificial intelligence for healthcare: A systematic review of the last decade (2011–2022) | F42: Computer Methods and Programs in Biomedicine | G42: 226 | I42: 107161 | L42: https://www.sciencedirect.com/science/article/pii/S0169260722005429 | M42: https://doi.org/10.1016/j.cmpb.2022.107161 | N42: Explainable artificial intelligence (XAI)_x000D_ Deep learning_x000D_ Machine learning_x000D_ PRISMA_x000D_ SHAP_x000D_ LIME_x000D_ GradCAM_x000D_ LRP_x000D_ EBM_x000D_ CBR_x000D_ Rule-based_x000D_ Expert system_x000D_ Saliency map_x000D_ Attention mechanism_x000D_ Healthcare | O42: Background and objectives Artificial intelligence (AI) has branched out to various applications in healthcare, such as health services management, predictive medicine, clinical decision-making, and patient data and diagnostics. Although AI models have achieved human-like performance, their use is still limited because they are seen as a black box. This lack of trust remains the main reason for their low use in practice, especially in healthcare. Hence, explainable artificial intelligence (XAI) has been introduced as a technique that can provide confidence in the model's prediction by explaining how the prediction is derived, thereby encouraging the use of AI systems in healthcare. The primary goal of this review is to provide areas of healthcare that require more attention from the XAI research community. Methods Multiple journal databases were thoroughly searched using PRISMA guidelines 2020. Studies that do not appear in Q1 journals, which are highly credible, were excluded. Results In this review, we surveyed 99 Q1 articles covering the following XAI techniques: SHAP, LIME, GradCAM, LRP, Fuzzy classifier, EBM, CBR, rule-based systems, and others. Conclusion We discovered that detecting abnormalities in 1D biosignals and identifying key text in clinical notes are areas that require more attention from the XAI research community. We hope this is review will encourage the development of a holistic cloud system for a smart city. | P42: 0 | Q42: 1 | R42: 0 | S42: 0.5 | T42: =SUM(Table145[[#This Row],[Relevence 0,1,0.5]:[Findings 0,1,0.5]]) -> 1.5
A43: ScienceDirect | B43: Journal Article | C43: K. Niranjan; S. Shankar Kumar; S. Vedanth; D. S. Chitrakala | D43: 2023 | E43: An Explainable AI driven Decision Support System for COVID-19 Diagnosis using Fused Classification and Segmentation | F43: Procedia Computer Science | G43: 218 | I43: 1915-1925 | L43: https://www.sciencedirect.com/science/article/pii/S1877050923001680 | M43: https://doi.org/10.1016/j.procs.2023.01.168 | N43: COVID-19_x000D_ Explainable AI_x000D_ Segmentation_x000D_ Convolutional Neural networks_x000D_ Class Activavtion Mapping_x000D_ Gradient weighted Class Activation Mapping (Grad-CAM)_x000D_ Guided Grad-CAM | O43: The coronavirus has caused havoc on billions of people worldwide. The Reverse Transcription Polymerase Chain Reaction(RT-PCR) test is widely accepted as a standard diagnostic tool for detecting infection, however, the severity of infection can't be measured accurately with RT-PCR results. Chest CT Scans of infected patients can manifest the presence of lesions with high sensitivity. During the pandemic, there is a dearth of competent doctors to examine chest CT images. Therefore, a Guided Gradcam based Explainable Classification and Segmentation system (GGECS) which is a real-time explainable classification and lesion identification decision support system is proposed in this work. The classification model used in the proposed GGECS system is inspired by Res2Net. Explainable AI techniques like GradCam and Guided GradCam are used to demystify Convolutional Neural Networks (CNNs). These explainable systems can assist in localizing the regions in the CT scan that contribute significantly to the system's prediction. The segmentation model can further reliably localize infected regions. The segmentation model is a fusion between the VGG-16 and the classification network. The proposed classification model in GGECS obtains an overall accuracy of 98.51 % and the segmentation model achieves an IoU score of 0.595. | P43: 1 | Q43: 1 | R43: 1 | S43: 1 | T43: =SUM(Table145[[#This Row],[Relevence 0,1,0.5]:[Findings 0,1,0.5]]) -> 4
A44: ScienceDirect | B44: Journal Article | C44: G. Rani; A. Misra; V. S. Dhaka; D. Buddhi; R. K. Sharma; E. Zumpano; E. Vocaturo | D44: 2022 | E44: A multi-modal bone suppression, lung segmentation, and classification approach for accurate COVID-19 detection using chest radiographs | F44: Intelligent Systems with Applications | G44: 16 | I44: 200148 | L44: https://www.sciencedirect.com/science/article/pii/S2667305322000850 | M44: https://doi.org/10.1016/j.iswa.2022.200148 | N44: SARS-CoV-2_x000D_ COVID-19_x000D_ Deep learning_x000D_ Biomedical_x000D_ Medical imaging | O44: The high transmission rate of COVID-19 and the lack of quick, robust, and intelligent systems for its detection have become a point of concern for the public, Government, and health experts worldwide. The study of radiological images is one of the fastest ways to comprehend the infectious spread and diagnose a patient. However, it is difficult to differentiate COVID-19 from other pneumonic infections. The purpose of this research is to provide an automatic, precise, reliable, robust, and intelligent assisting system ‘Covid Scanner’ for mass screening of COVID-19, Non-COVID Viral Pneumonia, and Bacterial Pneumonia from healthy chest radiographs. To train the proposed system, the authors of this research prepared novel a dataset called, “COVID-Pneumonia CXR”. The system is a coherent integration of bone suppression, lung segmentation, and the proposed classifier, ‘EXP-Net’. The system reported an AUC of 96.58% on the validation dataset and 96.48% on the testing dataset comprising chest radiographs. The results from the ablation study prove the efficacy and generalizability of the proposed integrated pipeline of models. To prove the system's reliability, the feature heatmaps visualized in the lung region were validated by radiology experts. Moreover, a comparison with the state-of-the-art models and existing approaches shows that the proposed system finds clearer demarcation between the highly similar chest radiographs of COVID-19 and Non-COVID viral pneumonia. The copyright of “Covid Scanner” is protected with registration number SW-13625/2020. The code for the models used in this research is publicly available at: https://github.com/Ankit-Misra/multi_modal_covid_detection/. | P44: 1 | Q44: 1 | R44: 0.5 | S44: 1 | T44: =SUM(Table145[[#This Row],[Relevence 0,1,0.5]:[Findings 0,1,0.5]]) -> 3.5
A45: ScienceDirect | B45: Journal Article | C45: A. Schöttl | D45: 2022 | E45: Improving the Interpretability of GradCAMs in Deep Classification Networks | F45: Procedia Computer Science | G45: 200 | I45: 620-628 | L45: https://www.sciencedirect.com/science/article/pii/S1877050922002691 | M45: https://doi.org/10.1016/j.procs.2022.01.260 | N45: GradCAM_x000D_ Interpretability_x000D_ CAM fostering | O45: Deep classification networks play an important role as backbone networks in industrial AI applications. These applications are often cost or safety critical; explainability of the AI results is a highly demanded feature. We introduce CAM fostering, a method to improve the explainability of classification nets based on local layers such as convolutional or pooling layers. Several CAM interpretability measures are defined and used as additional loss terms. Even though the method requires second-order derivatives, it is demonstrated that deep nets can be trained on large datasets without frozen parameters. The training parameters can be chosen such that the accuracy degradation remains decent in favor of the CAM interpretability improvement. We conclude by comparing the results of different training parameter configurations. | P45: 1 | Q45: 1 | R45: 1 | S45: 0.5 | T45: =SUM(Table145[[#This Row],[Relevence 0,1,0.5]:[Findings 0,1,0.5]]) -> 3.5
A46: ScienceDirect | B46: Journal Article | C46: S. Singh; P. K. Jain; N. Sharma; M. Pohit; S. Roy | D46: 2023 | E46: Atherosclerotic plaque classification in carotid ultrasound images using machine learning and explainable deep learning | F46: Intelligent Medicine | L46: https://www.sciencedirect.com/science/article/pii/S2667102623000414 | M46: https://doi.org/10.1016/j.imed.2023.05.003 | N46: Explainable deep learning_x000D_ Carotid artery_x000D_ Classification_x000D_ VGG16_x000D_ ResNet-50_x000D_ GoogLeNet_x000D_ XceptionNet_x000D_ SqueezeNet | O46: Objective The incidence of cardiovascular diseases (CVD) is rising rapidly worldwide. Some forms of CVD, such as stroke and heart attack, are more common among patients with certain conditions. Atherosclerosis development is a major factor underlying cardiovascular events, such as heart attack and stroke, and its early detection may prevent such events. Ultrasound imaging of carotid arteries is a useful method for diagnosis of atherosclerotic plaques; however, an automated method to classify atherosclerotic plaques for evaluation of early-stage CVD is needed. Here, we propose an automated method for classification of high-risk atherosclerotic plaque ultrasound images. Methods Five deep learning (DL) models (VGG16, ResNet-50, GoogLeNet, XceptionNet, and SqueezeNet) were used for automated classification and the results compared with those of a machine learning (ML)-based technique, involving extraction of 23 texture features from ultrasound images and classification using a Support Vector Machine classifier. To enhance model interpretability, output gradient-weighted convolutional activation maps (gradCAMs) were generated and overlayed on original images. Results A series of indices, including accuracy, sensitivity, specificity, F1-score, Cohen-kappa index, and area under the curve values, were calculated to evaluate model performance. GradCAM output images allowed visualization of the most significant ultrasound image regions. Conclusion Of models tested, the GoogLeNet model yielded the highest accuracy (98.20%). ML models are also suitable for applications requiring low computational resource, as their accuracy (96.85%) is similar to that of DL models. Further, DL models can be more completely automated than ML models. | P46: 1 | Q46: 1 | R46: 1 | S46: 1 | T46: =SUM(Table145[[#This Row],[Relevence 0,1,0.5]:[Findings 0,1,0.5]]) -> 4
A47: ScienceDirect | B47: Journal Article | C47: B. Tasci; I. Tasci | D47: 2022 | E47: Deep feature extraction based brain image classification model using preprocessed images: PDRNet | F47: Biomedical Signal Processing and Control | G47: 78 | I47: 103948 | L47: https://www.sciencedirect.com/science/article/pii/S1746809422004475 | M47: https://doi.org/10.1016/j.bspc.2022.103948 | N47: Hybrid deep feature engineering_x000D_ Transfer learning_x000D_ Ischemic acute infarction detection_x000D_ Diffusion MRI | O47: Background Stroke is a neurological condition that occurs when cerebral vessels become blocked and have reduced blood flow. This research proposes a hybrid deep feature-based feature engineering model to achieve high classification performance. Materials and method In this research, three brain magnetic resonance image datasets were used to test the proposed model. A deep feature engineering model has been proposed to deploy the raw MRI and four preprocessing algorithms: GradCAM, histogram-matching, canny edge detection, and Locally Interpretable Model-Agnostic Explanations(LIME). The deep features have been extracted using Resnet101 and DenseNet201 pre-trained convolutional neural networks (CNN). Thus, this model is titled preprocessing based DenseNet and ResNet (PDRNet). The iterative neighborhood component analysis (INCA) function selects the most suitable features. These features are trained and validated using support vector machine (SVM) classifiers. Iterative Majority Voting (IMV) has been applied to the results obtained from the SVM. The best classification result has been selected by deploying IMV. Results Our proposed PDRNet achieved a classification accuracy of 97.56% for Dataset 1, 99.32% for Dataset 2, and 99.16% for Dataset 3. The success of the presented model is demonstrated using these calculated accuracies. Conclusions Our proposed hybrid deep feature model was tested on two datasets with two and four classes. It has also been compared to other state-of-art deep learning-based models, and our model performs better. These results and findings clearly demonstrate the success of the introduced hybrid deep feature engineering method. | P47: 0 | Q47: 1 | R47: 0 | S47: 0.5 | T47: =SUM(Table145[[#This Row],[Relevence 0,1,0.5]:[Findings 0,1,0.5]]) -> 1.5
A48: ScienceDirect | B48: Journal Article | C48: Y. Xie; Z. Zhang; S. Chen; C. Qiu | D48: 2023 | E48: Detect, Grow, Seg: A weakly supervision method for medical image segmentation based on bounding box | F48: Biomedical Signal Processing and Control | G48: 86 | I48: 105158 | L48: https://www.sciencedirect.com/science/article/pii/S1746809423005918 | M48: https://doi.org/10.1016/j.bspc.2023.105158 | N48: Weakly supervised medical image segmentation_x000D_ GradCAM_x000D_ Adaptive regional growth_x000D_ UNet_x000D_ YoloV5 | O48: Weakly supervised semantic segmentation based on bounding box has been fully developed in natural scenes, but in medical image scenes it often faces the difficulties of blurred edges, imaging noise, and mutual interference between multiple organs, which makes the methods suitable in natural scenes tend to show poor performance in medical images. In this paper, we propose a weakly supervised segmentation method for medical images based on Detection, Growth, and Segmentation (DGS). For weak labels in the form of bounding boxes, the detector YOLOV5 and GradCAM are introduced to obtain the heatmap representation, while the additional unlabeled data can be also utilized through the detector. The thresholded heatmap is used to generate seed points for adaptive regional growth so that better pseudo labels are obtained. Finally, the pseudo labels are used for supervised training on UNet to obtain end to end segmentation. Sufficient experiments show that, compared with other methods, the pseudo label generation and segmentation model formed by our method achieve the best performance, while the use of unlabeled data by the detector brings significant improvement for segmentation in low-label scenarios, which greatly reduce the time and demand of labeling. | P48: 0 | Q48: 1 | R48: 0 | S48: 0.5 | T48: =SUM(Table145[[#This Row],[Relevence 0,1,0.5]:[Findings 0,1,0.5]]) -> 1.5
A49: ScienceDirect | B49: Journal Article | C49: Y. Yu; Y. Zhang; Z. Cheng; Z. Song; C. Tang | D49: 2023 | E49: MCA: Multidimensional collaborative attention in deep convolutional neural networks for image recognition | F49: Engineering Applications of Artificial Intelligence | G49: 126 | I49: 107079 | L49: https://www.sciencedirect.com/science/article/pii/S0952197623012630 | M49: https://doi.org/10.1016/j.engappai.2023.107079 | N49: Multidimensional collaborative attention_x000D_ Attention mechanisms_x000D_ Cross-dimension feature responses_x000D_ Local feature interactions | O49: A broad range of prior research has demonstrated that attention mechanisms offer great potential in advancing the performance of deep convolutional neural networks (CNNs). However, most existing approaches either ignore modeling attention in both channel and spatial dimensions or introduce higher model complexity and heavier computational burden. To alleviate this dilemma, in this paper, we propose a lightweight and efficient multidimensional collaborative attention, MCA, a novel method for simultaneously inferring attention in channel, height, and width dimensions with almost free additional overhead by using a three-branch architecture. For the essential components of MCA, we not only develop an adaptive combination mechanism for merging dual cross-dimension feature responses in squeeze transformation, enhancing the informativeness and discriminability of feature descriptors but also design a gating mechanism in excitation transformation that adaptively determines the coverage of interaction to capture local feature interactions, overcoming the paradox of performance and computational overhead trade-off. Our MCA is simple yet general and can be easily plugged into various classic CNNs as a plug-and-play module and trained along with the vanilla networks in an end-to-end manner. Extensive experimental results for image recognition on CIFAR and ImageNet-1K datasets demonstrate the superiority of our method over other state-of-the-art (SOTA) counterparts. In addition, we also provide insight into the practical benefits of MCA by visually inspecting the GradCAM++ visualization results. The code is available at https://github.com/ndsclark/MCANet. | P49: 0 | Q49: 0 | R49: 0.5 | S49: 1 | T49: =SUM(Table145[[#This Row],[Relevence 0,1,0.5]:[Findings 0,1,0.5]]) -> 1.5
A50: Web of Science | B50: Journal Article | C50: M. Ajmal; M. A. Khan; T. Akram; A. Alqahtani; M. Alhaisoni; A. Armghan; S. A. Althubiti; F. Alenezi | D50: 2023 | E50: BF<SUP>2</SUP>SkNet: best deep learning features fusion-assisted framework for multiclass skin lesion classification | F50: NEURAL COMPUTING & APPLICATIONS | G50: 35 | H50: 30 | I50: 22115-22131 | M50: 10.1007/s00521-022-08084-6 | O50: The convolutional neural network showed considerable success in medical imaging with explainable AI for cancer detection and recognition. However, the irrelevant and large number of features increases the computational time and decreases the accuracy. This work proposes a deep learning and fuzzy entropy slime mould algorithm-based architecture for multiclass skin lesion classification. In the first step, we employed the data augmentation technique to increase the training data and further utilized it for training two fine-tuned deep learning models such as Inception-ResNetV2 and NasNet Mobile. Then, we used transfer learning on augmented datasets to train both models and obtained two feature vectors from newly fine-tuned models. Later, we applied a fuzzy entropy slime mould algorithm on both vectors to get optimal features that are finally fused using the Serial-Threshold fusion technique and classified using several machine learning classifiers. Eventually, the explainable AI technique named Gradcam opted for the visualization of the lesion region. The experimental process was conducted on two datasets, such as HAM10000 and ISIC 2018, and achieved 97.1 and 90.2% accuracy, better than the other techniques. | P50: 0 | Q50: 1 | R50: 0 | S50: 0.5 | T50: =SUM(Table145[[#This Row],[Relevence 0,1,0.5]:[Findings 0,1,0.5]]) -> 1.5
A51: Web of Science | B51: Journal Article | C51: H. R. H. Al-Absi; M. T. Islam; M. A. Refaee; M. E. H. Chowdhury; T. Alam | D51: 2022 | E51: Cardiovascular Disease Diagnosis from DXA Scan and Retinal Images Using Deep Learning | F51: SENSORS | G51: 22 | H51: 12 | M51: 10.3390/s22124310 | O51: Cardiovascular diseases (CVD) are the leading cause of death worldwide. People affected by CVDs may go undiagnosed until the occurrence of a serious heart failure event such as stroke, heart attack, and myocardial infraction. In Qatar, there is a lack of studies focusing on CVD diagnosis based on non-invasive methods such as retinal image or dual-energy X-ray absorptiometry (DXA). In this study, we aimed at diagnosing CVD using a novel approach integrating information from retinal images and DXA data. We considered an adult Qatari cohort of 500 participants from Qatar Biobank (QBB) with an equal number of participants from the CVD and the control groups. We designed a case-control study with a novel multi-modal (combining data from multiple modalities-DXA and retinal images)-to propose a deep learning (DL)-based technique to distinguish the CVD group from the control group. Uni-modal models based on retinal images and DXA data achieved 75.6% and 77.4% accuracy, respectively. The multi-modal model showed an improved accuracy of 78.3% in classifying CVD group and the control group. We used gradient class activation map (GradCAM) to highlight the areas of interest in the retinal images that influenced the decisions of the proposed DL model most. It was observed that the model focused mostly on the centre of the retinal images where signs of CVD such as hemorrhages were present. This indicates that our model can identify and make use of certain prognosis markers for hypertension and ischemic heart disease. From DXA data, we found higher values for bone mineral density, fat content, muscle mass and bone area across majority of the body parts in CVD group compared to the control group indicating better bone health in the Qatari CVD cohort. This seminal method based on DXA scans and retinal images demonstrate major potentials for the early detection of CVD in a fast and relatively non-invasive manner. | P51: 0 | Q51: 1 | R51: 0 | S51: 0.5 | T51: =SUM(Table145[[#This Row],[Relevence 0,1,0.5]:[Findings 0,1,0.5]]) -> 1.5
A52: Web of Science | B52: Journal Article | C52: S. Ali; T. P. T. Abdullah; T. P. T. Armand; A. Athar; A. Hussain; M. Ali; M. Yaseen; M.-I. Joo; H.-C. Kim | D52: 2023 | E52: Metaverse in Healthcare Integrated with Explainable AI and Blockchain: Enabling Immersiveness, Ensuring Trust, and Providing Patient Data Security | F52: SENSORS | G52: 23 | H52: 2 | M52: 10.3390/s23020565 | O52: Digitization and automation have always had an immense impact on healthcare. It embraces every new and advanced technology. Recently the world has witnessed the prominence of the metaverse which is an emerging technology in digital space. The metaverse has huge potential to provide a plethora of health services seamlessly to patients and medical professionals with an immersive experience. This paper proposes the amalgamation of artificial intelligence and blockchain in the metaverse to provide better, faster, and more secure healthcare facilities in digital space with a realistic experience. Our proposed architecture can be summarized as follows. It consists of three environments, namely the doctor's environment, the patient's environment, and the metaverse environment. The doctors and patients interact in a metaverse environment assisted by blockchain technology which ensures the safety, security, and privacy of data. The metaverse environment is the main part of our proposed architecture. The doctors, patients, and nurses enter this environment by registering on the blockchain and they are represented by avatars in the metaverse environment. All the consultation activities between the doctor and the patient will be recorded and the data, i.e., images, speech, text, videos, clinical data, etc., will be gathered, transferred, and stored on the blockchain. These data are used for disease prediction and diagnosis by explainable artificial intelligence (XAI) models. The GradCAM and LIME approaches of XAI provide logical reasoning for the prediction of diseases and ensure trust, explainability, interpretability, and transparency regarding the diagnosis and prediction of diseases. Blockchain technology provides data security for patients while enabling transparency, traceability, and immutability regarding their data. These features of blockchain ensure trust among the patients regarding their data. Consequently, this proposed architecture ensures transparency and trust regarding both the diagnosis of diseases and the data security of the patient. We also explored the building block technologies of the metaverse. Furthermore, we also investigated the advantages and challenges of a metaverse in healthcare. | P52: 0 | Q52: 0.5 | R52: 0.5 | S52: 1 | T52: =SUM(Table145[[#This Row],[Relevence 0,1,0.5]:[Findings 0,1,0.5]]) -> 2
A53: Web of Science | B53: Journal Article | C53: V. A. Ashwath; O. K. Sikha; R. Benitez | D53: 2023 | E53: TS-CNN: A Three-Tier Self-Interpretable CNN for Multi-Region Medical Image Classification | F53: IEEE ACCESS | G53: 11 | I53: 78402-78418 | M53: 10.1109/ACCESS.2023.3299850 | O53: Medical image classification is critical, where reliability and transparency are crucial for the safe and accurate diagnosis of diseases. Deep Convolutional Neural Networks (DCNNs) are widely used in medical image classification due to their high performance. However, they are often considered black-boxes because they offer little insight into decision-making. Therefore, improving the interpretability of DCNNs is crucial for their adoption in medical diagnoses. This paper proposes a novel three-tier self-interpretable DCNN (TS-CNN) architecture for multi-region medical image classification, which improves classification performance while being inherently interpretable. The proposed TS-CNN architecture is well-suited for medical images with multiple regions, such as images with scattered and randomly shaped lesions. The proposed architecture has three branches: a global branch that learns the relevant patterns from the raw input image; an attention branch that selects the important regions and discards the irrelevant parts for the local branch to learn; and a fusion branch that distills knowledge from both the global and local branches for classification. The proposed architecture is flexible in terms of the backbone CNNs used for classification and post-hoc interpretability methods used for attention capture. We demonstrate the flexibility and generalization of the architecture through a series of experiments involving multiple state-of-the-art CNN architectures such as DenseNet-121, Inception, Xception, and ResNet-50 as the global/local branches, each paired with GradCAM and Saliency maps as attention modules. The proposed architecture outperformed the backbone model in classification tasks on two datasets: a custom-made blob dataset and a publicly available skin lesion PAD-UFES-20 dataset, demonstrating its potential for improving accuracy in medical image classification tasks. The code related to this work can be found at: https://github.com/sikha2552/TS-CNN-A-Three-Tier-Self-Interpretable-CNN-for-Medical-Image-Classification-Empowered-with-Post-hoc.git. | P53: 1 | Q53: 1 | R53: 1 | S53: 1 | T53: =SUM(Table145[[#This Row],[Relevence 0,1,0.5]:[Findings 0,1,0.5]]) -> 4
A54: Web of Science | B54: Journal Article | C54: R. Avram; J. P. Barrios; S. Abreau; C. Y. Goh; Z. Ahmed; K. Chung; D. Y. So; J. E. Olgin; G. H. Tison | D54: 2023 | E54: Automated Assessment of Cardiac Systolic Function From Coronary Angiograms With Video-Based Artificial Intelligence Algorithms | F54: JAMA CARDIOLOGY | G54: 8 | H54: 6 | I54: 586-594 | M54: 10.1001/jamacardio.2023.0968 | O54: Importance Understanding left ventricular ejection fraction (LVEF) during coronary angiography can assist in disease management.Objective To develop an automated approach to predict LVEF from left coronary angiograms.Design, Setting, and Participants This was a cross-sectional study with external validation using patient data from December 12, 2012, to December 31, 2019, from the University of California, San Francisco (UCSF). Data were randomly split into training, development, and test data sets. External validation data were obtained from the University of Ottawa Heart Institute. Included in the analysis were all patients 18 years or older who received a coronary angiogram and transthoracic echocardiogram (TTE) within 3 months before or 1 month after the angiogram.Exposure A video-based deep neural network (DNN) called CathEF was used to discriminate (binary) reduced LVEF (<= 40%) and to predict (continuous) LVEF percentage from standard angiogram videos of the left coronary artery. Guided class-discriminative gradient class activation mapping (GradCAM) was applied to visualize pixels in angiograms that contributed most to DNN LVEF prediction.Results A total of 4042 adult angiograms with corresponding TTE LVEF from 3679 UCSF patients were included in the analysis. Mean (SD) patient age was 64.3 (13.3) years, and 2212 patients were male (65%). In the UCSF test data set (n = 813), the video-based DNN discriminated (binary) reduced LVEF (= 40%) with an area under the receiver operating characteristic curve (AUROC) of 0.911 (95% CI, 0.887-0.934); diagnostic odds ratio for reduced LVEF was 22.7 (95% CI, 14.0-37.0). DNN-predicted continuous LVEF had a mean absolute error (MAE) of 8.5% (95% CI, 8.1%-9.0%) compared with TTE LVEF. Although DNN-predicted continuous LVEF differed 5% or less compared with TTE LVEF in 38.0% (309 of 813) of test data set studies, differences greater than 15% were observed in 15.2% (124 of 813). In external validation (n = 776), video-based DNN discriminated (binary) reduced LVEF (= 40%) with an AUROC of 0.906 (95% CI, 0.881-0.931), and DNN-predicted continuous LVEF had an MAE of 7.0% (95% CI, 6.6%-7.4%). Video-based DNN tended to overestimate low LVEFs and underestimate high LVEFs. Video-based DNN performance was consistent across sex, body mass index, low estimated glomerular filtration rate (= 45), presence of acute coronary syndromes, obstructive coronary artery disease, and left ventricular hypertrophy.Conclusion and relevanceThis cross-sectional study represents an early demonstration of estimating LVEF from standard angiogram videos of the left coronary artery using video-based DNNs. Further research can improve accuracy and reduce the variability of DNNs to maximize their clinical utility. | P54: 0 | Q54: 1 | R54: 0 | S54: 0.5 | T54: =SUM(Table145[[#This Row],[Relevence 0,1,0.5]:[Findings 0,1,0.5]]) -> 1.5
A55: Web of Science | B55: Journal Article | C55: J. Bai; J. Ren; Z. Xiao; Z. Chen; C. Gao; T. A. A. Ali; L. Jiao | D55: 2023 | E55: Localizing From Classification: Self-Directed Weakly Supervised Object Localization for Remote Sensing Images | F55: IEEE TRANSACTIONS ON NEURAL NETWORKS AND LEARNING SYSTEMS | M55: 10.1109/TNNLS.2023.3309889 | O55: In recent years, object localization and detection methods in remote sensing images (RSIs) have received increasing attention due to their broad applications. However, most previous fully supervised methods require a large number of time-consuming and labor-intensive instance-level annotations. Compared with those fully supervised methods, weakly supervised object localization (WSOL) aims to recognize object instances using only image-level labels, which greatly saves the labeling costs of RSIs. In this article, we propose a self-directed weakly supervised strategy (SD-WSS) to perform WSOL in RSIs. To specify, we fully exploit and enhance the spatial feature extraction capability of the RSIs' classification model to accurately localize the objects of interest. To alleviate the serious discriminative region problem exhibited by previous WSOL methods, the spatial location information implicit in the classification model is carefully extracted by GradCAM $++$ to guide the learning procedure. Furthermore, to eliminate the interference from complex backgrounds of RSIs, we design a novel self-directed loss to make the model optimize itself and explicitly tell it where to look. Finally, we review and annotate the existing remote sensing scene classification dataset and create two new WSOL benchmarks in RSIs, named C45V2 and PN2. We conduct extensive experiments to evaluate the proposed method and six mainstream WSOL methods with three backbones on C45V2 and PN2. The results demonstrate that our proposed method achieves better performance when compared with state-of-the-arts. | P55: 0 | Q55: 1 | R55: 0 | S55: 0.5 | T55: =SUM(Table145[[#This Row],[Relevence 0,1,0.5]:[Findings 0,1,0.5]]) -> 1.5
A56: Web of Science | B56: Journal Article | C56: M. Bhandari; T. B. Shahi; A. Neupane; K. B. Walsh | D56: 2023 | E56: BotanicX-AI: Identification of Tomato Leaf Diseases Using an Explanation-Driven Deep-Learning Model | F56: JOURNAL OF IMAGING | G56: 9 | H56: 2 | M56: 10.3390/jimaging9020053 | O56: Early and accurate tomato disease detection using easily available leaf photos is essential for farmers and stakeholders as it help reduce yield loss due to possible disease epidemics. This paper aims to visually identify nine different infectious diseases (bacterial spot, early blight, Septoria leaf spot, late blight, leaf mold, two-spotted spider mite, mosaic virus, target spot, and yellow leaf curl virus) in tomato leaves in addition to healthy leaves. We implemented EfficientNetB5 with a tomato leaf disease (TLD) dataset without any segmentation, and the model achieved an average training accuracy of 99.84% +/- 0.10%, average validation accuracy of 98.28% +/- 0.20%, and average test accuracy of 99.07% +/- 0.38% over 10 cross folds.The use of gradient-weighted class activation mapping (GradCAM) and local interpretable model-agnostic explanations are proposed to provide model interpretability, which is essential to predictive performance, helpful in building trust, and required for integration into agricultural practice. | P56: 0 | Q56: 0.5 | R56: 0.5 | S56: 1 | T56: =SUM(Table145[[#This Row],[Relevence 0,1,0.5]:[Findings 0,1,0.5]]) -> 2
A57: Web of Science | B57: Journal Article | C57: A. R. Bhatt; A. Ganatra; K. Kotecha | D57: 2021 | E57: Cervical cancer detection in pap smear whole slide images using convNet with transfer learning and progressive resizing | F57: PEERJ COMPUTER SCIENCE | M57: 10.7717/peerj-cs.348 | O57: Cervical intraepithelial neoplasia (CIN) and cervical cancer are major health problems faced by women worldwide. The conventional Papanicolaou (Pap) smear analysis is an effective method to diagnose cervical pre-malignant and malignant conditions by analyzing swab images. Various computer vision techniques can be explored to identify potential precancerous and cancerous lesions by analyzing the Pap smear image. The majority of existing work cover binary classification approaches using various classifiers and Convolution Neural Networks. However, they suffer from inherent challenges for minute feature extraction and precise classification. We propose a novel methodology to carry out the multiclass classification of cervical cells from Whole Slide Images (WSI) with optimum feature extraction. The actualization of Conv Net with Transfer Learning technique substantiates meaningful Metamorphic Diagnosis of neoplastic and pre-neoplastic lesions. As the Progressive Resizing technique (an advanced method for training ConvNet) incorporates prior knowledge of the feature hierarchy and can reuse old computations while learning new ones, the model can carry forward the extracted morphological cell features to subsequent Neural Network layers iteratively for elusive learning. The Progressive Resizing technique superimposition in consultation with the Transfer Learning technique while training the Conv Net models has shown a substantial performance increase. The proposed binary and multiclass classification methodology succored in achieving benchmark scores on the Herlev Dataset. We achieved singular multiclass classification scores for WSI images of the SIPaKMed dataset, that is, accuracy (99.70%), precision (99.70%), recall (99.72%), F-Beta (99.63%), and Kappa scores (99.31%), which supersede the scores obtained through principal methodologies. GradCam based feature interpretation extends enhanced assimilation of the generated results, highlighting the pre-malignant and malignant lesions by visual localization in the images. | P57: 1 | Q57: 1 | R57: 1 | S57: 1 | T57: =SUM(Table145[[#This Row],[Relevence 0,1,0.5]:[Findings 0,1,0.5]]) -> 4
A58: Web of Science | B58: Journal Article | C58: J. Chang; J. Lee; A. Ha; Y. S. Han; E. Bak; S. Choi; J. M. Yun; U. Kang; I. H. Shin; J. Y. Shin; T. Ko; Y. Seul; K. L. Oh; K. H. Park; S. M. Park | D58: 2021 | E58: Explaining the Rationale of Deep Learning Glaucoma Decisions with Adversarial Examples | F58: OPHTHALMOLOGY | G58: 128 | H58: 1 | I58: 78-88 | M58: 10.1016/j.opatha.2020.06.036 | O58: Purpose: To illustrate what is inside the so-called black box of deep learning models (DLMs) so that clinicians can have greater confidence in the conclusions of artificial intelligence by evaluating adversarial explanation on its ability to explain the rationale of DLM decisions for glaucoma and glaucoma-related findings. Adversarial explanation generates adversarial examples (AEs), or images that have been changed to gain or lose pathologic characteristic-specific traits, to explain the DLM's rationale.Design: Evaluation of explanation methods for DLMs.Participants: Health screening participants (n = 1653) at the Seoul National University Hospital Health Promotion Center, Seoul, Republic of Korea.Methods: We trained DLMs for referable glaucoma (RG), increased cup-to-disc ratio (ICDR), disc rim narrowing (DRN), and retinal nerve fiber layer defect (RNFLD) using 6430 retinal fundus images. Surveys consisting of explanations using AE and gradient-weighted class activation mapping (GradCAM), a conventional heatmapbased explanation method, were generated for 400 pathologic and healthy patient eyes. For each method, board-trained glaucoma specialists rated location explainability, the ability to pinpoint decision-relevant areas in the image, and rationale explainability, the ability to inform the user on the model's reasoning for the decision based on pathologic features. Scores were compared by paired Wilcoxon signed-rank test.Main Outcome Measures: Area under the receiver operating characteristic curve (AUC), sensitivities, and specificities of DLMs; visualization of clinical pathologic changes of AEs; and survey scores for locational and rationale explainability.Results: The AUCs were 0.90, 0.99, 0.95, and 0.79 and sensitivities were 0.79, 1.00, 0.82, and 0.55 at 0.90 specificity for RG, ICDR, DRN, and RNFLD DLMs, respectively. Generated AEs showed valid clinical feature changes, and survey results for location explainability were 3.94 1.33 and 2.55 1.24 using AEs and GradCAMs, respectively, of a possible maximum score of 5 points. The scores for rationale explainability were 3.97 1.31 and 2.10 1.25 for AEs and GradCAM, respectively. Adversarial example provided significantly better explainability than GradCAM.Conclusions: Adversarial explanation increased the explainability over GradCAM, a conventional heatmapbased explanation method. Adversarial explanation may help medical professionals understand more clearly the rationale of DLMs when using them for clinical decisions. (C) 2020 by the American Academy of Ophthalmology | P58: 1 | Q58: 1 | R58: 0.5 | S58: 1 | T58: =SUM(Table145[[#This Row],[Relevence 0,1,0.5]:[Findings 0,1,0.5]]) -> 3.5
A59: Web of Science | B59: Journal Article | C59: D. F. Collazos-Huertas; A. M. Alvarez-Meza; G. Castellanos-Dominguez | D59: 2022 | E59: Image-Based Learning Using Gradient Class Activation Maps for Enhanced Physiological Interpretability of Motor Imagery Skills | F59: APPLIED SCIENCES-BASEL | G59: 12 | H59: 3 | M59: 10.3390/app12031695 | O59: Brain activity stimulated by the motor imagery paradigm (MI) is measured by Electroencephalography (EEG), which has several advantages to be implemented with the widely used Brain-Computer Interfaces (BCIs) technology. However, the substantial inter/intra variability of recorded data significantly influences individual skills on the achieved performance. This study explores the ability to distinguish between MI tasks and the interpretability of the brain's ability to produce elicited mental responses with improved accuracy. We develop a Deep and Wide Convolutional Neuronal Network fed by a set of topoplots extracted from the multichannel EEG data. Further, we perform a visualization technique based on gradient-based class activation maps (namely, GradCam++) at different intervals along the MI paradigm timeline to account for intra-subject variability in neural responses over time. We also cluster the dynamic spatial representation of the extracted maps across the subject set to come to a deeper understanding of MI-BCI coordination skills. According to the results obtained from the evaluated GigaScience Database of motor-evoked potentials, the developed approach enhances the physiological explanation of motor imagery in aspects such as neural synchronization between rhythms, brain lateralization, and the ability to predict the MI onset responses and their evolution during training sessions. | P59: 1 | Q59: 1 | R59: 1 | S59: 1 | T59: =SUM(Table145[[#This Row],[Relevence 0,1,0.5]:[Findings 0,1,0.5]]) -> 4
A60: Web of Science | B60: Journal Article | C60: J. E. C. G. de Oro; P. J. Koch; J. Krois; A. G. C. Ros; J. Patel; H. Meyer-Lueckel; F. Schwendicke | D60: 2022 | E60: Hyperparameter Tuning and Automatic Image Augmentation for Deep Learning-Based Angle Classification on Intraoral Photographs-A Retrospective Study | F60: DIAGNOSTICS | G60: 12 | H60: 7 | M60: 10.3390/diagnostics12071526 | O60: We aimed to assess the effects of hyperparameter tuning and automatic image augmentation for deep learning-based classification of orthodontic photographs along the Angle classes. Our dataset consisted of 605 images of Angle class I, 1038 images of class II, and 408 images of class III. We trained ResNet architectures for classification of different combinations of learning rate and batch size. For the best combination, we compared the performance of models trained with and without automatic augmentation using 10-fold cross-validation. We used GradCAM to increase explainability, which can provide heat maps containing the salient areas relevant for the classification. The best combination of hyperparameters yielded a model with an accuracy of 0.63-0.64, F1-score 0.61-0.62, sensitivity 0.59-0.65, and specificity 0.80-0.81. For all metrics, it was apparent that there was an ideal corridor of batch size and learning rate combinations; smaller learning rates were associated with higher classification performance. Overall, the performance was highest for learning rates of around 1-3 x 10(-6) and a batch size of eight, respectively. Additional automatic augmentation improved all metrics by 5-10% for all metrics. Misclassifications were most common between Angle classes I and II. GradCAM showed that the models employed features relevant for human classification, too. The choice of hyperparameters drastically affected the performance of deep learning models in orthodontics, and automatic image augmentation resulted in further improvements. Our models managed to classify the dental sagittal occlusion along Angle classes based on digital intraoral photos. | P60: 0 | Q60: 0.5 | R60: 0.5 | S60: 1 | T60: =SUM(Table145[[#This Row],[Relevence 0,1,0.5]:[Findings 0,1,0.5]]) -> 2
A61: Web of Science | B61: Journal Article | C61: V. S. Dhaka; G. Rani; M. G. Oza; T. Sharma; A. Misra | D61: 2021 | E61: A deep learning model for mass screening of COVID-19 | F61: INTERNATIONAL JOURNAL OF IMAGING SYSTEMS AND TECHNOLOGY | G61: 31 | H61: 2 | I61: 483-498 | M61: 10.1002/ima.22544 | O61: The objective of this research is to develop a convolutional neural network model 'COVID-Screen-Net' for multi-class classification of chest X-ray images into three classes viz. COVID-19, bacterial pneumonia, and normal. The model performs the automatic feature extraction from X-ray images and accurately identifies the features responsible for distinguishing the X-ray images of different classes. It plots these features on the GradCam. The authors optimized the number of convolution and activation layers according to the size of the dataset. They also fine-tuned the hyperparameters to minimize the computation time and to enhance the efficiency of the model. The performance of the model has been evaluated on the anonymous chest X-ray images collected from hospitals and the dataset available on the web. The model attains an average accuracy of 97.71% and a maximum recall of 100%. The comparative analysis shows that the 'COVID-Screen-Net' outperforms the existing systems for screening of COVID-19. The effectiveness of the model is validated by the radiology experts on the real-time dataset. Therefore, it may prove a useful tool for quick and low-cost mass screening of patients of COVID-19. This tool may reduce the burden on health experts in the present situation of the Global Pandemic. The copyright of this tool is registered in the names of authors under the laws of Intellectual Property Rights in India with the registration number 'SW-13625/2020'. | P61: 0 | Q61: 1 | R61: 0 | S61: 0.5 | T61: =SUM(Table145[[#This Row],[Relevence 0,1,0.5]:[Findings 0,1,0.5]]) -> 1.5
A62: Web of Science | B62: Journal Article | C62: A. Dhere; J. Sivaswamy | D62: 2022 | E62: COVID Detection From Chest X-Ray Images Using Multi-Scale Attention | F62: IEEE JOURNAL OF BIOMEDICAL AND HEALTH INFORMATICS | G62: 26 | H62: 4 | I62: 1496-1505 | M62: 10.1109/JBHI.2022.3151171 | O62: Deep learning based methods have shown great promise in achieving accurate automatic detection of Coronavirus Disease (covid) - 19 from Chest X-Ray (cxr) images.However, incorporating explainability in these solutions remains relatively less explored. We present a hierarchical classification approach for separating normal, non-covid pneumonia (ncp) and covid cases using cxr images. We demonstrate that the proposed method achieves clinically consistent explainations. We achieve this using a novel multi-scale attention architecture called Multi-scale Attention Residual Learning (marl) and a new loss function based on conicity for training the proposed architecture. The proposed classification strategy has two stages. The first stage uses a model derived from DenseNet to separate pneumonia cases from normal cases while the second stage uses the marl architecture to discriminate between covid and ncp cases. With a five-fold cross validation the proposed method achieves 93%, 96.28%, and 84.51% accuracy respectively over three large, public datasets for normal vs. ncp vs. covid classification. This is competitive to the state-of-the-art methods. We also provide explanations in the form of GradCAM attributions, which are well aligned with expert annotations. The attributions are also seen to clearly indicate that marl deems the peripheral regions of the lungs to be more important in the case of covid cases while central regions are seen as more important in ncp cases. This observation matches the criteria described by radiologists in clinical literature, thereby attesting to the utility of the derived explanations. | P62: 0 | Q62: 0 | R62: 0.5 | S62: 1 | T62: =SUM(Table145[[#This Row],[Relevence 0,1,0.5]:[Findings 0,1,0.5]]) -> 1.5
A63: Web of Science | B63: Journal Article | C63: E. Elfatimi; R. Eryigit; H. A. Shehu | D63: 2024 | E63: Impact of datasets on the effectiveness of MobileNet for beans leaf disease detection | F63: NEURAL COMPUTING & APPLICATIONS | G63: 36 | H63: 4 | I63: 1773-1789 | M63: 10.1007/s00521-023-09187-4 | O63: Bean is a widely cultivated crop worldwide; however, it is susceptible to various diseases that can adversely affect the quality of beans, including rust and angular leaf spot diseases. These diseases can cause significant damage by wiping out hectares of crops, emphasizing the need for early detection. Deep learning algorithms have shown remarkable performance in image detection tasks, achieving high accuracy on many datasets. This study used a deep learning technique, specifically the MobileNet architecture, to detect bean leaf disease. We evaluated the effectiveness of the approach by testing the model on three different bean leaf image datasets with varying difficulty. MobileNet was chosen due to its ability to achieve high performance with a reduced number of parameters and faster execution time. Additionally, we examined the impact of the datasets on the model's performance and presented a comparative analysis of the three datasets, and then we applied the GradCAM technique to the model's predictions. Experimental results showed that the proposed approach achieved remarkable accuracy, with over 92% accuracy on all three datasets. The study provides a valuable contribution to the field of plant disease detection and highlights the potential of deep learning techniques in detecting bean leaf disease. | P63: 0 | Q63: 0.5 | R63: 0.5 | S63: 1 | T63: =SUM(Table145[[#This Row],[Relevence 0,1,0.5]:[Findings 0,1,0.5]]) -> 2
A64: Web of Science | B64: Journal Article | C64: M. Frueh; M. Fischer; A. Schilling; S. Gatidis; T. Hepp | D64: 2021 | E64: Weakly supervised segmentation of tumor lesions in PET-CT hybrid imaging | F64: JOURNAL OF MEDICAL IMAGING | G64: 8 | H64: 5 | M64: 10.1117/1.JMI.8.5.054003 | O64: Purpose: We introduce and evaluate deep learning methods for weakly supervised segmentation of tumor lesions in whole-body fluorodeoxyglucose-positron emission tomography (FDG-PET) based solely on binary global labels (tumor" versus "no tumor").Approach: We propose a three-step approach based on (i) a deep learning framework for image classification, (ii) subsequent generation of class activation maps (CAMs) using different CAM methods (CAM, GradCAM, GradCAM++, ScoreCAM), and (iii) final tumor segmentation based on the aforementioned CAMs. A VGG-based classification neural network was trained to distinguish between PET image slices with and without FDG-avid tumor lesions. Subsequently, the CAMs of this network were used to identify the tumor regions within images. This proposed framework was applied to FDG-PET/CT data of 453 oncological patients with available manually generated ground-truth segmentations. Quantitative segmentation performance was assessed for the different CAM approaches and compared with the manual ground truth segmentation and with supervised segmentation methods. In addition, further biomarkers (MTV and TLG) were extracted from the segmentation masks.Results: A weakly supervised segmentation of tumor lesions was feasible with satisfactory performance [best median Dice score 0.47, interquartile range (IQR) 0.35] compared with a fully supervised U-Net model (median Dice score 0.72, IQR 0.36) and a simple threshold based segmentation (Dice score 0.29, IQR 0.28). CAM, GradCAM++, and ScoreCAM yielded similar results. However, GradCAM led to inferior results (median Dice score: 0.12, IQR 0.21) and was likely to ignore multiple instances within a given slice. CAM, GradCAM++, and ScoreCAM yielded accurate estimates of metabolic tumor volume (MTV) and tumor lesion glycolysis. Again, worse results were observed for GradCAM.Conclusions: This work demonstrated the feasibility of weakly supervised segmentation of tumor lesions and accurate estimation of derived metrics such as MTV and tumor lesion glycolysis. (C) The Authors. Published by SPIE under a Creative Commons Attribution 4.0 International License." | P64: 0 | Q64: 1 | R64: 0 | S64: 0.5 | T64: =SUM(Table145[[#This Row],[Relevence 0,1,0.5]:[Findings 0,1,0.5]]) -> 1.5
A65: Web of Science | B65: Journal Article | C65: P. Gulati; Q. Hu; S. F. Atashzar | D65: 2021 | E65: Toward Deep Generalization of Peripheral EMG-Based Human-Robot Interfacing: A Hybrid Explainable Solution for NeuroRobotic Systems | F65: IEEE ROBOTICS AND AUTOMATION LETTERS | G65: 6 | H65: 2 | I65: 2650-2657 | M65: 10.1109/LRA.2021.3062320 | O65: This letter investigates the feasibility of a generalizable solution for human-robot interfaces through peripheral multichannel Electromyography (EMG) recording. We propose a tangential approach in comparison to the literature to minimize the need for (re)calibration of the system for new users. The proposed algorithm decodes the signal space and detects the common underlying global neurophysiological components, which can be detected robustly across various users, minimizing the need for retraining and (re)calibration. The research question is how to go beyond techniques that detect a high number of gestures for a given individual (which requires extensive calibration) and achieve an algorithm that can detect a lower number of classes but without the need for (re)calibration. The outcomes of this letter address a challenge affecting the usability and acceptance of advanced myoelectric prostheses. For this, the paper proposes an explainable generalizable hybrid deep learning architecture that incorporates CNN and LSTM. We also utilize the GradCAM analysis to explain and optimize the structure of the generalized model, securing higher computational performance whiles proposing a shallower design. | P65: 0 | Q65: 1 | R65: 1 | S65: 1 | T65: =SUM(Table145[[#This Row],[Relevence 0,1,0.5]:[Findings 0,1,0.5]]) -> 3
A66: Web of Science | B66: Journal Article | C66: R. Guo; X. Sun; K. Chen; X. Zhou; Z. Yan; W. Diao; M. Yan | D66: 2020 | E66: JMLNet: Joint Multi-Label Learning Network for Weakly Supervised Semantic Segmentation in Aerial Images | F66: REMOTE SENSING | G66: 12 | H66: 19 | M66: 10.3390/rs12193169 | O66: Weakly supervised semantic segmentation in aerial images has attracted growing research attention due to the significant saving in annotation cost. Most of the current approaches are based on one specific pseudo label. These methods easily overfit the wrongly labeled pixels from noisy label and limit the performance and generalization of the segmentation model. To tackle these problems, we propose a novel joint multi-label learning network (JMLNet) to help the model learn common knowledge from multiple noisy labels and prevent the model from overfitting one specific label. Our combination strategy of multiple proposals is that we regard them all as ground truth and propose three new multi-label losses to use the multi-label guide segmentation model in the training process. JMLNet also contains two methods to generate high-quality proposals, which further improve the performance of the segmentation task. First we propose a detection-based GradCAM (GradCAMD) to generate segmentation proposals from object detectors. Then we use GradCAMD to adjust the GrabCut algorithm and generate segmentation proposals (GrabCutC). We report the state-of-the-art results on the semantic segmentation task of iSAID and mapping challenge dataset when training with bounding boxes annotations. | P66: 0 | Q66: 1 | R66: 0.5 | S66: 1 | T66: =SUM(Table145[[#This Row],[Relevence 0,1,0.5]:[Findings 0,1,0.5]]) -> 2.5
A67: Web of Science | B67: Journal Article | C67: A. Gupta; F. Mendonca; S. S. Mostafa; A. G. Ravelo-Garcia; F. Morgado-Dias | D67: 2023 | E67: Visual Explanations of Deep Learning Architectures in Predicting Cyclic Alternating Patterns Using Wavelet Transforms | F67: ELECTRONICS | G67: 12 | H67: 13 | M67: 10.3390/electronics12132954 | O67: Cyclic Alternating Pattern (CAP) is a sleep instability marker defined based on the amplitude and frequency of the electroencephalogram signal. Because of the time and intensive process of labeling the data, different machine learning and automatic approaches are proposed. However, due to the low accuracy of the traditional approach and the black box approach of the machine learning approach, the proposed systems remain untrusted by the physician. This study contributes to accurately estimating CAP in a Frequency-Time domain by A-phase and its subtypes prediction by transforming the monopolar deviated electroencephalogram signals into corresponding scalograms. Subsequently, various computer vision classifiers were tested for the A-phase using scalogram images. It was found that MobileNetV2 outperformed all other tested classifiers by achieving the average accuracy, sensitivity, and specificity values of 0.80, 0.75, and 0.81, respectively. The MobileNetV2 trained model was further fine-tuned for A-phase subtypes prediction. To further verify the visual ability of the trained models, Gradcam++ was employed to identify the targeted regions by the trained network. It was verified that the areas identified by the model match the regions focused on by the sleep experts for A-phase predictions, thereby proving its clinical viability and robustness. This motivates the development of novel deep learning based methods for CAP patterns predictions. | P67: 0 | Q67: 1 | R67: 1 | S67: 1 | T67: =SUM(Table145[[#This Row],[Relevence 0,1,0.5]:[Findings 0,1,0.5]]) -> 3
A68: Web of Science | B68: Journal Article | C68: K. Haciefendioglu; H. B. Basaga; Z. Yavuz; M. T. Karimi | D68: 2022 | E68: Intelligent ice detection on wind turbine blades using semantic segmentation and class activation map approaches based on deep learning method | F68: RENEWABLE ENERGY | G68: 182 | M68: 10.1016/j.renene.2021.10.025 | O68: Studying the efficacy of intelligent systems to successfully detect ice accumulation on wind turbines in cold climates has been gaining traction in recent years. In this study, both visualization and segmentation techniques were utilized in order to compare their respective results in the detection of ice on wind turbines. In pursuit of this objective, photos of wind turbines, taken under different conditions, were analyzed. To correctly classify objects automatically, pre-trained models of Resnet-50, VGG-16, VGG-19, and Inception-V3, were used. The deep learning approaches used to reliably predict the exact position of icing on wind turbine blades, including the visualization techniques Grad-CAM, Grad-CAM ++, and Score-CAM, proved to have adequate reliability with Score-CAM subsequently identified as the best visualization technique for localization. Additionally, the U-Net segmentation approach was used to delineate icing area boundaries. The U-Net approach was compared with the best visualization technique and pre-trained model to evaluate the visualization efficiency in different situations, including near and far views of a wind turbine, ice density, and light. Results showed that these methods have a high degree of accuracy in detecting ice on wind turbines. (C) 2021 Elsevier Ltd. All rights reserved. | P68: 0 | Q68: 0 | R68: 0.5 | S68: 1 | T68: =SUM(Table145[[#This Row],[Relevence 0,1,0.5]:[Findings 0,1,0.5]]) -> 1.5
